Workbook
Name gongfuKPI: '汇报-gongfu'!$Y$184
Name gongfu付费arppu: '汇报-gongfu'!$A$259
Name gongfu付费贡献组成: '汇报-gongfu'!$A$211
Name gongfu付费基本: '汇报-gongfu'!$A$118
Name gongfu付费率: '汇报-gongfu'!$A$332
Name gongfu付费用户组成: '汇报-gongfu'!$A$166
Name gongfu活跃构成: '汇报-gongfu'!$A$72
Name gongfu活跃基本: '汇报-gongfu'!$A$29
Name gongfu页首: '汇报-gongfu'!$A$1
Name gongfu游戏习惯: '汇报-gongfu'!$A$384
Name gongfu有效活跃: '汇报-gongfu'!$A$359
Name huaKPI: '汇报-hua'!$Y$182
Name hua付费arppu: '汇报-hua'!$A$256
Name hua付费贡献组成: '汇报-hua'!$A$208
Name hua付费基本: '汇报-hua'!$A$117
Name hua付费率: '汇报-hua'!$A$329
Name hua付费用户组成: '汇报-hua'!$A$164
Name hua活跃构成: '汇报-hua'!$A$71
Name hua活跃基本: '汇报-hua'!$A$30
Name hua页首: '汇报-hua'!$A$1
Name hua游戏习惯: '汇报-hua'!$A$381
Name hua有效活跃: '汇报-hua'!$A$358
Name jlKPI: '汇报-jl'!$Z$181
Name jl付费arppu: '汇报-jl'!$A$257
Name jl付费贡献组成: '汇报-jl'!$A$209
Name jl付费基本: '汇报-jl'!$A$117
Name jl付费率: '汇报-jl'!$A$330
Name jl付费用户组成: '汇报-jl'!$A$163
Name jl活跃构成: '汇报-jl'!$A$73
Name jl活跃基本: '汇报-jl'!$A$29
Name jl页首: '汇报-jl'!$A$1
Name jl游戏习惯: '汇报-jl'!$A$382
Name jl有效活跃: '汇报-jl'!$A$358
Name seer2KPI: '汇报-seer2'!$Y$185
Name seer2付费arppu: '汇报-seer2'!$A$258
Name seer2付费贡献组成: '汇报-seer2'!$A$211
Name seer2付费基本: '汇报-seer2'!$A$117
Name seer2付费率: '汇报-seer2'!$A$331
Name seer2付费用户组成: '汇报-seer2'!$A$166
Name seer2活跃构成: '汇报-seer2'!$A$73
Name seer2活跃基本: '汇报-seer2'!$A$30
Name seer2页首: '汇报-seer2'!$A$1
Name seer2游戏习惯: '汇报-seer2'!$A$384
Name seer2有效活跃: '汇报-seer2'!$A$359
Name seerKPI: '汇报-seer'!$Z$182
Name seer付费arppu: '汇报-seer'!$A$243
Name seer付费贡献组成: '汇报-seer'!$A$197
Name seer付费基本: '汇报-seer'!$A$106
Name seer付费率: '汇报-seer'!$A$316
Name seer付费用户组成: '汇报-seer'!$A$153
Name seer活跃构成: '汇报-seer'!$A$61
Name seer活跃基本: '汇报-seer'!$A$12
Name seer页首: '汇报-seer'!$A$1
Name seer游戏习惯: '汇报-seer'!$A$367
Name seer有效活跃: '汇报-seer'!$A$343
Name 创想兵团: '汇报-合作产品'!$B$26
Name 创想兵团KPI: '汇报-合作产品'!$AD$60
Name 海外产品: '汇报-合作产品'!$B$209
Name 合作产品部页首: '汇报-合作产品'!$A$1
Name 联运产品: '汇报-合作产品'!$B$125

Sheet 对比
A1: 用于比对数据中心（老）和数据分析平台（新）的月报数据，发现问题
A2: 1、 | B2: 新平台提供不含短信包月续费的包月收入
A3: 2、 | B3: 赛尔号历史转化新增付费用户的差异逐渐减小
A4: 3、 | B4: 5月前无数据的，有效活跃用户、PCU，ACU
A5: 4、 | B5: ACU，赛尔号的7,8月有问题
A6: 5、 | B6: 与活跃相关的，5月之前都有问题，最好能补全。
A7: 6、 | B7: 小花仙新平台偏小2%，原因为统计节点不同，原数据中心是偏大的，同、环比时可拿偏小值代替
BE9: =BE64/历史汇总!AY3 -> -0.00063082162
A10: 新 | B10: 旧 | BE10: =BE13/历史汇总!AY42 -> 7.6463239e-05
A11: 历史新 | B11: 历史汇总 | H11: 1 | I11: 2 | J11: 3 | K11: 4 | L11: 5 | M11: 6 | N11: 7 | O11: 8 | P11: 9 | Q11: 10 | R11: 11 | S11: 12 | T11: 13 | U11: 14 | V11: 15 | W11: 16 | X11: 17 | Y11: 18 | Z11: 19 | AA11: 20 | AB11: 21 | AC11: 22 | AD11: 23 | AE11: 24 | AF11: 25 | AG11: 26 | AH11: 27 | AI11: 28 | AJ11: 29 | AK11: 30 | AL11: 31 | AM11: 32 | AN11: 33 | AO11: 34 | AP11: 35 | AQ11: 36 | AR11: 37 | AS11: 38 | AT11: 39 | AU11: 40 | AV11: 41 | AW11: 42 | AX11: 43 | AY11: 44 | AZ11: 45 | BA11: 46 | BB11: 47 | BC11: 48 | BD11: 49 | BE11: 50 | BF11: 51
G12: 赛尔号 | H12: 2011-01 | I12: 2011-02 | J12: 2011-03 | K12: 2011-04 | L12: 2011-05 | M12: 2011-06 | N12: 2011-07 | O12: 2011-08 | P12: 2011-09 | Q12: 2011-10 | R12: 2011-11 | S12: 2011-12 | T12: 2012-01 | U12: 2012-02 | V12: 2012-03 | W12: 2012-04 | X12: 2012-05 | Y12: 2012-06 | Z12: 2012-07 | AA12: 2012-08 | AB12: 2012-09 | AC12: 2012-10 | AD12: 2012-11 | AE12: 2012-12 | AF12: 2013-01 | AG12: 2013-02 | AH12: 2013-03 | AI12: 2013-04 | AJ12: 2013-05 | AK12: 2013-06 | AL12: 2013-07 | AM12: 2013-08 | AN12: 2013-09 | AO12: 2013-10 | AP12: 2013-11 | AQ12: 2013-12 | AR12: 2014-01 | AS12: 2014-02 | AT12: 2014-03 | AU12: 2014-04 | AV12: 2014-05 | AW12: 2014-06 | AX12: 2014-07 | AY12: 2014-08 | AZ12: 2014-09 | BA12: 2014-10 | BB12: 2014-11 | BC12: 2014-12 | BD12: 2015-01 | BE12: 2015-02 | BF12: 2015-03
A13: !C | B13: !B | C13: 2 | D13: 42 | E13: =$A$11&$A$13&C13 -> 历史新!C2 | F13: =$B$11&$B$13&D13 -> 历史汇总!B42 | G13: 付费总额(元) | H13: =OFFSET(INDIRECT($E13),0,H$11)-OFFSET(INDIRECT($F13),0,H$11) -> 55480 | I13: =OFFSET(INDIRECT($E13),0,I$11)-OFFSET(INDIRECT($F13),0,I$11) -> 37630 | J13: =OFFSET(INDIRECT($E13),0,J$11)-OFFSET(INDIRECT($F13),0,J$11) -> 37720 | K13: =OFFSET(INDIRECT($E13),0,K$11)-OFFSET(INDIRECT($F13),0,K$11) -> 39680 | L13: =OFFSET(INDIRECT($E13),0,L$11)-OFFSET(INDIRECT($F13),0,L$11) -> 31590 | M13: =OFFSET(INDIRECT($E13),0,M$11)-OFFSET(INDIRECT($F13),0,M$11) -> 52070 | N13: =OFFSET(INDIRECT($E13),0,N$11)-OFFSET(INDIRECT($F13),0,N$11) -> 48180 | O13: =OFFSET(INDIRECT($E13),0,O$11)-OFFSET(INDIRECT($F13),0,O$11) -> 26230 | ... BF13: =OFFSET(INDIRECT($E13),0,BF$11)-OFFSET(INDIRECT($F13),0,BF$11) -> 8902157
C14: 3 | D14: 43 | E14: =$A$11&$A$13&C14 -> 历史新!C3 | F14: =$B$11&$B$13&D14 -> 历史汇总!B43 | G14: 付费总额(元)增长率 | H14: =OFFSET(INDIRECT($E14),0,H$11)-OFFSET(INDIRECT($F14),0,H$11) -> -0.0015 | I14: =OFFSET(INDIRECT($E14),0,I$11)-OFFSET(INDIRECT($F14),0,I$11) -> 0.0001 | J14: =OFFSET(INDIRECT($E14),0,J$11)-OFFSET(INDIRECT($F14),0,J$11) -> -0.0001 | K14: =OFFSET(INDIRECT($E14),0,K$11)-OFFSET(INDIRECT($F14),0,K$11) -> 0.0003 | L14: =OFFSET(INDIRECT($E14),0,L$11)-OFFSET(INDIRECT($F14),0,L$11) -> -0.0002 | M14: =OFFSET(INDIRECT($E14),0,M$11)-OFFSET(INDIRECT($F14),0,M$11) -> 0.0011 | N14: =OFFSET(INDIRECT($E14),0,N$11)-OFFSET(INDIRECT($F14),0,N$11) -> -0.0003 | O14: =OFFSET(INDIRECT($E14),0,O$11)-OFFSET(INDIRECT($F14),0,O$11) -> -0.0003 | ... BF14: =OFFSET(INDIRECT($E14),0,BF$11)-OFFSET(INDIRECT($F14),0,BF$11) -> -0.0815
C15: 4 | D15: 44 | E15: =$A$11&$A$13&C15 -> 历史新!C4 | F15: =$B$11&$B$13&D15 -> 历史汇总!B44 | G15: 付费用户数 | H15: =OFFSET(INDIRECT($E15),0,H$11)-OFFSET(INDIRECT($F15),0,H$11) -> 1828 | I15: =OFFSET(INDIRECT($E15),0,I$11)-OFFSET(INDIRECT($F15),0,I$11) -> 1626 | J15: =OFFSET(INDIRECT($E15),0,J$11)-OFFSET(INDIRECT($F15),0,J$11) -> 1618 | K15: =OFFSET(INDIRECT($E15),0,K$11)-OFFSET(INDIRECT($F15),0,K$11) -> 1517 | L15: =OFFSET(INDIRECT($E15),0,L$11)-OFFSET(INDIRECT($F15),0,L$11) -> 1353 | M15: =OFFSET(INDIRECT($E15),0,M$11)-OFFSET(INDIRECT($F15),0,M$11) -> 2456 | N15: =OFFSET(INDIRECT($E15),0,N$11)-OFFSET(INDIRECT($F15),0,N$11) -> 1898 | O15: =OFFSET(INDIRECT($E15),0,O$11)-OFFSET(INDIRECT($F15),0,O$11) -> 1112 | ... BF15: =OFFSET(INDIRECT($E15),0,BF$11)-OFFSET(INDIRECT($F15),0,BF$11) -> 146274
C16: 5 | D16: 45 | E16: =$A$11&$A$13&C16 -> 历史新!C5 | F16: =$B$11&$B$13&D16 -> 历史汇总!B45 | G16: 付费用户数增长率 | H16: =OFFSET(INDIRECT($E16),0,H$11)-OFFSET(INDIRECT($F16),0,H$11) -> -0.004 | I16: =OFFSET(INDIRECT($E16),0,I$11)-OFFSET(INDIRECT($F16),0,I$11) -> 0.0002 | J16: =OFFSET(INDIRECT($E16),0,J$11)-OFFSET(INDIRECT($F16),0,J$11) -> 0.0002 | K16: =OFFSET(INDIRECT($E16),0,K$11)-OFFSET(INDIRECT($F16),0,K$11) -> 0 | L16: =OFFSET(INDIRECT($E16),0,L$11)-OFFSET(INDIRECT($F16),0,L$11) -> 0 | M16: =OFFSET(INDIRECT($E16),0,M$11)-OFFSET(INDIRECT($F16),0,M$11) -> 0.002 | N16: =OFFSET(INDIRECT($E16),0,N$11)-OFFSET(INDIRECT($F16),0,N$11) -> -0.0008 | O16: =OFFSET(INDIRECT($E16),0,O$11)-OFFSET(INDIRECT($F16),0,O$11) -> -0.0007 | ... BF16: =OFFSET(INDIRECT($E16),0,BF$11)-OFFSET(INDIRECT($F16),0,BF$11) -> -0.0991
C17: 6 | D17: 56 | E17: =$A$11&$A$13&C17 -> 历史新!C6 | F17: =$B$11&$B$13&D17 -> 历史汇总!B56 | G17: arppu值 | H17: =OFFSET(INDIRECT($E17),0,H$11)-OFFSET(INDIRECT($F17),0,H$11) -> -0.0201 | I17: =OFFSET(INDIRECT($E17),0,I$11)-OFFSET(INDIRECT($F17),0,I$11) -> -0.0278 | J17: =OFFSET(INDIRECT($E17),0,J$11)-OFFSET(INDIRECT($F17),0,J$11) -> -0.0405 | K17: =OFFSET(INDIRECT($E17),0,K$11)-OFFSET(INDIRECT($F17),0,K$11) -> -0.0236 | L17: =OFFSET(INDIRECT($E17),0,L$11)-OFFSET(INDIRECT($F17),0,L$11) -> -0.0275 | M17: =OFFSET(INDIRECT($E17),0,M$11)-OFFSET(INDIRECT($F17),0,M$11) -> -0.0562 | N17: =OFFSET(INDIRECT($E17),0,N$11)-OFFSET(INDIRECT($F17),0,N$11) -> -0.0365 | O17: =OFFSET(INDIRECT($E17),0,O$11)-OFFSET(INDIRECT($F17),0,O$11) -> -0.0229 | ... BF17: =OFFSET(INDIRECT($E17),0,BF$11)-OFFSET(INDIRECT($F17),0,BF$11) -> 60.86
C18: 7 | D18: 57 | E18: =$A$11&$A$13&C18 -> 历史新!C7 | F18: =$B$11&$B$13&D18 -> 历史汇总!B57 | G18: arppu值增长率 | H18: =OFFSET(INDIRECT($E18),0,H$11)-OFFSET(INDIRECT($F18),0,H$11) -> 0.0032 | I18: =OFFSET(INDIRECT($E18),0,I$11)-OFFSET(INDIRECT($F18),0,I$11) -> -0.0002 | J18: =OFFSET(INDIRECT($E18),0,J$11)-OFFSET(INDIRECT($F18),0,J$11) -> -0.0003 | K18: =OFFSET(INDIRECT($E18),0,K$11)-OFFSET(INDIRECT($F18),0,K$11) -> 0.0004 | L18: =OFFSET(INDIRECT($E18),0,L$11)-OFFSET(INDIRECT($F18),0,L$11) -> -0.0001 | M18: =OFFSET(INDIRECT($E18),0,M$11)-OFFSET(INDIRECT($F18),0,M$11) -> -0.0009 | N18: =OFFSET(INDIRECT($E18),0,N$11)-OFFSET(INDIRECT($F18),0,N$11) -> 0.0007 | O18: =OFFSET(INDIRECT($E18),0,O$11)-OFFSET(INDIRECT($F18),0,O$11) -> 0.0002 | ... BF18: =OFFSET(INDIRECT($E18),0,BF$11)-OFFSET(INDIRECT($F18),0,BF$11) -> 0.0194
C19: 8 | D19: 59 | E19: =$A$11&$A$13&C19 -> 历史新!C8 | F19: =$B$11&$B$13&D19 -> 历史汇总!B59 | G19: 包月支付总额(不含短信包月续费) | H19: =OFFSET(INDIRECT($E19),0,H$11)-OFFSET(INDIRECT($F19),0,H$11) -> -14488650 | I19: =OFFSET(INDIRECT($E19),0,I$11)-OFFSET(INDIRECT($F19),0,I$11) -> -10755380 | J19: =OFFSET(INDIRECT($E19),0,J$11)-OFFSET(INDIRECT($F19),0,J$11) -> -7243730 | K19: =OFFSET(INDIRECT($E19),0,K$11)-OFFSET(INDIRECT($F19),0,K$11) -> -8883210 | L19: =OFFSET(INDIRECT($E19),0,L$11)-OFFSET(INDIRECT($F19),0,L$11) -> -7590000 | M19: =OFFSET(INDIRECT($E19),0,M$11)-OFFSET(INDIRECT($F19),0,M$11) -> -6791710 | N19: =OFFSET(INDIRECT($E19),0,N$11)-OFFSET(INDIRECT($F19),0,N$11) -> -6951950 | O19: =OFFSET(INDIRECT($E19),0,O$11)-OFFSET(INDIRECT($F19),0,O$11) -> -5385760 | ... BF19: =OFFSET(INDIRECT($E19),0,BF$11)-OFFSET(INDIRECT($F19),0,BF$11) -> 2024280
C20: 9 | D20: 60 | E20: =$A$11&$A$13&C20 -> 历史新!C9 | F20: =$B$11&$B$13&D20 -> 历史汇总!B60 | G20: 包月支付总额(不含短信包月续费)增长率 | H20: =OFFSET(INDIRECT($E20),0,H$11)-OFFSET(INDIRECT($F20),0,H$11) -> -0.0092 | I20: =OFFSET(INDIRECT($E20),0,I$11)-OFFSET(INDIRECT($F20),0,I$11) -> 0.2577 | J20: =OFFSET(INDIRECT($E20),0,J$11)-OFFSET(INDIRECT($F20),0,J$11) -> 0.3265 | K20: =OFFSET(INDIRECT($E20),0,K$11)-OFFSET(INDIRECT($F20),0,K$11) -> -0.2263 | L20: =OFFSET(INDIRECT($E20),0,L$11)-OFFSET(INDIRECT($F20),0,L$11) -> 0.1456 | M20: =OFFSET(INDIRECT($E20),0,M$11)-OFFSET(INDIRECT($F20),0,M$11) -> 0.1052 | N20: =OFFSET(INDIRECT($E20),0,N$11)-OFFSET(INDIRECT($F20),0,N$11) -> -0.0236 | O20: =OFFSET(INDIRECT($E20),0,O$11)-OFFSET(INDIRECT($F20),0,O$11) -> 0.2253 | ... BF20: =OFFSET(INDIRECT($E20),0,BF$11)-OFFSET(INDIRECT($F20),0,BF$11) -> 0.0805
C21: 10 | D21: 61 | E21: =$A$11&$A$13&C21 -> 历史新!C10 | F21: =$B$11&$B$13&D21 -> 历史汇总!B61 | G21: 包月支付用户数(不含短信包月续费) | H21: =OFFSET(INDIRECT($E21),0,H$11)-OFFSET(INDIRECT($F21),0,H$11) -> -706101 | I21: =OFFSET(INDIRECT($E21),0,I$11)-OFFSET(INDIRECT($F21),0,I$11) -> -567022 | J21: =OFFSET(INDIRECT($E21),0,J$11)-OFFSET(INDIRECT($F21),0,J$11) -> -449315 | K21: =OFFSET(INDIRECT($E21),0,K$11)-OFFSET(INDIRECT($F21),0,K$11) -> -446538 | L21: =OFFSET(INDIRECT($E21),0,L$11)-OFFSET(INDIRECT($F21),0,L$11) -> -395479 | M21: =OFFSET(INDIRECT($E21),0,M$11)-OFFSET(INDIRECT($F21),0,M$11) -> -411101 | N21: =OFFSET(INDIRECT($E21),0,N$11)-OFFSET(INDIRECT($F21),0,N$11) -> -398957 | O21: =OFFSET(INDIRECT($E21),0,O$11)-OFFSET(INDIRECT($F21),0,O$11) -> -317935 | ... BF21: =OFFSET(INDIRECT($E21),0,BF$11)-OFFSET(INDIRECT($F21),0,BF$11) -> 71586
C22: 11 | D22: 62 | E22: =$A$11&$A$13&C22 -> 历史新!C11 | F22: =$B$11&$B$13&D22 -> 历史汇总!B62 | G22: 包月支付用户数(不含短信包月续费)增长率 | H22: =OFFSET(INDIRECT($E22),0,H$11)-OFFSET(INDIRECT($F22),0,H$11) -> 0.1055 | I22: =OFFSET(INDIRECT($E22),0,I$11)-OFFSET(INDIRECT($F22),0,I$11) -> 0.197 | J22: =OFFSET(INDIRECT($E22),0,J$11)-OFFSET(INDIRECT($F22),0,J$11) -> 0.2076 | K22: =OFFSET(INDIRECT($E22),0,K$11)-OFFSET(INDIRECT($F22),0,K$11) -> 0.0062 | L22: =OFFSET(INDIRECT($E22),0,L$11)-OFFSET(INDIRECT($F22),0,L$11) -> 0.1143 | M22: =OFFSET(INDIRECT($E22),0,M$11)-OFFSET(INDIRECT($F22),0,M$11) -> -0.0395 | N22: =OFFSET(INDIRECT($E22),0,N$11)-OFFSET(INDIRECT($F22),0,N$11) -> 0.0295 | O22: =OFFSET(INDIRECT($E22),0,O$11)-OFFSET(INDIRECT($F22),0,O$11) -> 0.2031 | ... BF22: =OFFSET(INDIRECT($E22),0,BF$11)-OFFSET(INDIRECT($F22),0,BF$11) -> 0.0409
C23: 12 | D23: 63 | E23: =$A$11&$A$13&C23 -> 历史新!C12 | F23: =$B$11&$B$13&D23 -> 历史汇总!B63 | G23: 包月支付arppu值 | H23: =OFFSET(INDIRECT($E23),0,H$11)-OFFSET(INDIRECT($F23),0,H$11) -> -20.5192 | I23: =OFFSET(INDIRECT($E23),0,I$11)-OFFSET(INDIRECT($F23),0,I$11) -> -18.9682 | J23: =OFFSET(INDIRECT($E23),0,J$11)-OFFSET(INDIRECT($F23),0,J$11) -> -16.1217 | K23: =OFFSET(INDIRECT($E23),0,K$11)-OFFSET(INDIRECT($F23),0,K$11) -> -19.8935 | L23: =OFFSET(INDIRECT($E23),0,L$11)-OFFSET(INDIRECT($F23),0,L$11) -> -19.1919 | M23: =OFFSET(INDIRECT($E23),0,M$11)-OFFSET(INDIRECT($F23),0,M$11) -> -16.5208 | N23: =OFFSET(INDIRECT($E23),0,N$11)-OFFSET(INDIRECT($F23),0,N$11) -> -17.4253 | O23: =OFFSET(INDIRECT($E23),0,O$11)-OFFSET(INDIRECT($F23),0,O$11) -> -16.9398 | ... BF23: =OFFSET(INDIRECT($E23),0,BF$11)-OFFSET(INDIRECT($F23),0,BF$11) -> 28.28
C24: 13 | D24: 64 | E24: =$A$11&$A$13&C24 -> 历史新!C13 | F24: =$B$11&$B$13&D24 -> 历史汇总!B64 | G24: 包月支付arppu值增长率 | H24: =OFFSET(INDIRECT($E24),0,H$11)-OFFSET(INDIRECT($F24),0,H$11) -> -0.1283 | I24: =OFFSET(INDIRECT($E24),0,I$11)-OFFSET(INDIRECT($F24),0,I$11) -> 0.0756 | J24: =OFFSET(INDIRECT($E24),0,J$11)-OFFSET(INDIRECT($F24),0,J$11) -> 0.1501 | K24: =OFFSET(INDIRECT($E24),0,K$11)-OFFSET(INDIRECT($F24),0,K$11) -> -0.234 | L24: =OFFSET(INDIRECT($E24),0,L$11)-OFFSET(INDIRECT($F24),0,L$11) -> 0.0353 | M24: =OFFSET(INDIRECT($E24),0,M$11)-OFFSET(INDIRECT($F24),0,M$11) -> 0.1392 | N24: =OFFSET(INDIRECT($E24),0,N$11)-OFFSET(INDIRECT($F24),0,N$11) -> -0.0547 | O24: =OFFSET(INDIRECT($E24),0,O$11)-OFFSET(INDIRECT($F24),0,O$11) -> 0.0279 | ... BF24: =OFFSET(INDIRECT($E24),0,BF$11)-OFFSET(INDIRECT($F24),0,BF$11) -> 0.0382
C25: 14 | D25: 66 | E25: =$A$11&$A$13&C25 -> 历史新!C14 | F25: =$B$11&$B$13&D25 -> 历史汇总!B66 | G25: 按条支付总额 | H25: =OFFSET(INDIRECT($E25),0,H$11)-OFFSET(INDIRECT($F25),0,H$11) -> 0 | I25: =OFFSET(INDIRECT($E25),0,I$11)-OFFSET(INDIRECT($F25),0,I$11) -> 0 | J25: =OFFSET(INDIRECT($E25),0,J$11)-OFFSET(INDIRECT($F25),0,J$11) -> 0 | K25: =OFFSET(INDIRECT($E25),0,K$11)-OFFSET(INDIRECT($F25),0,K$11) -> 0 | L25: =OFFSET(INDIRECT($E25),0,L$11)-OFFSET(INDIRECT($F25),0,L$11) -> 0 | M25: =OFFSET(INDIRECT($E25),0,M$11)-OFFSET(INDIRECT($F25),0,M$11) -> 0 | N25: =OFFSET(INDIRECT($E25),0,N$11)-OFFSET(INDIRECT($F25),0,N$11) -> 0 | O25: =OFFSET(INDIRECT($E25),0,O$11)-OFFSET(INDIRECT($F25),0,O$11) -> 0 | ... BF25: =OFFSET(INDIRECT($E25),0,BF$11)-OFFSET(INDIRECT($F25),0,BF$11) -> 6683807
... C34: 23 | D34: 49 | E34: =$A$11&$A$13&C34 -> 历史新!C23 | F34: =$B$11&$B$13&D34 -> 历史汇总!B49 | G34: 回流付费用户数 | H34: =OFFSET(INDIRECT($E34),0,H$11)-OFFSET(INDIRECT($F34),0,H$11) -> -1912 | I34: =OFFSET(INDIRECT($E34),0,I$11)-OFFSET(INDIRECT($F34),0,I$11) -> -212 | J34: =OFFSET(INDIRECT($E34),0,J$11)-OFFSET(INDIRECT($F34),0,J$11) -> -142 | K34: =OFFSET(INDIRECT($E34),0,K$11)-OFFSET(INDIRECT($F34),0,K$11) -> -218 | L34: =OFFSET(INDIRECT($E34),0,L$11)-OFFSET(INDIRECT($F34),0,L$11) -> -113 | M34: =OFFSET(INDIRECT($E34),0,M$11)-OFFSET(INDIRECT($F34),0,M$11) -> 323 | N34: =OFFSET(INDIRECT($E34),0,N$11)-OFFSET(INDIRECT($F34),0,N$11) -> -396 | O34: =OFFSET(INDIRECT($E34),0,O$11)-OFFSET(INDIRECT($F34),0,O$11) -> -321 | ... BF34: =OFFSET(INDIRECT($E34),0,BF$11)-OFFSET(INDIRECT($F34),0,BF$11) -> 38913
C35: 24 | G35: 新增用户中的付费用户数
C36: 25 | G36: 留存用户中的付费用户数
C37: 26 | G37: 回流用户中的付费用户数
C38: 27 | G38: 付费率
C39: 28 | G39: 付费率增长率
C40: 29 | G40: 新增用户付费率
C41: 30 | G41: 留存用户付费率
C42: 31 | G42: 回流用户付费率
C43: 32 | D43: 50 | E43: =$A$11&$A$13&C43 -> 历史新!C32 | F43: =$B$11&$B$13&D43 -> 历史汇总!B50 | G43: 纯新增付费用户占比 | H43: =OFFSET(INDIRECT($E43),0,H$11)-OFFSET(INDIRECT($F43),0,H$11) -> 0.0017 | I43: =OFFSET(INDIRECT($E43),0,I$11)-OFFSET(INDIRECT($F43),0,I$11) -> 0.0009 | J43: =OFFSET(INDIRECT($E43),0,J$11)-OFFSET(INDIRECT($F43),0,J$11) -> 0.0033 | K43: =OFFSET(INDIRECT($E43),0,K$11)-OFFSET(INDIRECT($F43),0,K$11) -> 0.0008 | L43: =OFFSET(INDIRECT($E43),0,L$11)-OFFSET(INDIRECT($F43),0,L$11) -> 0.0008 | M43: =OFFSET(INDIRECT($E43),0,M$11)-OFFSET(INDIRECT($F43),0,M$11) -> 0.0015 | N43: =OFFSET(INDIRECT($E43),0,N$11)-OFFSET(INDIRECT($F43),0,N$11) -> 0.0013 | O43: =OFFSET(INDIRECT($E43),0,O$11)-OFFSET(INDIRECT($F43),0,O$11) -> 0.0007 | ... BF43: =OFFSET(INDIRECT($E43),0,BF$11)-OFFSET(INDIRECT($F43),0,BF$11) -> 0.1379
C44: 33 | D44: 51 | E44: =$A$11&$A$13&C44 -> 历史新!C33 | F44: =$B$11&$B$13&D44 -> 历史汇总!B51 | G44: 历史转化新增付费用户占比 | H44: =OFFSET(INDIRECT($E44),0,H$11)-OFFSET(INDIRECT($F44),0,H$11) -> -0.0034 | I44: =OFFSET(INDIRECT($E44),0,I$11)-OFFSET(INDIRECT($F44),0,I$11) -> -0.0014 | J44: =OFFSET(INDIRECT($E44),0,J$11)-OFFSET(INDIRECT($F44),0,J$11) -> -0.0038 | K44: =OFFSET(INDIRECT($E44),0,K$11)-OFFSET(INDIRECT($F44),0,K$11) -> -0.0011 | L44: =OFFSET(INDIRECT($E44),0,L$11)-OFFSET(INDIRECT($F44),0,L$11) -> -0.0011 | M44: =OFFSET(INDIRECT($E44),0,M$11)-OFFSET(INDIRECT($F44),0,M$11) -> -0.0011 | N44: =OFFSET(INDIRECT($E44),0,N$11)-OFFSET(INDIRECT($F44),0,N$11) -> -0.002 | O44: =OFFSET(INDIRECT($E44),0,O$11)-OFFSET(INDIRECT($F44),0,O$11) -> -0.002 | ... BF44: =OFFSET(INDIRECT($E44),0,BF$11)-OFFSET(INDIRECT($F44),0,BF$11) -> 0.1735
C45: 34 | D45: 52 | E45: =$A$11&$A$13&C45 -> 历史新!C34 | F45: =$B$11&$B$13&D45 -> 历史汇总!B52 | G45: 连续两月付费用户占比 | H45: =OFFSET(INDIRECT($E45),0,H$11)-OFFSET(INDIRECT($F45),0,H$11) -> 0.0043 | I45: =OFFSET(INDIRECT($E45),0,I$11)-OFFSET(INDIRECT($F45),0,I$11) -> 0.0013 | J45: =OFFSET(INDIRECT($E45),0,J$11)-OFFSET(INDIRECT($F45),0,J$11) -> 0.0013 | K45: =OFFSET(INDIRECT($E45),0,K$11)-OFFSET(INDIRECT($F45),0,K$11) -> 0.0013 | L45: =OFFSET(INDIRECT($E45),0,L$11)-OFFSET(INDIRECT($F45),0,L$11) -> 0.0013 | M45: =OFFSET(INDIRECT($E45),0,M$11)-OFFSET(INDIRECT($F45),0,M$11) -> 0.0006 | N45: =OFFSET(INDIRECT($E45),0,N$11)-OFFSET(INDIRECT($F45),0,N$11) -> 0.0026 | O45: =OFFSET(INDIRECT($E45),0,O$11)-OFFSET(INDIRECT($F45),0,O$11) -> 0.0029 | ... BF45: =OFFSET(INDIRECT($E45),0,BF$11)-OFFSET(INDIRECT($F45),0,BF$11) -> 0.4358
C46: 35 | D46: 53 | E46: =$A$11&$A$13&C46 -> 历史新!C35 | F46: =$B$11&$B$13&D46 -> 历史汇总!B53 | G46: 回流付费用户占比 | H46: =OFFSET(INDIRECT($E46),0,H$11)-OFFSET(INDIRECT($F46),0,H$11) -> -0.0026 | I46: =OFFSET(INDIRECT($E46),0,I$11)-OFFSET(INDIRECT($F46),0,I$11) -> -0.0009 | J46: =OFFSET(INDIRECT($E46),0,J$11)-OFFSET(INDIRECT($F46),0,J$11) -> -0.001 | K46: =OFFSET(INDIRECT($E46),0,K$11)-OFFSET(INDIRECT($F46),0,K$11) -> -0.0011 | L46: =OFFSET(INDIRECT($E46),0,L$11)-OFFSET(INDIRECT($F46),0,L$11) -> -0.0009 | M46: =OFFSET(INDIRECT($E46),0,M$11)-OFFSET(INDIRECT($F46),0,M$11) -> -0.001 | N46: =OFFSET(INDIRECT($E46),0,N$11)-OFFSET(INDIRECT($F46),0,N$11) -> -0.002 | O46: =OFFSET(INDIRECT($E46),0,O$11)-OFFSET(INDIRECT($F46),0,O$11) -> -0.0016 | ... BF46: =OFFSET(INDIRECT($E46),0,BF$11)-OFFSET(INDIRECT($F46),0,BF$11) -> 0.266
C47: 36 | G47: 纯新增付费用户付费额
C48: 37 | G48: 历史转化新增付费用户付费额
C49: 38 | G49: 连续两月付费用户付费额
C50: 39 | G50: 回流付费用户付费额
C51: 40 | G51: 新增用户付费额
C52: 41 | G52: 留存用户付费额
C53: 42 | G53: 回流用户付费额
C54: 43 | G54: 纯新增付费用户ARPPU值
C55: 44 | G55: 历史转化新增付费用户ARPPU值
C56: 45 | G56: 连续两月付费用户ARPPU值
C57: 46 | G57: 回流付费用户ARPPU值
C58: 47 | G58: 新增用户ARPPU值
... C60: 49 | G60: 回流用户ARPPU值
AT62: 0 | AU62: 1 | AV62: 2 | AW62: 3 | AX62: 4 | AY62: 5 | AZ62: 6 | BA62: 7 | BB62: 8 | BC62: 9 | BD62: 10 | BE62: 11 | BF62: 12
G63: 赛尔号 | H63: 2011-01 | I63: 2011-02 | J63: 2011-03 | K63: 2011-04 | L63: 2011-05 | M63: 2011-06 | N63: 2011-07 | O63: 2011-08 | P63: 2011-09 | Q63: 2011-10 | R63: 2011-11 | S63: 2011-12 | T63: 2012-01 | U63: 2012-02 | V63: 2012-03 | W63: 2012-04 | X63: 2012-05 | Y63: 2012-06 | Z63: 2012-07 | AA63: 2012-08 | AB63: 2012-09 | AC63: 2012-10 | AD63: 2012-11 | AE63: 2012-12 | AF63: 2013-01 | AG63: 2013-02 | AH63: 2013-03 | AI63: 2013-04 | AJ63: 2013-05 | AK63: 2013-06 | AL63: 2013-07 | AM63: 2013-08 | AN63: 2013-09 | AO63: 2013-10 | AP63: 2013-11 | AQ63: 2013-12 | AR63: 2014-01 | AS63: 2014-02 | AT63: 2014-03 | AU63: 2014-04 | AV63: 2014-05 | AW63: 2014-06 | AX63: 2014-07 | AY63: 2014-08 | AZ63: 2014-09 | BA63: 2014-10 | BB63: 2014-11 | BC63: 2014-12 | BD63: 2015-01 | BE63: 2015-02 | BF63: 2015-03
C64: 53 | D64: 3 | E64: =$A$11&$A$13&C64 -> 历史新!C53 | F64: =$B$11&$B$13&D64 -> 历史汇总!B3 | G64: 活跃用户 | H64: =OFFSET(INDIRECT($E64),0,H$11)-OFFSET(INDIRECT($F64),0,H$11) -> 0 | I64: =OFFSET(INDIRECT($E64),0,I$11)-OFFSET(INDIRECT($F64),0,I$11) -> 0 | J64: =OFFSET(INDIRECT($E64),0,J$11)-OFFSET(INDIRECT($F64),0,J$11) -> 0 | K64: =OFFSET(INDIRECT($E64),0,K$11)-OFFSET(INDIRECT($F64),0,K$11) -> 0 | L64: =OFFSET(INDIRECT($E64),0,L$11)-OFFSET(INDIRECT($F64),0,L$11) -> 0 | M64: =OFFSET(INDIRECT($E64),0,M$11)-OFFSET(INDIRECT($F64),0,M$11) -> 0 | N64: =OFFSET(INDIRECT($E64),0,N$11)-OFFSET(INDIRECT($F64),0,N$11) -> 0 | O64: =OFFSET(INDIRECT($E64),0,O$11)-OFFSET(INDIRECT($F64),0,O$11) -> 0 | ... BF64: =OFFSET(INDIRECT($E64),0,BF$11)-OFFSET(INDIRECT($F64),0,BF$11) -> 5839002
C65: 54 | D65: 4 | E65: =$A$11&$A$13&C65 -> 历史新!C54 | F65: =$B$11&$B$13&D65 -> 历史汇总!B4 | G65: 活跃用户增长率 | H65: =OFFSET(INDIRECT($E65),0,H$11)-OFFSET(INDIRECT($F65),0,H$11) -> 0 | I65: =OFFSET(INDIRECT($E65),0,I$11)-OFFSET(INDIRECT($F65),0,I$11) -> 0 | J65: =OFFSET(INDIRECT($E65),0,J$11)-OFFSET(INDIRECT($F65),0,J$11) -> 0 | K65: =OFFSET(INDIRECT($E65),0,K$11)-OFFSET(INDIRECT($F65),0,K$11) -> 0 | L65: =OFFSET(INDIRECT($E65),0,L$11)-OFFSET(INDIRECT($F65),0,L$11) -> 0 | M65: =OFFSET(INDIRECT($E65),0,M$11)-OFFSET(INDIRECT($F65),0,M$11) -> 0 | N65: =OFFSET(INDIRECT($E65),0,N$11)-OFFSET(INDIRECT($F65),0,N$11) -> 0 | O65: =OFFSET(INDIRECT($E65),0,O$11)-OFFSET(INDIRECT($F65),0,O$11) -> 0 | ... BF65: =OFFSET(INDIRECT($E65),0,BF$11)-OFFSET(INDIRECT($F65),0,BF$11) -> 0.0301
C66: 55 | D66: 5 | E66: =$A$11&$A$13&C66 -> 历史新!C55 | F66: =$B$11&$B$13&D66 -> 历史汇总!B5 | G66: 有效活跃用户 | H66: =OFFSET(INDIRECT($E66),0,H$11)-OFFSET(INDIRECT($F66),0,H$11) -> -6015987 | I66: =OFFSET(INDIRECT($E66),0,I$11)-OFFSET(INDIRECT($F66),0,I$11) -> -4729044 | J66: =OFFSET(INDIRECT($E66),0,J$11)-OFFSET(INDIRECT($F66),0,J$11) -> -4816678 | K66: =OFFSET(INDIRECT($E66),0,K$11)-OFFSET(INDIRECT($F66),0,K$11) -> -4523249 | L66: =OFFSET(INDIRECT($E66),0,L$11)-OFFSET(INDIRECT($F66),0,L$11) -> -4370334 | M66: =OFFSET(INDIRECT($E66),0,M$11)-OFFSET(INDIRECT($F66),0,M$11) -> -5247085 | N66: =OFFSET(INDIRECT($E66),0,N$11)-OFFSET(INDIRECT($F66),0,N$11) -> -5061189 | O66: =OFFSET(INDIRECT($E66),0,O$11)-OFFSET(INDIRECT($F66),0,O$11) -> -3893732 | ... BF66: =OFFSET(INDIRECT($E66),0,BF$11)-OFFSET(INDIRECT($F66),0,BF$11) -> 2380117
C67: 56 | D67: 6 | E67: =$A$11&$A$13&C67 -> 历史新!C56 | F67: =$B$11&$B$13&D67 -> 历史汇总!B6 | G67: 有效活跃用户增长率 | H67: =OFFSET(INDIRECT($E67),0,H$11)-OFFSET(INDIRECT($F67),0,H$11) -> 0 | I67: =OFFSET(INDIRECT($E67),0,I$11)-OFFSET(INDIRECT($F67),0,I$11) -> 0.2139 | J67: =OFFSET(INDIRECT($E67),0,J$11)-OFFSET(INDIRECT($F67),0,J$11) -> -0.0185 | K67: =OFFSET(INDIRECT($E67),0,K$11)-OFFSET(INDIRECT($F67),0,K$11) -> 0.0609 | L67: =OFFSET(INDIRECT($E67),0,L$11)-OFFSET(INDIRECT($F67),0,L$11) -> 0.0338 | M67: =OFFSET(INDIRECT($E67),0,M$11)-OFFSET(INDIRECT($F67),0,M$11) -> -0.2006 | N67: =OFFSET(INDIRECT($E67),0,N$11)-OFFSET(INDIRECT($F67),0,N$11) -> 0.0354 | O67: =OFFSET(INDIRECT($E67),0,O$11)-OFFSET(INDIRECT($F67),0,O$11) -> 0.2307 | ... BF67: =OFFSET(INDIRECT($E67),0,BF$11)-OFFSET(INDIRECT($F67),0,BF$11) -> 0.0581
C68: 57 | D68: 12 | E68: =$A$11&$A$13&C68 -> 历史新!C57 | F68: =$B$11&$B$13&D68 -> 历史汇总!B12 | G68: 新增活跃用户 | H68: =OFFSET(INDIRECT($E68),0,H$11)-OFFSET(INDIRECT($F68),0,H$11) -> 69650 | I68: =OFFSET(INDIRECT($E68),0,I$11)-OFFSET(INDIRECT($F68),0,I$11) -> 31793 | J68: =OFFSET(INDIRECT($E68),0,J$11)-OFFSET(INDIRECT($F68),0,J$11) -> 131799 | K68: =OFFSET(INDIRECT($E68),0,K$11)-OFFSET(INDIRECT($F68),0,K$11) -> 26169 | L68: =OFFSET(INDIRECT($E68),0,L$11)-OFFSET(INDIRECT($F68),0,L$11) -> 22761 | M68: =OFFSET(INDIRECT($E68),0,M$11)-OFFSET(INDIRECT($F68),0,M$11) -> 36540 | N68: =OFFSET(INDIRECT($E68),0,N$11)-OFFSET(INDIRECT($F68),0,N$11) -> 35049 | O68: =OFFSET(INDIRECT($E68),0,O$11)-OFFSET(INDIRECT($F68),0,O$11) -> 19450 | ... BF68: =OFFSET(INDIRECT($E68),0,BF$11)-OFFSET(INDIRECT($F68),0,BF$11) -> 2799943
C69: 58 | D69: 13 | E69: =$A$11&$A$13&C69 -> 历史新!C58 | F69: =$B$11&$B$13&D69 -> 历史汇总!B13 | G69: 新增活跃用户增长率 | H69: =OFFSET(INDIRECT($E69),0,H$11)-OFFSET(INDIRECT($F69),0,H$11) -> -0.0031 | I69: =OFFSET(INDIRECT($E69),0,I$11)-OFFSET(INDIRECT($F69),0,I$11) -> -0.006 | J69: =OFFSET(INDIRECT($E69),0,J$11)-OFFSET(INDIRECT($F69),0,J$11) -> 0.0579 | K69: =OFFSET(INDIRECT($E69),0,K$11)-OFFSET(INDIRECT($F69),0,K$11) -> -0.0474 | L69: =OFFSET(INDIRECT($E69),0,L$11)-OFFSET(INDIRECT($F69),0,L$11) -> -0.0028 | M69: =OFFSET(INDIRECT($E69),0,M$11)-OFFSET(INDIRECT($F69),0,M$11) -> 0.001 | N69: =OFFSET(INDIRECT($E69),0,N$11)-OFFSET(INDIRECT($F69),0,N$11) -> -0.0024 | O69: =OFFSET(INDIRECT($E69),0,O$11)-OFFSET(INDIRECT($F69),0,O$11) -> -0.0017 | ... BF69: =OFFSET(INDIRECT($E69),0,BF$11)-OFFSET(INDIRECT($F69),0,BF$11) -> -0.0103
C70: 59 | D70: 14 | E70: =$A$11&$A$13&C70 -> 历史新!C59 | F70: =$B$11&$B$13&D70 -> 历史汇总!B14 | G70: 留存用户 | H70: =OFFSET(INDIRECT($E70),0,H$11)-OFFSET(INDIRECT($F70),0,H$11) -> 0 | I70: =OFFSET(INDIRECT($E70),0,I$11)-OFFSET(INDIRECT($F70),0,I$11) -> 0 | J70: =OFFSET(INDIRECT($E70),0,J$11)-OFFSET(INDIRECT($F70),0,J$11) -> 0 | K70: =OFFSET(INDIRECT($E70),0,K$11)-OFFSET(INDIRECT($F70),0,K$11) -> 0 | L70: =OFFSET(INDIRECT($E70),0,L$11)-OFFSET(INDIRECT($F70),0,L$11) -> 0 | M70: =OFFSET(INDIRECT($E70),0,M$11)-OFFSET(INDIRECT($F70),0,M$11) -> 0 | N70: =OFFSET(INDIRECT($E70),0,N$11)-OFFSET(INDIRECT($F70),0,N$11) -> 0 | O70: =OFFSET(INDIRECT($E70),0,O$11)-OFFSET(INDIRECT($F70),0,O$11) -> 0 | ... BF70: =OFFSET(INDIRECT($E70),0,BF$11)-OFFSET(INDIRECT($F70),0,BF$11) -> 2072959
C71: 60 | D71: 15 | E71: =$A$11&$A$13&C71 -> 历史新!C60 | F71: =$B$11&$B$13&D71 -> 历史汇总!B15 | G71: 留存用户增长率 | H71: =OFFSET(INDIRECT($E71),0,H$11)-OFFSET(INDIRECT($F71),0,H$11) -> 0 | I71: =OFFSET(INDIRECT($E71),0,I$11)-OFFSET(INDIRECT($F71),0,I$11) -> 0 | J71: =OFFSET(INDIRECT($E71),0,J$11)-OFFSET(INDIRECT($F71),0,J$11) -> 0 | K71: =OFFSET(INDIRECT($E71),0,K$11)-OFFSET(INDIRECT($F71),0,K$11) -> 0 | L71: =OFFSET(INDIRECT($E71),0,L$11)-OFFSET(INDIRECT($F71),0,L$11) -> 0 | M71: =OFFSET(INDIRECT($E71),0,M$11)-OFFSET(INDIRECT($F71),0,M$11) -> 0 | N71: =OFFSET(INDIRECT($E71),0,N$11)-OFFSET(INDIRECT($F71),0,N$11) -> 0 | O71: =OFFSET(INDIRECT($E71),0,O$11)-OFFSET(INDIRECT($F71),0,O$11) -> 0 | ... BF71: =OFFSET(INDIRECT($E71),0,BF$11)-OFFSET(INDIRECT($F71),0,BF$11) -> 0.0232
C72: 61 | D72: 16 | E72: =$A$11&$A$13&C72 -> 历史新!C61 | F72: =$B$11&$B$13&D72 -> 历史汇总!B16 | G72: 回流用户 | H72: =OFFSET(INDIRECT($E72),0,H$11)-OFFSET(INDIRECT($F72),0,H$11) -> -69650 | I72: =OFFSET(INDIRECT($E72),0,I$11)-OFFSET(INDIRECT($F72),0,I$11) -> -31793 | J72: =OFFSET(INDIRECT($E72),0,J$11)-OFFSET(INDIRECT($F72),0,J$11) -> -131799 | K72: =OFFSET(INDIRECT($E72),0,K$11)-OFFSET(INDIRECT($F72),0,K$11) -> -26169 | L72: =OFFSET(INDIRECT($E72),0,L$11)-OFFSET(INDIRECT($F72),0,L$11) -> -22761 | M72: =OFFSET(INDIRECT($E72),0,M$11)-OFFSET(INDIRECT($F72),0,M$11) -> -36541 | N72: =OFFSET(INDIRECT($E72),0,N$11)-OFFSET(INDIRECT($F72),0,N$11) -> -35049 | O72: =OFFSET(INDIRECT($E72),0,O$11)-OFFSET(INDIRECT($F72),0,O$11) -> -19450 | ... BF72: =OFFSET(INDIRECT($E72),0,BF$11)-OFFSET(INDIRECT($F72),0,BF$11) -> 966100
C73: 62 | D73: 17 | E73: =$A$11&$A$13&C73 -> 历史新!C62 | F73: =$B$11&$B$13&D73 -> 历史汇总!B17 | G73: 回流用户增长率 | H73: =OFFSET(INDIRECT($E73),0,H$11)-OFFSET(INDIRECT($F73),0,H$11) -> -0.0048 | I73: =OFFSET(INDIRECT($E73),0,I$11)-OFFSET(INDIRECT($F73),0,I$11) -> 0.0247 | J73: =OFFSET(INDIRECT($E73),0,J$11)-OFFSET(INDIRECT($F73),0,J$11) -> -0.1023 | K73: =OFFSET(INDIRECT($E73),0,K$11)-OFFSET(INDIRECT($F73),0,K$11) -> 0.0673 | L73: =OFFSET(INDIRECT($E73),0,L$11)-OFFSET(INDIRECT($F73),0,L$11) -> 0.0077 | M73: =OFFSET(INDIRECT($E73),0,M$11)-OFFSET(INDIRECT($F73),0,M$11) -> -0.0056 | N73: =OFFSET(INDIRECT($E73),0,N$11)-OFFSET(INDIRECT($F73),0,N$11) -> -0.0061 | O73: =OFFSET(INDIRECT($E73),0,O$11)-OFFSET(INDIRECT($F73),0,O$11) -> 0.008 | ... BF73: =OFFSET(INDIRECT($E73),0,BF$11)-OFFSET(INDIRECT($F73),0,BF$11) -> 0.1872
C74: 63 | D74: 7 | E74: =$A$11&$A$13&C74 -> 历史新!C63 | F74: =$B$11&$B$13&D74 -> 历史汇总!B7 | G74: 新增活跃用户占比 | H74: =OFFSET(INDIRECT($E74),0,H$11)-OFFSET(INDIRECT($F74),0,H$11) -> 0.0071 | I74: =OFFSET(INDIRECT($E74),0,I$11)-OFFSET(INDIRECT($F74),0,I$11) -> 0.0039 | J74: =OFFSET(INDIRECT($E74),0,J$11)-OFFSET(INDIRECT($F74),0,J$11) -> 0.0159 | K74: =OFFSET(INDIRECT($E74),0,K$11)-OFFSET(INDIRECT($F74),0,K$11) -> 0.0034 | L74: =OFFSET(INDIRECT($E74),0,L$11)-OFFSET(INDIRECT($F74),0,L$11) -> 0.003 | M74: =OFFSET(INDIRECT($E74),0,M$11)-OFFSET(INDIRECT($F74),0,M$11) -> 0.0041 | N74: =OFFSET(INDIRECT($E74),0,N$11)-OFFSET(INDIRECT($F74),0,N$11) -> 0.0039 | O74: =OFFSET(INDIRECT($E74),0,O$11)-OFFSET(INDIRECT($F74),0,O$11) -> 0.0027 | ... BF74: =OFFSET(INDIRECT($E74),0,BF$11)-OFFSET(INDIRECT($F74),0,BF$11) -> 0.4795
C75: 64 | D75: 8 | E75: =$A$11&$A$13&C75 -> 历史新!C64 | F75: =$B$11&$B$13&D75 -> 历史汇总!B8 | G75: 留存用户占比 | H75: =OFFSET(INDIRECT($E75),0,H$11)-OFFSET(INDIRECT($F75),0,H$11) -> 0 | I75: =OFFSET(INDIRECT($E75),0,I$11)-OFFSET(INDIRECT($F75),0,I$11) -> 0 | J75: =OFFSET(INDIRECT($E75),0,J$11)-OFFSET(INDIRECT($F75),0,J$11) -> 0 | K75: =OFFSET(INDIRECT($E75),0,K$11)-OFFSET(INDIRECT($F75),0,K$11) -> 0 | L75: =OFFSET(INDIRECT($E75),0,L$11)-OFFSET(INDIRECT($F75),0,L$11) -> 0 | M75: =OFFSET(INDIRECT($E75),0,M$11)-OFFSET(INDIRECT($F75),0,M$11) -> 0 | N75: =OFFSET(INDIRECT($E75),0,N$11)-OFFSET(INDIRECT($F75),0,N$11) -> 0 | O75: =OFFSET(INDIRECT($E75),0,O$11)-OFFSET(INDIRECT($F75),0,O$11) -> 0 | ... BF75: =OFFSET(INDIRECT($E75),0,BF$11)-OFFSET(INDIRECT($F75),0,BF$11) -> 0.355
... C82: 71 | D82: 20 | E82: =$A$11&$A$13&C82 -> 历史新!C71 | F82: =$B$11&$B$13&D82 -> 历史汇总!B20 | G82: 流失率 | H82: =OFFSET(INDIRECT($E82),0,H$11)-OFFSET(INDIRECT($F82),0,H$11) -> 0 | I82: =OFFSET(INDIRECT($E82),0,I$11)-OFFSET(INDIRECT($F82),0,I$11) -> 0 | J82: =OFFSET(INDIRECT($E82),0,J$11)-OFFSET(INDIRECT($F82),0,J$11) -> 0 | K82: =OFFSET(INDIRECT($E82),0,K$11)-OFFSET(INDIRECT($F82),0,K$11) -> 0 | L82: =OFFSET(INDIRECT($E82),0,L$11)-OFFSET(INDIRECT($F82),0,L$11) -> 0 | M82: =OFFSET(INDIRECT($E82),0,M$11)-OFFSET(INDIRECT($F82),0,M$11) -> 0 | N82: =OFFSET(INDIRECT($E82),0,N$11)-OFFSET(INDIRECT($F82),0,N$11) -> 0 | O82: =OFFSET(INDIRECT($E82),0,O$11)-OFFSET(INDIRECT($F82),0,O$11) -> 0 | ... BF82: =OFFSET(INDIRECT($E82),0,BF$11)-OFFSET(INDIRECT($F82),0,BF$11) -> 0.6343
C83: 72 | G83: 上月新增活跃用户本月流失率
C84: 73 | G84: 上月留存用户本月流失率
C85: 74 | G85: 上月回流用户本月流失率
C86: 75 | D86: 28 | E86: =$A$11&$A$13&C86 -> 历史新!C75 | F86: =$B$11&$B$13&D86 -> 历史汇总!B28 | G86: PCU | H86: =OFFSET(INDIRECT($E86),0,H$11)-OFFSET(INDIRECT($F86),0,H$11) -> -315843 | I86: =OFFSET(INDIRECT($E86),0,I$11)-OFFSET(INDIRECT($F86),0,I$11) -> -282440 | J86: =OFFSET(INDIRECT($E86),0,J$11)-OFFSET(INDIRECT($F86),0,J$11) -> -257814 | K86: =OFFSET(INDIRECT($E86),0,K$11)-OFFSET(INDIRECT($F86),0,K$11) -> -236282 | L86: =OFFSET(INDIRECT($E86),0,L$11)-OFFSET(INDIRECT($F86),0,L$11) -> -195304 | M86: =OFFSET(INDIRECT($E86),0,M$11)-OFFSET(INDIRECT($F86),0,M$11) -> -170131 | N86: =OFFSET(INDIRECT($E86),0,N$11)-OFFSET(INDIRECT($F86),0,N$11) -> -213757 | O86: =OFFSET(INDIRECT($E86),0,O$11)-OFFSET(INDIRECT($F86),0,O$11) -> -205567 | ... BF86: =OFFSET(INDIRECT($E86),0,BF$11)-OFFSET(INDIRECT($F86),0,BF$11) -> 93167
C87: 76 | D87: 29 | E87: =$A$11&$A$13&C87 -> 历史新!C76 | F87: =$B$11&$B$13&D87 -> 历史汇总!B29 | G87: PCU增长率 | H87: =OFFSET(INDIRECT($E87),0,H$11)-OFFSET(INDIRECT($F87),0,H$11) -> 0.0747 | I87: =OFFSET(INDIRECT($E87),0,I$11)-OFFSET(INDIRECT($F87),0,I$11) -> 0.1058 | J87: =OFFSET(INDIRECT($E87),0,J$11)-OFFSET(INDIRECT($F87),0,J$11) -> 0.0872 | K87: =OFFSET(INDIRECT($E87),0,K$11)-OFFSET(INDIRECT($F87),0,K$11) -> 0.0835 | L87: =OFFSET(INDIRECT($E87),0,L$11)-OFFSET(INDIRECT($F87),0,L$11) -> 0.1734 | M87: =OFFSET(INDIRECT($E87),0,M$11)-OFFSET(INDIRECT($F87),0,M$11) -> 0.1289 | N87: =OFFSET(INDIRECT($E87),0,N$11)-OFFSET(INDIRECT($F87),0,N$11) -> -0.2564 | O87: =OFFSET(INDIRECT($E87),0,O$11)-OFFSET(INDIRECT($F87),0,O$11) -> 0.0383 | ... BF87: =OFFSET(INDIRECT($E87),0,BF$11)-OFFSET(INDIRECT($F87),0,BF$11) -> 0.0546
C88: 77 | D88: 30 | E88: =$A$11&$A$13&C88 -> 历史新!C77 | F88: =$B$11&$B$13&D88 -> 历史汇总!B30 | G88: ACU | H88: =OFFSET(INDIRECT($E88),0,H$11)-OFFSET(INDIRECT($F88),0,H$11) -> -125071 | I88: =OFFSET(INDIRECT($E88),0,I$11)-OFFSET(INDIRECT($F88),0,I$11) -> -70689 | J88: =OFFSET(INDIRECT($E88),0,J$11)-OFFSET(INDIRECT($F88),0,J$11) -> -76164 | K88: =OFFSET(INDIRECT($E88),0,K$11)-OFFSET(INDIRECT($F88),0,K$11) -> -69229 | L88: =OFFSET(INDIRECT($E88),0,L$11)-OFFSET(INDIRECT($F88),0,L$11) -> -68161 | M88: =OFFSET(INDIRECT($E88),0,M$11)-OFFSET(INDIRECT($F88),0,M$11) -> -100753 | N88: =OFFSET(INDIRECT($E88),0,N$11)-OFFSET(INDIRECT($F88),0,N$11) -> -99684 | O88: =OFFSET(INDIRECT($E88),0,O$11)-OFFSET(INDIRECT($F88),0,O$11) -> -55226 | ... BF88: =OFFSET(INDIRECT($E88),0,BF$11)-OFFSET(INDIRECT($F88),0,BF$11) -> 29499.53
C89: 78 | D89: 31 | E89: =$A$11&$A$13&C89 -> 历史新!C78 | F89: =$B$11&$B$13&D89 -> 历史汇总!B31 | G89: ACU增长率 | H89: =OFFSET(INDIRECT($E89),0,H$11)-OFFSET(INDIRECT($F89),0,H$11) -> 0.0915 | I89: =OFFSET(INDIRECT($E89),0,I$11)-OFFSET(INDIRECT($F89),0,I$11) -> 0.4348 | J89: =OFFSET(INDIRECT($E89),0,J$11)-OFFSET(INDIRECT($F89),0,J$11) -> -0.0775 | K89: =OFFSET(INDIRECT($E89),0,K$11)-OFFSET(INDIRECT($F89),0,K$11) -> 0.0911 | L89: =OFFSET(INDIRECT($E89),0,L$11)-OFFSET(INDIRECT($F89),0,L$11) -> 0.0154 | M89: =OFFSET(INDIRECT($E89),0,M$11)-OFFSET(INDIRECT($F89),0,M$11) -> -0.4782 | N89: =OFFSET(INDIRECT($E89),0,N$11)-OFFSET(INDIRECT($F89),0,N$11) -> 0.0106 | O89: =OFFSET(INDIRECT($E89),0,O$11)-OFFSET(INDIRECT($F89),0,O$11) -> 0.446 | ... BF89: =OFFSET(INDIRECT($E89),0,BF$11)-OFFSET(INDIRECT($F89),0,BF$11) -> 0.094
C90: 79 | D90: 32 | E90: =$A$11&$A$13&C90 -> 历史新!C79 | F90: =$B$11&$B$13&D90 -> 历史汇总!B32 | G90: 活跃用户日平均在线时长 | H90: =OFFSET(INDIRECT($E90),0,H$11)-OFFSET(INDIRECT($F90),0,H$11) -> 0 | I90: =OFFSET(INDIRECT($E90),0,I$11)-OFFSET(INDIRECT($F90),0,I$11) -> 0 | J90: =OFFSET(INDIRECT($E90),0,J$11)-OFFSET(INDIRECT($F90),0,J$11) -> 0 | K90: =OFFSET(INDIRECT($E90),0,K$11)-OFFSET(INDIRECT($F90),0,K$11) -> 0 | L90: =OFFSET(INDIRECT($E90),0,L$11)-OFFSET(INDIRECT($F90),0,L$11) -> 0 | M90: =OFFSET(INDIRECT($E90),0,M$11)-OFFSET(INDIRECT($F90),0,M$11) -> 0 | N90: =OFFSET(INDIRECT($E90),0,N$11)-OFFSET(INDIRECT($F90),0,N$11) -> 0 | O90: =OFFSET(INDIRECT($E90),0,O$11)-OFFSET(INDIRECT($F90),0,O$11) -> 0 | ... BF90: =OFFSET(INDIRECT($E90),0,BF$11)-OFFSET(INDIRECT($F90),0,BF$11) -> 2854.38
C91: 80 | G91: 付费用户日平均在线时长
C92: 81 | D92: 33 | E92: =$A$11&$A$13&C92 -> 历史新!C81 | F92: =$B$11&$B$13&D92 -> 历史汇总!B33 | G92: 新增用户日平均在线时长 | H92: =OFFSET(INDIRECT($E92),0,H$11)-OFFSET(INDIRECT($F92),0,H$11) -> 0 | I92: =OFFSET(INDIRECT($E92),0,I$11)-OFFSET(INDIRECT($F92),0,I$11) -> 0 | J92: =OFFSET(INDIRECT($E92),0,J$11)-OFFSET(INDIRECT($F92),0,J$11) -> 0 | K92: =OFFSET(INDIRECT($E92),0,K$11)-OFFSET(INDIRECT($F92),0,K$11) -> 0 | L92: =OFFSET(INDIRECT($E92),0,L$11)-OFFSET(INDIRECT($F92),0,L$11) -> 0 | M92: =OFFSET(INDIRECT($E92),0,M$11)-OFFSET(INDIRECT($F92),0,M$11) -> 0 | N92: =OFFSET(INDIRECT($E92),0,N$11)-OFFSET(INDIRECT($F92),0,N$11) -> 0 | O92: =OFFSET(INDIRECT($E92),0,O$11)-OFFSET(INDIRECT($F92),0,O$11) -> 0 | ... BF92: =OFFSET(INDIRECT($E92),0,BF$11)-OFFSET(INDIRECT($F92),0,BF$11) -> 2838.27
C93: 82 | D93: 34 | E93: =$A$11&$A$13&C93 -> 历史新!C82 | F93: =$B$11&$B$13&D93 -> 历史汇总!B34 | G93: 留存用户日平均在线时长 | H93: =OFFSET(INDIRECT($E93),0,H$11)-OFFSET(INDIRECT($F93),0,H$11) -> 0 | I93: =OFFSET(INDIRECT($E93),0,I$11)-OFFSET(INDIRECT($F93),0,I$11) -> 0 | J93: =OFFSET(INDIRECT($E93),0,J$11)-OFFSET(INDIRECT($F93),0,J$11) -> 0 | K93: =OFFSET(INDIRECT($E93),0,K$11)-OFFSET(INDIRECT($F93),0,K$11) -> 0 | L93: =OFFSET(INDIRECT($E93),0,L$11)-OFFSET(INDIRECT($F93),0,L$11) -> 0 | M93: =OFFSET(INDIRECT($E93),0,M$11)-OFFSET(INDIRECT($F93),0,M$11) -> 0 | N93: =OFFSET(INDIRECT($E93),0,N$11)-OFFSET(INDIRECT($F93),0,N$11) -> 0 | O93: =OFFSET(INDIRECT($E93),0,O$11)-OFFSET(INDIRECT($F93),0,O$11) -> 0 | ... BF93: =OFFSET(INDIRECT($E93),0,BF$11)-OFFSET(INDIRECT($F93),0,BF$11) -> 2974.39
C94: 83 | D94: 35 | E94: =$A$11&$A$13&C94 -> 历史新!C83 | F94: =$B$11&$B$13&D94 -> 历史汇总!B35 | G94: 回流用户日平均在线时长 | H94: =OFFSET(INDIRECT($E94),0,H$11)-OFFSET(INDIRECT($F94),0,H$11) -> 0 | I94: =OFFSET(INDIRECT($E94),0,I$11)-OFFSET(INDIRECT($F94),0,I$11) -> 0 | J94: =OFFSET(INDIRECT($E94),0,J$11)-OFFSET(INDIRECT($F94),0,J$11) -> 0 | K94: =OFFSET(INDIRECT($E94),0,K$11)-OFFSET(INDIRECT($F94),0,K$11) -> 0 | L94: =OFFSET(INDIRECT($E94),0,L$11)-OFFSET(INDIRECT($F94),0,L$11) -> 0 | M94: =OFFSET(INDIRECT($E94),0,M$11)-OFFSET(INDIRECT($F94),0,M$11) -> 0 | N94: =OFFSET(INDIRECT($E94),0,N$11)-OFFSET(INDIRECT($F94),0,N$11) -> 0 | O94: =OFFSET(INDIRECT($E94),0,O$11)-OFFSET(INDIRECT($F94),0,O$11) -> 0 | ... BF94: =OFFSET(INDIRECT($E94),0,BF$11)-OFFSET(INDIRECT($F94),0,BF$11) -> 2234.66
C95: 84 | D95: 36 | E95: =$A$11&$A$13&C95 -> 历史新!C84 | F95: =$B$11&$B$13&D95 -> 历史汇总!B36 | G95: 活跃用户月平均登录天数 | H95: =OFFSET(INDIRECT($E95),0,H$11)-OFFSET(INDIRECT($F95),0,H$11) -> 0 | I95: =OFFSET(INDIRECT($E95),0,I$11)-OFFSET(INDIRECT($F95),0,I$11) -> 0 | J95: =OFFSET(INDIRECT($E95),0,J$11)-OFFSET(INDIRECT($F95),0,J$11) -> 0 | K95: =OFFSET(INDIRECT($E95),0,K$11)-OFFSET(INDIRECT($F95),0,K$11) -> 0 | L95: =OFFSET(INDIRECT($E95),0,L$11)-OFFSET(INDIRECT($F95),0,L$11) -> 0 | M95: =OFFSET(INDIRECT($E95),0,M$11)-OFFSET(INDIRECT($F95),0,M$11) -> 0 | N95: =OFFSET(INDIRECT($E95),0,N$11)-OFFSET(INDIRECT($F95),0,N$11) -> 0 | O95: =OFFSET(INDIRECT($E95),0,O$11)-OFFSET(INDIRECT($F95),0,O$11) -> 0 | ... BF95: =OFFSET(INDIRECT($E95),0,BF$11)-OFFSET(INDIRECT($F95),0,BF$11) -> 3.41
C96: 85 | G96: 付费用户平均登录天数
C97: 86 | D97: 37 | E97: =$A$11&$A$13&C97 -> 历史新!C86 | F97: =$B$11&$B$13&D97 -> 历史汇总!B37 | G97: 新增用户月平均登录天数 | H97: =OFFSET(INDIRECT($E97),0,H$11)-OFFSET(INDIRECT($F97),0,H$11) -> 0 | I97: =OFFSET(INDIRECT($E97),0,I$11)-OFFSET(INDIRECT($F97),0,I$11) -> 0 | J97: =OFFSET(INDIRECT($E97),0,J$11)-OFFSET(INDIRECT($F97),0,J$11) -> 0 | K97: =OFFSET(INDIRECT($E97),0,K$11)-OFFSET(INDIRECT($F97),0,K$11) -> 0 | L97: =OFFSET(INDIRECT($E97),0,L$11)-OFFSET(INDIRECT($F97),0,L$11) -> 0 | M97: =OFFSET(INDIRECT($E97),0,M$11)-OFFSET(INDIRECT($F97),0,M$11) -> 0 | N97: =OFFSET(INDIRECT($E97),0,N$11)-OFFSET(INDIRECT($F97),0,N$11) -> 0 | O97: =OFFSET(INDIRECT($E97),0,O$11)-OFFSET(INDIRECT($F97),0,O$11) -> 0 | ... BF97: =OFFSET(INDIRECT($E97),0,BF$11)-OFFSET(INDIRECT($F97),0,BF$11) -> 2.4
C98: 87 | D98: 38 | E98: =$A$11&$A$13&C98 -> 历史新!C87 | F98: =$B$11&$B$13&D98 -> 历史汇总!B38 | G98: 留存用户月平均登录天数 | H98: =OFFSET(INDIRECT($E98),0,H$11)-OFFSET(INDIRECT($F98),0,H$11) -> 0 | I98: =OFFSET(INDIRECT($E98),0,I$11)-OFFSET(INDIRECT($F98),0,I$11) -> 0 | J98: =OFFSET(INDIRECT($E98),0,J$11)-OFFSET(INDIRECT($F98),0,J$11) -> 0 | K98: =OFFSET(INDIRECT($E98),0,K$11)-OFFSET(INDIRECT($F98),0,K$11) -> 0 | L98: =OFFSET(INDIRECT($E98),0,L$11)-OFFSET(INDIRECT($F98),0,L$11) -> 0 | M98: =OFFSET(INDIRECT($E98),0,M$11)-OFFSET(INDIRECT($F98),0,M$11) -> 0 | N98: =OFFSET(INDIRECT($E98),0,N$11)-OFFSET(INDIRECT($F98),0,N$11) -> 0 | O98: =OFFSET(INDIRECT($E98),0,O$11)-OFFSET(INDIRECT($F98),0,O$11) -> 0 | ... BF98: =OFFSET(INDIRECT($E98),0,BF$11)-OFFSET(INDIRECT($F98),0,BF$11) -> 5.46
C99: 88 | D99: 39 | E99: =$A$11&$A$13&C99 -> 历史新!C88 | F99: =$B$11&$B$13&D99 -> 历史汇总!B39 | G99: 回流用户月平均登录天数 | H99: =OFFSET(INDIRECT($E99),0,H$11)-OFFSET(INDIRECT($F99),0,H$11) -> 0 | I99: =OFFSET(INDIRECT($E99),0,I$11)-OFFSET(INDIRECT($F99),0,I$11) -> 0 | J99: =OFFSET(INDIRECT($E99),0,J$11)-OFFSET(INDIRECT($F99),0,J$11) -> 0 | K99: =OFFSET(INDIRECT($E99),0,K$11)-OFFSET(INDIRECT($F99),0,K$11) -> 0 | L99: =OFFSET(INDIRECT($E99),0,L$11)-OFFSET(INDIRECT($F99),0,L$11) -> 0 | M99: =OFFSET(INDIRECT($E99),0,M$11)-OFFSET(INDIRECT($F99),0,M$11) -> 0 | N99: =OFFSET(INDIRECT($E99),0,N$11)-OFFSET(INDIRECT($F99),0,N$11) -> 0 | O99: =OFFSET(INDIRECT($E99),0,O$11)-OFFSET(INDIRECT($F99),0,O$11) -> 0 | ... BF99: =OFFSET(INDIRECT($E99),0,BF$11)-OFFSET(INDIRECT($F99),0,BF$11) -> 2.06
AT104: 0 | AU104: 1 | AV104: 2 | AW104: 3 | AX104: 4 | AY104: 5 | AZ104: 6 | BA104: 7 | BB104: 8 | BC104: 9 | BD104: 10 | BE104: 11 | BF104: 12
B105: 与赛尔偏移值 | C105: 94 | D105: 73 | G105: 约瑟传说 | H105: 2011-01 | I105: 2011-02 | J105: 2011-03 | K105: 2011-04 | L105: 2011-05 | M105: 2011-06 | N105: 2011-07 | O105: 2011-08 | P105: 2011-09 | Q105: 2011-10 | R105: 2011-11 | S105: 2011-12 | T105: 2012-01 | U105: 2012-02 | V105: 2012-03 | W105: 2012-04 | X105: 2012-05 | Y105: 2012-06 | Z105: 2012-07 | AA105: 2012-08 | AB105: 2012-09 | AC105: 2012-10 | AD105: 2012-11 | AE105: 2012-12 | AF105: 2013-01 | AG105: 2013-02 | AH105: 2013-03 | AI105: 2013-04 | AJ105: 2013-05 | AK105: 2013-06 | AL105: 2013-07 | AM105: 2013-08 | AN105: 2013-09 | AO105: 2013-10 | AP105: 2013-11 | AQ105: 2013-12 | AR105: 2014-01 | AS105: 2014-02 | AT105: 2014-03 | AU105: 2014-04 | AV105: 2014-05 | AW105: 2014-06 | AX105: 2014-07 | AY105: 2014-08 | AZ105: 2014-09 | BA105: 2014-10 | BB105: 2014-11 | BC105: 2014-12 | BD105: 2015-01 | BE105: 2015-02 | BF105: 2015-03
C106: =C13+$C$105 -> 96 | D106: =D13+$D$105 -> 115 | E106: =$A$11&$A$13&C106 -> 历史新!C96 | F106: =$B$11&$B$13&D106 -> 历史汇总!B115 | G106: 付费总额(元) | H106: =OFFSET(INDIRECT($E106),0,H$11)-OFFSET(INDIRECT($F106),0,H$11) -> 0 | I106: =OFFSET(INDIRECT($E106),0,I$11)-OFFSET(INDIRECT($F106),0,I$11) -> 0 | J106: =OFFSET(INDIRECT($E106),0,J$11)-OFFSET(INDIRECT($F106),0,J$11) -> 0 | K106: =OFFSET(INDIRECT($E106),0,K$11)-OFFSET(INDIRECT($F106),0,K$11) -> 0 | L106: =OFFSET(INDIRECT($E106),0,L$11)-OFFSET(INDIRECT($F106),0,L$11) -> 0 | M106: =OFFSET(INDIRECT($E106),0,M$11)-OFFSET(INDIRECT($F106),0,M$11) -> 0 | N106: =OFFSET(INDIRECT($E106),0,N$11)-OFFSET(INDIRECT($F106),0,N$11) -> 0 | O106: =OFFSET(INDIRECT($E106),0,O$11)-OFFSET(INDIRECT($F106),0,O$11) -> 0 | ... BF106: =OFFSET(INDIRECT($E106),0,BF$11)-OFFSET(INDIRECT($F106),0,BF$11) -> 531407
C107: =C14+$C$105 -> 97 | D107: =D14+$D$105 -> 116 | E107: =$A$11&$A$13&C107 -> 历史新!C97 | F107: =$B$11&$B$13&D107 -> 历史汇总!B116 | G107: 付费总额(元)增长率 | H107: =OFFSET(INDIRECT($E107),0,H$11)-OFFSET(INDIRECT($F107),0,H$11) -> 0 | I107: =OFFSET(INDIRECT($E107),0,I$11)-OFFSET(INDIRECT($F107),0,I$11) -> 0 | J107: =OFFSET(INDIRECT($E107),0,J$11)-OFFSET(INDIRECT($F107),0,J$11) -> 0 | K107: =OFFSET(INDIRECT($E107),0,K$11)-OFFSET(INDIRECT($F107),0,K$11) -> 0 | L107: =OFFSET(INDIRECT($E107),0,L$11)-OFFSET(INDIRECT($F107),0,L$11) -> 0 | M107: =OFFSET(INDIRECT($E107),0,M$11)-OFFSET(INDIRECT($F107),0,M$11) -> 0 | N107: =OFFSET(INDIRECT($E107),0,N$11)-OFFSET(INDIRECT($F107),0,N$11) -> 0 | O107: =OFFSET(INDIRECT($E107),0,O$11)-OFFSET(INDIRECT($F107),0,O$11) -> 0 | ... BF107: =OFFSET(INDIRECT($E107),0,BF$11)-OFFSET(INDIRECT($F107),0,BF$11) -> -0.36
C108: =C15+$C$105 -> 98 | D108: =D15+$D$105 -> 117 | E108: =$A$11&$A$13&C108 -> 历史新!C98 | F108: =$B$11&$B$13&D108 -> 历史汇总!B117 | G108: 付费用户数 | H108: =OFFSET(INDIRECT($E108),0,H$11)-OFFSET(INDIRECT($F108),0,H$11) -> 0 | I108: =OFFSET(INDIRECT($E108),0,I$11)-OFFSET(INDIRECT($F108),0,I$11) -> 0 | J108: =OFFSET(INDIRECT($E108),0,J$11)-OFFSET(INDIRECT($F108),0,J$11) -> 0 | K108: =OFFSET(INDIRECT($E108),0,K$11)-OFFSET(INDIRECT($F108),0,K$11) -> 0 | L108: =OFFSET(INDIRECT($E108),0,L$11)-OFFSET(INDIRECT($F108),0,L$11) -> 0 | M108: =OFFSET(INDIRECT($E108),0,M$11)-OFFSET(INDIRECT($F108),0,M$11) -> 0 | N108: =OFFSET(INDIRECT($E108),0,N$11)-OFFSET(INDIRECT($F108),0,N$11) -> 0 | O108: =OFFSET(INDIRECT($E108),0,O$11)-OFFSET(INDIRECT($F108),0,O$11) -> 0 | ... BF108: =OFFSET(INDIRECT($E108),0,BF$11)-OFFSET(INDIRECT($F108),0,BF$11) -> 13599
C109: =C16+$C$105 -> 99 | D109: =D16+$D$105 -> 118 | E109: =$A$11&$A$13&C109 -> 历史新!C99 | F109: =$B$11&$B$13&D109 -> 历史汇总!B118 | G109: 付费用户数增长率 | H109: =OFFSET(INDIRECT($E109),0,H$11)-OFFSET(INDIRECT($F109),0,H$11) -> 0 | I109: =OFFSET(INDIRECT($E109),0,I$11)-OFFSET(INDIRECT($F109),0,I$11) -> 0 | J109: =OFFSET(INDIRECT($E109),0,J$11)-OFFSET(INDIRECT($F109),0,J$11) -> 0 | K109: =OFFSET(INDIRECT($E109),0,K$11)-OFFSET(INDIRECT($F109),0,K$11) -> 0 | L109: =OFFSET(INDIRECT($E109),0,L$11)-OFFSET(INDIRECT($F109),0,L$11) -> 0 | M109: =OFFSET(INDIRECT($E109),0,M$11)-OFFSET(INDIRECT($F109),0,M$11) -> 0 | N109: =OFFSET(INDIRECT($E109),0,N$11)-OFFSET(INDIRECT($F109),0,N$11) -> 0 | O109: =OFFSET(INDIRECT($E109),0,O$11)-OFFSET(INDIRECT($F109),0,O$11) -> 0 | ... BF109: =OFFSET(INDIRECT($E109),0,BF$11)-OFFSET(INDIRECT($F109),0,BF$11) -> -0.2348
C110: =C17+$C$105 -> 100 | D110: =D17+$D$105 -> 129 | E110: =$A$11&$A$13&C110 -> 历史新!C100 | F110: =$B$11&$B$13&D110 -> 历史汇总!B129 | G110: arppu值 | H110: =OFFSET(INDIRECT($E110),0,H$11)-OFFSET(INDIRECT($F110),0,H$11) -> 0 | I110: =OFFSET(INDIRECT($E110),0,I$11)-OFFSET(INDIRECT($F110),0,I$11) -> 0 | J110: =OFFSET(INDIRECT($E110),0,J$11)-OFFSET(INDIRECT($F110),0,J$11) -> 0 | K110: =OFFSET(INDIRECT($E110),0,K$11)-OFFSET(INDIRECT($F110),0,K$11) -> 0 | L110: =OFFSET(INDIRECT($E110),0,L$11)-OFFSET(INDIRECT($F110),0,L$11) -> 0 | M110: =OFFSET(INDIRECT($E110),0,M$11)-OFFSET(INDIRECT($F110),0,M$11) -> 0 | N110: =OFFSET(INDIRECT($E110),0,N$11)-OFFSET(INDIRECT($F110),0,N$11) -> 0 | O110: =OFFSET(INDIRECT($E110),0,O$11)-OFFSET(INDIRECT($F110),0,O$11) -> 0 | ... BF110: =OFFSET(INDIRECT($E110),0,BF$11)-OFFSET(INDIRECT($F110),0,BF$11) -> 39.08
C111: =C18+$C$105 -> 101 | D111: =D18+$D$105 -> 130 | E111: =$A$11&$A$13&C111 -> 历史新!C101 | F111: =$B$11&$B$13&D111 -> 历史汇总!B130 | G111: arppu值增长率 | H111: =OFFSET(INDIRECT($E111),0,H$11)-OFFSET(INDIRECT($F111),0,H$11) -> 0 | I111: =OFFSET(INDIRECT($E111),0,I$11)-OFFSET(INDIRECT($F111),0,I$11) -> 0 | J111: =OFFSET(INDIRECT($E111),0,J$11)-OFFSET(INDIRECT($F111),0,J$11) -> 0 | K111: =OFFSET(INDIRECT($E111),0,K$11)-OFFSET(INDIRECT($F111),0,K$11) -> 0 | L111: =OFFSET(INDIRECT($E111),0,L$11)-OFFSET(INDIRECT($F111),0,L$11) -> 0 | M111: =OFFSET(INDIRECT($E111),0,M$11)-OFFSET(INDIRECT($F111),0,M$11) -> 0 | N111: =OFFSET(INDIRECT($E111),0,N$11)-OFFSET(INDIRECT($F111),0,N$11) -> 0 | O111: =OFFSET(INDIRECT($E111),0,O$11)-OFFSET(INDIRECT($F111),0,O$11) -> 0 | ... BF111: =OFFSET(INDIRECT($E111),0,BF$11)-OFFSET(INDIRECT($F111),0,BF$11) -> -0.1635
C112: =C19+$C$105 -> 102 | D112: =D19+$D$105 -> 132 | E112: =$A$11&$A$13&C112 -> 历史新!C102 | F112: =$B$11&$B$13&D112 -> 历史汇总!B132 | G112: 包月支付总额(不含短信包月续费) | H112: =OFFSET(INDIRECT($E112),0,H$11)-OFFSET(INDIRECT($F112),0,H$11) -> 0 | I112: =OFFSET(INDIRECT($E112),0,I$11)-OFFSET(INDIRECT($F112),0,I$11) -> 0 | J112: =OFFSET(INDIRECT($E112),0,J$11)-OFFSET(INDIRECT($F112),0,J$11) -> 0 | K112: =OFFSET(INDIRECT($E112),0,K$11)-OFFSET(INDIRECT($F112),0,K$11) -> 0 | L112: =OFFSET(INDIRECT($E112),0,L$11)-OFFSET(INDIRECT($F112),0,L$11) -> 0 | M112: =OFFSET(INDIRECT($E112),0,M$11)-OFFSET(INDIRECT($F112),0,M$11) -> 0 | N112: =OFFSET(INDIRECT($E112),0,N$11)-OFFSET(INDIRECT($F112),0,N$11) -> 0 | O112: =OFFSET(INDIRECT($E112),0,O$11)-OFFSET(INDIRECT($F112),0,O$11) -> 0 | ... BF112: =OFFSET(INDIRECT($E112),0,BF$11)-OFFSET(INDIRECT($F112),0,BF$11) -> 155930
C113: =C20+$C$105 -> 103 | D113: =D20+$D$105 -> 133 | E113: =$A$11&$A$13&C113 -> 历史新!C103 | F113: =$B$11&$B$13&D113 -> 历史汇总!B133 | G113: 包月支付总额(不含短信包月续费)增长率 | H113: =OFFSET(INDIRECT($E113),0,H$11)-OFFSET(INDIRECT($F113),0,H$11) -> 0 | I113: =OFFSET(INDIRECT($E113),0,I$11)-OFFSET(INDIRECT($F113),0,I$11) -> 0 | J113: =OFFSET(INDIRECT($E113),0,J$11)-OFFSET(INDIRECT($F113),0,J$11) -> 0 | K113: =OFFSET(INDIRECT($E113),0,K$11)-OFFSET(INDIRECT($F113),0,K$11) -> 0 | L113: =OFFSET(INDIRECT($E113),0,L$11)-OFFSET(INDIRECT($F113),0,L$11) -> 0 | M113: =OFFSET(INDIRECT($E113),0,M$11)-OFFSET(INDIRECT($F113),0,M$11) -> 0 | N113: =OFFSET(INDIRECT($E113),0,N$11)-OFFSET(INDIRECT($F113),0,N$11) -> 0 | O113: =OFFSET(INDIRECT($E113),0,O$11)-OFFSET(INDIRECT($F113),0,O$11) -> 0 | ... BF113: =OFFSET(INDIRECT($E113),0,BF$11)-OFFSET(INDIRECT($F113),0,BF$11) -> -0.3711
C114: =C21+$C$105 -> 104 | D114: =D21+$D$105 -> 134 | E114: =$A$11&$A$13&C114 -> 历史新!C104 | F114: =$B$11&$B$13&D114 -> 历史汇总!B134 | G114: 包月支付用户数(不含短信包月续费) | H114: =OFFSET(INDIRECT($E114),0,H$11)-OFFSET(INDIRECT($F114),0,H$11) -> 0 | I114: =OFFSET(INDIRECT($E114),0,I$11)-OFFSET(INDIRECT($F114),0,I$11) -> 0 | J114: =OFFSET(INDIRECT($E114),0,J$11)-OFFSET(INDIRECT($F114),0,J$11) -> 0 | K114: =OFFSET(INDIRECT($E114),0,K$11)-OFFSET(INDIRECT($F114),0,K$11) -> 0 | L114: =OFFSET(INDIRECT($E114),0,L$11)-OFFSET(INDIRECT($F114),0,L$11) -> 0 | M114: =OFFSET(INDIRECT($E114),0,M$11)-OFFSET(INDIRECT($F114),0,M$11) -> 0 | N114: =OFFSET(INDIRECT($E114),0,N$11)-OFFSET(INDIRECT($F114),0,N$11) -> 0 | O114: =OFFSET(INDIRECT($E114),0,O$11)-OFFSET(INDIRECT($F114),0,O$11) -> 0 | ... BF114: =OFFSET(INDIRECT($E114),0,BF$11)-OFFSET(INDIRECT($F114),0,BF$11) -> 6106
C115: =C22+$C$105 -> 105 | D115: =D22+$D$105 -> 135 | E115: =$A$11&$A$13&C115 -> 历史新!C105 | F115: =$B$11&$B$13&D115 -> 历史汇总!B135 | G115: 包月支付用户数(不含短信包月续费)增长率 | H115: =OFFSET(INDIRECT($E115),0,H$11)-OFFSET(INDIRECT($F115),0,H$11) -> 0 | I115: =OFFSET(INDIRECT($E115),0,I$11)-OFFSET(INDIRECT($F115),0,I$11) -> 0 | J115: =OFFSET(INDIRECT($E115),0,J$11)-OFFSET(INDIRECT($F115),0,J$11) -> 0 | K115: =OFFSET(INDIRECT($E115),0,K$11)-OFFSET(INDIRECT($F115),0,K$11) -> 0 | L115: =OFFSET(INDIRECT($E115),0,L$11)-OFFSET(INDIRECT($F115),0,L$11) -> 0 | M115: =OFFSET(INDIRECT($E115),0,M$11)-OFFSET(INDIRECT($F115),0,M$11) -> 0 | N115: =OFFSET(INDIRECT($E115),0,N$11)-OFFSET(INDIRECT($F115),0,N$11) -> 0 | O115: =OFFSET(INDIRECT($E115),0,O$11)-OFFSET(INDIRECT($F115),0,O$11) -> 0 | ... BF115: =OFFSET(INDIRECT($E115),0,BF$11)-OFFSET(INDIRECT($F115),0,BF$11) -> -0.2749
C116: =C23+$C$105 -> 106 | D116: =D23+$D$105 -> 136 | E116: =$A$11&$A$13&C116 -> 历史新!C106 | F116: =$B$11&$B$13&D116 -> 历史汇总!B136 | G116: 包月支付arppu值 | H116: =OFFSET(INDIRECT($E116),0,H$11)-OFFSET(INDIRECT($F116),0,H$11) -> 0 | I116: =OFFSET(INDIRECT($E116),0,I$11)-OFFSET(INDIRECT($F116),0,I$11) -> 0 | J116: =OFFSET(INDIRECT($E116),0,J$11)-OFFSET(INDIRECT($F116),0,J$11) -> 0 | K116: =OFFSET(INDIRECT($E116),0,K$11)-OFFSET(INDIRECT($F116),0,K$11) -> 0 | L116: =OFFSET(INDIRECT($E116),0,L$11)-OFFSET(INDIRECT($F116),0,L$11) -> 0 | M116: =OFFSET(INDIRECT($E116),0,M$11)-OFFSET(INDIRECT($F116),0,M$11) -> 0 | N116: =OFFSET(INDIRECT($E116),0,N$11)-OFFSET(INDIRECT($F116),0,N$11) -> 0 | O116: =OFFSET(INDIRECT($E116),0,O$11)-OFFSET(INDIRECT($F116),0,O$11) -> 0 | ... BF116: =OFFSET(INDIRECT($E116),0,BF$11)-OFFSET(INDIRECT($F116),0,BF$11) -> 25.54
C117: =C24+$C$105 -> 107 | D117: =D24+$D$105 -> 137 | E117: =$A$11&$A$13&C117 -> 历史新!C107 | F117: =$B$11&$B$13&D117 -> 历史汇总!B137 | G117: 包月支付arppu值增长率 | H117: =OFFSET(INDIRECT($E117),0,H$11)-OFFSET(INDIRECT($F117),0,H$11) -> 0 | I117: =OFFSET(INDIRECT($E117),0,I$11)-OFFSET(INDIRECT($F117),0,I$11) -> 0 | J117: =OFFSET(INDIRECT($E117),0,J$11)-OFFSET(INDIRECT($F117),0,J$11) -> 0 | K117: =OFFSET(INDIRECT($E117),0,K$11)-OFFSET(INDIRECT($F117),0,K$11) -> 0 | L117: =OFFSET(INDIRECT($E117),0,L$11)-OFFSET(INDIRECT($F117),0,L$11) -> 0 | M117: =OFFSET(INDIRECT($E117),0,M$11)-OFFSET(INDIRECT($F117),0,M$11) -> 0 | N117: =OFFSET(INDIRECT($E117),0,N$11)-OFFSET(INDIRECT($F117),0,N$11) -> 0 | O117: =OFFSET(INDIRECT($E117),0,O$11)-OFFSET(INDIRECT($F117),0,O$11) -> 0 | ... BF117: =OFFSET(INDIRECT($E117),0,BF$11)-OFFSET(INDIRECT($F117),0,BF$11) -> -0.1325
... C127: =C34+$C$105 -> 117 | D127: =D34+$D$105 -> 122 | E127: =$A$11&$A$13&C127 -> 历史新!C117 | F127: =$B$11&$B$13&D127 -> 历史汇总!B122 | G127: 回流付费用户数 | H127: =OFFSET(INDIRECT($E127),0,H$11)-OFFSET(INDIRECT($F127),0,H$11) -> 0 | I127: =OFFSET(INDIRECT($E127),0,I$11)-OFFSET(INDIRECT($F127),0,I$11) -> 0 | J127: =OFFSET(INDIRECT($E127),0,J$11)-OFFSET(INDIRECT($F127),0,J$11) -> 0 | K127: =OFFSET(INDIRECT($E127),0,K$11)-OFFSET(INDIRECT($F127),0,K$11) -> 0 | L127: =OFFSET(INDIRECT($E127),0,L$11)-OFFSET(INDIRECT($F127),0,L$11) -> 0 | M127: =OFFSET(INDIRECT($E127),0,M$11)-OFFSET(INDIRECT($F127),0,M$11) -> 0 | N127: =OFFSET(INDIRECT($E127),0,N$11)-OFFSET(INDIRECT($F127),0,N$11) -> 0 | O127: =OFFSET(INDIRECT($E127),0,O$11)-OFFSET(INDIRECT($F127),0,O$11) -> 0 | ... BF127: =OFFSET(INDIRECT($E127),0,BF$11)-OFFSET(INDIRECT($F127),0,BF$11) -> 2335
C128: =C35+$C$105 -> 118 | E128: =$A$11&$A$13&C128 -> 历史新!C118 | F128: =$B$11&$B$13&D128 -> 历史汇总!B | G128: 新增用户中的付费用户数
C129: =C36+$C$105 -> 119 | E129: =$A$11&$A$13&C129 -> 历史新!C119 | F129: =$B$11&$B$13&D129 -> 历史汇总!B | G129: 留存用户中的付费用户数
C130: =C37+$C$105 -> 120 | E130: =$A$11&$A$13&C130 -> 历史新!C120 | F130: =$B$11&$B$13&D130 -> 历史汇总!B | G130: 回流用户中的付费用户数
...

Sheet 历史汇总
A1: 赛尔号 | B1: =TEXT(DATE(LEFT(B2,4),RIGHT(B2,2),1),"yyyymm") -> 201101 | C1: =TEXT(DATE(LEFT(C2,4),RIGHT(C2,2),1),"yyyymm") -> 201102 | D1: =TEXT(DATE(LEFT(D2,4),RIGHT(D2,2),1),"yyyymm") -> 201103 | E1: =TEXT(DATE(LEFT(E2,4),RIGHT(E2,2),1),"yyyymm") -> 201104 | F1: =TEXT(DATE(LEFT(F2,4),RIGHT(F2,2),1),"yyyymm") -> 201105 | G1: =TEXT(DATE(LEFT(G2,4),RIGHT(G2,2),1),"yyyymm") -> 201106 | H1: =TEXT(DATE(LEFT(H2,4),RIGHT(H2,2),1),"yyyymm") -> 201107 | I1: =TEXT(DATE(LEFT(I2,4),RIGHT(I2,2),1),"yyyymm") -> 201108 | ... BC1: =TEXT(DATE(LEFT(BC2,4),RIGHT(BC2,2),1),"yyyymm") -> 201506
A2: 活跃在线情况 | B2: 201101 | C2: 201102 | D2: 201103 | E2: 201104 | F2: 201105 | G2: 201106 | H2: 201107 | I2: 201108 | J2: 201109 | K2: 201110 | L2: 201111 | M2: 201112 | N2: 201201 | O2: 201202 | P2: 201203 | Q2: 201204 | R2: 201205 | S2: 201206 | T2: 201207 | U2: 201208 | V2: 201209 | W2: 201210 | X2: 201211 | Y2: 201212 | Z2: 201301 | AA2: 201302 | AB2: 201303 | AC2: 201304 | AD2: 201305 | AE2: 201306 | AF2: 201307 | AG2: 201308 | AH2: 201309 | AI2: 201310 | AJ2: 201311 | AK2: 201312 | AL2: 201401 | AM2: 201402 | AN2: 201403 | AO2: 201404 | AP2: 201405 | AQ2: 201406 | AR2: 201407 | AS2: 201408 | AT2: 201409 | AU2: 201410 | AV2: 201411 | AW2: 201412 | AX2: 201501 | AY2: 201502 | AZ2: 201503 | BA2: 201504 | BB2: 201505 | BC2: 201506
A3: 活跃用户 | B3: 10679060 | C3: 9880147 | D3: 8087431 | E3: 8271173 | F3: 7580424 | G3: 7591640 | H3: 8898732 | I3: 8913903 | J3: 7176807 | K3: 7341309 | L3: 5816303 | M3: 6110993 | N3: 11032476 | O3: 9009967 | P3: 8269799 | Q3: 9729462 | R3: 8214876 | S3: 9116872 | T3: 10387046 | U3: 10301822 | V3: 7158214 | W3: 7540606 | X3: 5833153 | Y3: 6523281 | Z3: 7494097 | AA3: 9061604 | AB3: 7759770 | AC3: 7398010 | AD3: 7579863 | AE3: 9377764 | AF3: 13230360 | AG3: 11903660 | AH3: 8291649 | AI3: 8623420 | AJ3: 7117115 | AK3: 6022014 | AL3: 8290643 | AM3: 7034277 | AN3: 6390210 | AO3: 6110147 | AP3: 6648997 | AQ3: 9035146 | AR3: 12920754 | AS3: 11016505 | AT3: 6952463 | AU3: 7600303 | AV3: 6260587 | AW3: 5351572 | AX3: 6044284 | AY3: 7797767 | AZ3: 5673575
A4: 活跃用户增长率 | B4: 0.2765 | C4: -0.0748 | D4: -0.1814 | E4: 0.0227 | F4: -0.0835 | G4: 0.0015 | H4: 0.1722 | I4: 0.0017 | J4: -0.1949 | K4: 0.0229 | L4: -0.2077 | M4: 0.0507 | N4: 0 | O4: -0.1833 | P4: -0.0821 | Q4: 0.1765 | R4: -0.1557 | S4: 0.1098 | T4: 0.1393 | U4: -0.0082 | V4: -0.3052 | W4: 0.0534 | X4: -0.2264 | Y4: 0.1183 | Z4: 0.1488 | AA4: 0.2092 | AB4: -0.1437 | AC4: -0.0466 | AD4: 0.0246 | AE4: 0.2372 | AF4: 0.4108 | AG4: -0.1003 | AH4: -0.3034 | AI4: 0.04 | AJ4: -0.1747 | AK4: -0.1539 | AL4: 0.3767 | AM4: -0.1515 | AN4: -0.0916 | AO4: -0.0438 | AP4: 0.0882 | AQ4: 0.3589 | AR4: 0.4301 | AS4: -0.1474 | AT4: -0.3689 | AU4: 0.0932 | AV4: -0.1763 | AW4: -0.1452 | AX4: 0.1294 | AY4: 0.2901 | AZ4: -0.2724
A5: 有效活跃用户 | B5: 0 | C5: 6015987 | D5: 4729044 | E5: 4816678 | F5: 4523249 | G5: 4370334 | H5: 5247085 | I5: 5061189 | J5: 3893732 | K5: 3871730 | L5: 2871527 | M5: 2938432 | N5: 5600910 | O5: 4411513 | P5: 3908241 | Q5: 4658527 | R5: 3969112 | S5: 4665221 | T5: 5669060 | U5: 5265849 | V5: 3438885 | W5: 3617068 | X5: 2715457 | Y5: 3203918 | Z5: 3707141 | AA5: 4676058 | AB5: 3691747 | AC5: 3606194 | AD5: 3783049 | AE5: 4826590 | AF5: 7060016 | AG5: 5992233 | AH5: 3839386 | AI5: 3906883 | AJ5: 3130482 | AK5: 2706326 | AL5: 3838640 | AM5: 3157635 | AN5: 2838728 | AO5: 2566242 | AP5: 2824955 | AQ5: 4402011 | AR5: 6475739 | AS5: 4936778 | AT5: 2664554 | AU5: 2805731 | AV5: 2351833 | AW5: 2013640 | AX5: 2294364 | AY5: 2920420 | AZ5: 2193193
A6: 有效活跃用户增长率 | B6: 0 | C6: 0 | D6: -0.2139 | E6: 0.0185 | F6: -0.0609 | G6: -0.0338 | H6: 0.2006 | I6: -0.0354 | J6: -0.2307 | K6: -0.0057 | L6: -0.2583 | M6: 0.0233 | N6: 0 | O6: -0.2124 | P6: -0.1141 | Q6: 0.192 | R6: -0.148 | S6: 0.1754 | T6: 0.2152 | U6: -0.0711 | V6: -0.3469 | W6: 0.0518 | X6: -0.2493 | Y6: 0.1799 | Z6: 0.1571 | AA6: 0.2614 | AB6: -0.2105 | AC6: -0.0232 | AD6: 0.049 | AE6: 0.2758 | AF6: 0.4627 | AG6: -0.1512 | AH6: -0.3593 | AI6: 0.0176 | AJ6: -0.1987 | AK6: -0.1355 | AL6: 0.4184 | AM6: -0.1774 | AN6: -0.101 | AO6: -0.096 | AP6: 0.1008 | AQ6: 0.5583 | AR6: 0.4711 | AS6: -0.2377 | AT6: -0.4603 | AU6: 0.053 | AV6: -0.1618 | AW6: -0.1438 | AX6: 0.1394 | AY6: 0.2729 | AZ6: -0.249
A7: 新增活跃用户占比 | B7: 0.2955 | C7: 0.2519 | D7: 0.2089 | E7: 0.2068 | F7: 0.1944 | G7: 0.1997 | H7: 0.2618 | I7: 0.2904 | J7: 0.2475 | K7: 0.2412 | L7: 0.163 | M7: 0.2425 | N7: 0.4347 | O7: 0.3664 | P7: 0.3695 | Q7: 0.4251 | R7: 0.362 | S7: 0.3727 | T7: 0.4446 | U7: 0.4552 | V7: 0.3719 | W7: 0.3941 | X7: 0.3566 | Y7: 0.3863 | Z7: 0.4094 | AA7: 0.4537 | AB7: 0.4153 | AC7: 0.3975 | AD7: 0.3842 | AE7: 0.4343 | AF7: 0.5026 | AG7: 0.4434 | AH7: 0.3901 | AI7: 0.4062 | AJ7: 0.3794 | AK7: 0.3767 | AL7: 0.4524 | AM7: 0.4249 | AN7: 0.4301 | AO7: 0.4322 | AP7: 0.4603 | AQ7: 0.5485 | AR7: 0.5703 | AS7: 0.5225 | AT7: 0.4665 | AU7: 0.4906 | AV7: 0.4642 | AW7: 0.4488 | AX7: 0.4823 | AY7: 0.5441 | AZ7: 0.4991
A8: 留存用户占比 | B8: 0.5409 | C8: 0.6403 | D8: 0.6846 | E8: 0.6395 | F8: 0.6748 | G8: 0.6495 | H8: 0.5669 | I8: 0.5882 | J8: 0.6326 | K8: 0.5947 | L8: 0.6573 | M8: 0.5571 | N8: 0.3627 | O8: 0.5326 | P8: 0.5002 | Q8: 0.436 | R8: 0.5229 | S8: 0.4657 | T8: 0.4272 | U8: 0.4299 | V8: 0.5127 | W8: 0.4425 | X8: 0.4951 | Y8: 0.4135 | Z8: 0.3987 | AA8: 0.3769 | AB8: 0.4327 | AC8: 0.44 | AD8: 0.4473 | AE8: 0.3858 | AF8: 0.3471 | AG8: 0.4484 | AH8: 0.4859 | AI8: 0.4311 | AJ8: 0.4661 | AK8: 0.4522 | AL8: 0.3377 | AM8: 0.4286 | AN8: 0.3963 | AO8: 0.4027 | AP8: 0.3708 | AQ8: 0.3052 | AR8: 0.3045 | AS8: 0.3827 | AT8: 0.4194 | AU8: 0.349 | AV8: 0.3887 | AW8: 0.386 | AX8: 0.3304 | AY8: 0.2837 | AZ8: 0.3574
A9: 回流用户占比 | B9: 0.1636 | C9: 0.1077 | D9: 0.1065 | E9: 0.1537 | F9: 0.1309 | G9: 0.1508 | H9: 0.1713 | I9: 0.1214 | J9: 0.1199 | K9: 0.1641 | L9: 0.1798 | M9: 0.2004 | N9: 0.2026 | O9: 0.101 | P9: 0.1303 | Q9: 0.1389 | R9: 0.1151 | S9: 0.1616 | T9: 0.1282 | U9: 0.1149 | V9: 0.1154 | W9: 0.1634 | X9: 0.1482 | Y9: 0.2002 | Z9: 0.192 | AA9: 0.1694 | AB9: 0.152 | AC9: 0.1626 | AD9: 0.1684 | AE9: 0.1799 | AF9: 0.1503 | AG9: 0.1082 | AH9: 0.124 | AI9: 0.1626 | AJ9: 0.1545 | AK9: 0.1711 | AL9: 0.2099 | AM9: 0.1465 | AN9: 0.1737 | AO9: 0.1652 | AP9: 0.1689 | AQ9: 0.1463 | AR9: 0.1252 | AS9: 0.0948 | AT9: 0.1141 | AU9: 0.1604 | AV9: 0.147 | AW9: 0.1651 | AX9: 0.1874 | AY9: 0.1721 | AZ9: 0.1435
A10: 新增注册角色 | B10: 3192473 | C10: 2519319 | D10: 1739098 | E10: 1779321 | F10: 1530699 | G10: 1672478 | H10: 2774404 | I10: 3142565 | J10: 1957442 | K10: 1887215 | L10: 1016575 | M10: 1552450 | N10: 5002855 | O10: 3492692 | P10: 3231128 | Q10: 4369968 | R10: 3111683 | S10: 3581861 | T10: 4863476 | U10: 5119148 | V10: 2811126 | W10: 3126329 | X10: 2206898 | Y10: 2672310 | Z10: 3234314 | AA10: 4344818 | AB10: 3393467 | AC10: 3094448 | AD10: 3156133 | AE10: 4618774 | AF10: 7112200 | AG10: 5657495 | AH10: 3437761 | AI10: 3695571 | AJ10: 2844144 | AK10: 2396264 | AL10: 3934858 | AM10: 3110718 | AN10: 2820780 | AO10: 2722369 | AP10: 3140861 | AQ10: 5037306 | AR10: 7607893 | AS10: 5862209 | AT10: 3299965 | AU10: 3793363 | AV10: 2967853 | AW10: 2446637 | AX10: 2968260 | AY10: 4332823 | AZ10: 2894494
A11: 新增注册角色增长率 | B11: 0.7808 | C11: -0.2109 | D11: -0.3097 | E11: 0.0231 | F11: -0.1397 | G11: 0.0926 | H11: 0.6589 | I11: 0.1327 | J11: -0.3771 | K11: -0.0359 | L11: -0.4613 | M11: 0.5271 | N11: 0 | O11: -0.3019 | P11: -0.0749 | Q11: 0.3525 | R11: -0.2879 | S11: 0.1511 | T11: 0.3578 | U11: 0.0526 | V11: -0.4509 | W11: 0.1121 | X11: -0.2941 | Y11: 0.2109 | Z11: 0.2103 | AA11: 0.3434 | AB11: -0.219 | AC11: -0.0881 | AD11: 0.0199 | AE11: 0.4634 | AF11: 0.5398 | AG11: -0.2045 | AH11: -0.3924 | AI11: 0.075 | AJ11: -0.2304 | AK11: -0.1575 | AL11: 0.6421 | AM11: -0.2094 | AN11: -0.0932 | AO11: -0.0349 | AP11: 0.1537 | AQ11: 0.6038 | AR11: 0.5103 | AS11: -0.2295 | AT11: -0.4371 | AU11: 0.1495 | AV11: -0.2176 | AW11: -0.1756 | AX11: 0.2132 | AY11: 0.4597 | AZ11: -0.332
A12: 新增活跃用户 | B12: 3155576 | C12: 2488946 | D12: 1689276 | E12: 1710364 | F12: 1473349 | G12: 1516254 | H12: 2329659 | I12: 2588471 | J12: 1775970 | K12: 1770642 | L12: 947781 | M12: 1481695 | N12: 4795627 | O12: 3301068 | P12: 3055786 | Q12: 4135725 | R12: 2973836 | S12: 3397470 | T12: 4618319 | U12: 4689397 | V12: 2662247 | W12: 2971545 | X12: 2080247 | Y12: 2519752 | Z12: 3067810 | AA12: 4111216 | AB12: 3222777 | AC12: 2940423 | AD12: 2912558 | AE12: 4072682 | AF12: 6650218 | AG12: 5278612 | AH12: 3234445 | AI12: 3503160 | AJ12: 2700279 | AK12: 2268308 | AL12: 3750790 | AM12: 2988686 | AN12: 2748117 | AO12: 2640594 | AP12: 3060654 | AQ12: 4955585 | AR12: 7369052 | AS12: 5755969 | AT12: 3243214 | AU12: 3729035 | AV12: 2906373 | AW12: 2402005 | AX12: 2914885 | AY12: 4243154 | AZ12: 2831607
A13: 新增活跃用户增长率 | B13: 0.7927 | C13: -0.2113 | D13: -0.3213 | E13: 0.0125 | F13: -0.1386 | G13: 0.0291 | H13: 0.5365 | I13: 0.1111 | J13: -0.3139 | K13: -0.003 | L13: -0.4647 | M13: 0.5633 | N13: 0 | O13: -0.3117 | P13: -0.0743 | Q13: 0.3534 | R13: -0.2809 | S13: 0.1425 | T13: 0.3593 | U13: 0.0154 | V13: -0.4323 | W13: 0.1162 | X13: -0.2999 | Y13: 0.2113 | Z13: 0.2175 | AA13: 0.3401 | AB13: -0.2161 | AC13: -0.0876 | AD13: -0.0095 | AE13: 0.3983 | AF13: 0.6329 | AG13: -0.2062 | AH13: -0.3873 | AI13: 0.0831 | AJ13: -0.2292 | AK13: -0.16 | AL13: 0.6536 | AM13: -0.2032 | AN13: -0.0805 | AO13: -0.0391 | AP13: 0.1591 | AQ13: 0.6191 | AR13: 0.487 | AS13: -0.2189 | AT13: -0.4365 | AU13: 0.1498 | AV13: -0.2206 | AW13: -0.1735 | AX13: 0.2135 | AY13: 0.4557 | AZ13: -0.3327
A14: 留存用户 | B14: 5776495 | C14: 6326681 | D14: 5536522 | E14: 5289541 | F14: 5115106 | G14: 4930833 | H14: 5045004 | I14: 5243039 | J14: 4540015 | K14: 4365701 | L14: 3823037 | M14: 3404515 | N14: 4001514 | O14: 4799052 | P14: 4136685 | Q14: 4241897 | R14: 4295907 | S14: 4245764 | T14: 4436957 | U14: 4428364 | V14: 3669796 | W14: 3337015 | X14: 2888205 | Y14: 2697631 | Z14: 2987522 | AA14: 3415111 | AB14: 3357664 | AC14: 3254923 | AD14: 3390546 | AE14: 3617997 | AF14: 4592252 | AG14: 5337305 | AH14: 4029299 | AI14: 3717872 | AJ14: 3317431 | AK14: 2723435 | AL14: 2799551 | AM14: 3014921 | AN14: 2532262 | AO14: 2460391 | AP14: 2465288 | AQ14: 2757892 | AR14: 3934538 | AS14: 4215649 | AT14: 2915708 | AU14: 2652519 | AV14: 2433677 | AW14: 2065766 | AX14: 1996875 | AY14: 2212499 | AZ14: 2027795
... A31: ACU增长率 | B31: 0.6998 | C31: -0.0915 | D31: -0.4348 | E31: 0.0775 | F31: -0.0911 | G31: -0.0154 | H31: 0.4782 | I31: -0.0106 | J31: -0.446 | K31: -0.0504 | L31: -0.3045 | M31: 0.0123 | N31: 1.461 | O31: -0.2658 | P31: -0.1575 | Q31: 0.3558 | R31: -0.2399 | S31: 0.3643 | T31: 0.3652 | U31: -0.0875 | V31: -0.5054 | W31: 0.0523 | X31: -0.2848 | Y31: 0.154 | Z31: 0.2846 | AA31: 0.4334 | AB31: -0.3613 | AC31: 0.0342 | AD31: 0.0383 | AE31: 0.3665 | AF31: 0.8299 | AG31: -0.1468 | AH31: -0.5329 | AI31: -0.0293 | AJ31: -0.2121 | AK31: -0.0537 | AL31: 0.5686 | AM31: -0.1732 | AN31: -0.2178 | AO31: -0.0823 | AP31: -0.0017 | AQ31: 0.5603 | AR31: 0.8265 | AS31: -0.3185 | AT31: -0.5614 | AU31: 0.0192 | AV31: -0.0937 | AW31: -0.0976 | AX31: 0.1686 | AY31: 0.4277 | AZ31: -0.3265
A32: 活跃用户日平均在线时长 | N32: 3601.9052 | O32: 3287 | P32: 3201 | Q32: 3540 | R32: 3260 | S32: 3760 | T32: 4122 | U32: 4016 | V32: 3389 | W32: 3457 | X32: 3316 | Y32: 3577 | Z32: 3856 | AA32: 3852 | AB32: 3334 | AC32: 3466 | AD32: 3412 | AE32: 3742 | AF32: 4165 | AG32: 3936 | AH32: 3164 | AI32: 3199 | AJ32: 3114 | AK32: 3342 | AL32: 3751 | AM32: 3630 | AN32: 3330 | AO32: 3170 | AP32: 3148 | AQ32: 3192 | AR32: 3560 | AS32: 3270 | AT32: 2676 | AU32: 2691 | AV32: 2794 | AW32: 2900 | AX32: 3059 | AY32: 3116 | AZ32: 2893
A33: 新增用户日平均在线时长 | N33: 3528.0833 | O33: 3189 | P33: 2997 | Q33: 3247 | R33: 3066 | S33: 3645 | T33: 4094 | U33: 3947 | V33: 3056 | W33: 3211 | X33: 3162 | Y33: 3550 | Z33: 3871 | AA33: 3950 | AB33: 3412 | AC33: 3507 | AD33: 3413 | AE33: 3885 | AF33: 4160 | AG33: 3697 | AH33: 3052 | AI33: 3075 | AJ33: 3111 | AK33: 3172 | AL33: 3520 | AM33: 3408 | AN33: 3128 | AO33: 2945 | AP33: 2959 | AQ33: 3103 | AR33: 3394 | AS33: 3055 | AT33: 2580 | AU33: 2534 | AV33: 2639 | AW33: 2619 | AX33: 2768 | AY33: 2839 | AZ33: 2711
A34: 留存用户日平均在线时长 | N34: 3738.165 | O34: 3348 | P34: 3328 | Q34: 3719 | R34: 3367 | S34: 3889 | T34: 4207 | U34: 4104 | V34: 3550 | W34: 3650 | X34: 3453 | Y34: 3717 | Z34: 4001 | AA34: 3922 | AB34: 3387 | AC34: 3555 | AD34: 3500 | AE34: 3778 | AF34: 4259 | AG34: 4069 | AH34: 3257 | AI34: 3352 | AJ34: 3206 | AK34: 3511 | AL34: 4041 | AM34: 3827 | AN34: 3534 | AO34: 3381 | AP34: 3371 | AQ34: 3371 | AR34: 3742 | AS34: 3455 | AT34: 2783 | AU34: 2911 | AV34: 2986 | AW34: 3160 | AX34: 3398 | AY34: 3487 | AZ34: 3141
A35: 回流用户日平均在线时长 | N35: 3100.2212 | O35: 2807 | P35: 2514 | Q35: 2749 | R35: 2445 | S35: 3017 | T35: 3511 | U35: 3408 | V35: 2718 | W35: 2707 | X35: 2590 | Y35: 2877 | Z35: 3161 | AA35: 3272 | AB35: 2798 | AC35: 2820 | AD35: 2755 | AE35: 3246 | AF35: 3625 | AG35: 3250 | AH35: 2584 | AI35: 2394 | AJ35: 2365 | AK35: 2505 | AL35: 2987 | AM35: 2865 | AN35: 2622 | AO35: 2407 | AP35: 2419 | AQ35: 2774 | AR35: 3328 | AS35: 2877 | AT35: 2249 | AU35: 2116 | AV35: 2169 | AW35: 2219 | AX35: 2367 | AY35: 2481 | AZ35: 2223
A36: 活跃用户月平均登录天数 | N36: 4.43 | O36: 4.13 | P36: 4.17 | Q36: 4.07 | R36: 4.21 | S36: 4.3 | T36: 4.66 | U36: 4.24 | V36: 3.62 | W36: 3.59 | X36: 3.36 | Y36: 3.33 | Z36: 3.48 | AA36: 3.72 | AB36: 3.6 | AC36: 3.63 | AD36: 3.86 | AE36: 3.78 | AF36: 4.56 | AG36: 4.62 | AH36: 3.72 | AI36: 3.54 | AJ36: 3.36 | AK36: 3.6 | AL36: 3.65 | AM36: 3.31 | AN36: 3.46 | AO36: 3.37 | AP36: 3.23 | AQ36: 3.55 | AR36: 4.17 | AS36: 3.67 | AT36: 3 | AU36: 2.87 | AV36: 2.96 | AW36: 3.1 | AX36: 3.04 | AY36: 2.99 | AZ36: 3.11
A37: 新增用户月平均登录天数 | N37: 2.16 | O37: 2.09 | P37: 2.09 | Q37: 2.09 | R37: 2.13 | S37: 2.21 | T37: 2.52 | U37: 2.34 | V37: 2.04 | W37: 2.12 | X37: 2.05 | Y37: 2.12 | Z37: 2.18 | AA37: 2.22 | AB37: 2.22 | AC37: 2.15 | AD37: 2.26 | AE37: 2.33 | AF37: 2.84 | AG37: 2.5 | AH37: 2.1 | AI37: 2.13 | AJ37: 2.07 | AK37: 2.13 | AL37: 2.2 | AM37: 2.02 | AN37: 2.14 | AO37: 2 | AP37: 2 | AQ37: 2.81 | AR37: 3 | AS37: 2.55 | AT37: 2.19 | AU37: 2.13 | AV37: 2.13 | AW37: 2.07 | AX37: 2.08 | AY37: 2.11 | AZ37: 2.3
A38: 留存用户月平均登录天数 | N38: 7.88 | O38: 5.85 | P38: 6.16 | Q38: 6.54 | R38: 6.1 | S38: 6.61 | T38: 7.42 | U38: 6.71 | V38: 5.08 | W38: 5.45 | X38: 4.73 | Y38: 5.07 | Z38: 5.38 | AA38: 6.09 | AB38: 5.37 | AC38: 5.51 | AD38: 5.86 | AE38: 5.97 | AF38: 7.7 | AG38: 7.24 | AH38: 5.43 | AI38: 5.48 | AJ38: 4.91 | AK38: 5.45 | AL38: 6.4 | AM38: 5.04 | AN38: 5.46 | AO38: 5.37 | AP38: 5.26 | AQ38: 5.43 | AR38: 6.82 | AS38: 5.52 | AT38: 4.14 | AU38: 4.34 | AV38: 4.34 | AW38: 4.78 | AX38: 5.01 | AY38: 5.19 | AZ38: 4.64
A39: 回流用户月平均登录天数 | N39: 3.12 | O39: 2.47 | P39: 2.38 | Q39: 2.41 | R39: 2.2 | S39: 2.45 | T39: 2.86 | U39: 2.52 | V39: 2.24 | W39: 2.09 | X39: 1.94 | Y39: 2.1 | Z39: 2.28 | AA39: 2.43 | AB39: 2.32 | AC39: 2.11 | AD39: 2.22 | AE39: 2.59 | AF39: 3.07 | AG39: 2.49 | AH39: 2.11 | AI39: 1.91 | AJ39: 1.87 | AK39: 1.94 | AL39: 2.32 | AM39: 1.96 | AN39: 2.19 | AO39: 2.08 | AP39: 2.13 | AQ39: 2.37 | AR39: 3.04 | AS39: 2.32 | AT39: 2.18 | AU39: 1.96 | AV39: 1.96 | AW39: 1.98 | AX39: 2.03 | AY39: 2.16 | AZ39: 2.12
A41: 总体支付情况 | B41: 201101 | C41: 201102 | D41: 201103 | E41: 201104 | F41: 201105 | G41: 201106 | H41: 201107 | I41: 201108 | J41: 201109 | K41: 201110 | L41: 201111 | M41: 201112 | N41: 201201 | O41: 201202 | P41: 201203 | Q41: 201204 | R41: 201205 | S41: 201206 | T41: 201207 | U41: 201208 | V41: 201209 | W41: 201210 | X41: 201211 | Y41: 201212 | Z41: 201301 | AA41: 201302 | AB41: 201303 | AC41: 201304 | AD41: 201305 | AE41: 201306 | AF41: 201307 | AG41: 201308 | AH41: 201309 | AI41: 201310 | AJ41: 201311 | AK41: 201312 | AL41: 201401 | AM41: 201402 | AN41: 201403 | AO41: 201404 | AP41: 201405 | AQ41: 201406 | AR41: 201407 | AS41: 201408 | AT41: 201409 | AU41: 201410 | AV41: 201411 | AW41: 201412 | AX41: 201501 | AY41: 201502 | AZ41: 201503
A42: 付费总额 | B42: 32123599 | C42: 36894506 | D42: 23967439 | E42: 25757499 | F42: 21695812 | G42: 19546261 | H42: 18555169 | I42: 18883212 | J42: 12327202 | K42: 11273181 | L42: 9352357.6 | M42: 10672723 | N42: 15107847 | O42: 17229893 | P42: 12579458 | Q42: 12110076 | R42: 13887055 | S42: 15231927 | T42: 13945913 | U42: 10252351 | V42: 7147410.5 | W42: 6010753 | X42: 6607620.3 | Y42: 7330241.2 | Z42: 7951642.9 | AA42: 14174713 | AB42: 12715791 | AC42: 10381787 | AD42: 11472833 | AE42: 13837517 | AF42: 17639904 | AG42: 18855919 | AH42: 13175383 | AI42: 11418264 | AJ42: 9723287 | AK42: 9048428.8 | AL42: 12083997 | AM42: 13695893 | AN42: 9289421 | AO42: 7855976.6 | AP42: 8733128.7 | AQ42: 10963147 | AR42: 14526363 | AS42: 11163794 | AT42: 8917664.1 | AU42: 8006488.3 | AV42: 7076763.9 | AW42: 7449044.6 | AX42: 8069678.1 | AY42: 10724108 | AZ42: 9691534
A43: 付费总额增长率 | B43: 0.4322 | C43: 0.1485 | D43: -0.3504 | E43: 0.0747 | F43: -0.1577 | G43: -0.0991 | H43: -0.0507 | I43: 0.0177 | J43: -0.3472 | K43: -0.0855 | L43: -0.1704 | M43: 0.1412 | N43: 0 | O43: 0.1405 | P43: -0.2699 | Q43: -0.0373 | R43: 0.1467 | S43: 0.0968 | T43: -0.0844 | U43: -0.2648 | V43: -0.3029 | W43: -0.159 | X43: 0.0993 | Y43: 0.1094 | Z43: 0.0848 | AA43: 0.7826 | AB43: -0.1029 | AC43: -0.1836 | AD43: 0.1051 | AE43: 0.2061 | AF43: 0.2748 | AG43: 0.0689 | AH43: -0.3013 | AI43: -0.1334 | AJ43: -0.1484 | AK43: -0.0694 | AL43: 0.3355 | AM43: 0.1334 | AN43: -0.3217 | AO43: -0.1543 | AP43: 0.1117 | AQ43: 0.2554 | AR43: 0.325 | AS43: -0.2315 | AT43: -0.2012 | AU43: -0.1022 | AV43: -0.1161 | AW43: 0.0526 | AX43: 0.0833 | AY43: 0.3289 | AZ43: -0.0963
A44: 付费用户数 | B44: 951556 | C44: 930502 | D44: 715065 | E44: 672335 | F44: 609372 | G44: 555646 | H44: 555608 | I44: 525022 | J44: 407203 | K44: 402263 | L44: 331276 | M44: 377444 | N44: 468933 | O44: 450339 | P44: 430161 | Q44: 426599 | R44: 409281 | S44: 458968 | T44: 424785 | U44: 306266 | V44: 240381 | W44: 230387 | X44: 201997 | Y44: 216266 | Z44: 276391 | AA44: 345462 | AB44: 310129 | AC44: 268003 | AD44: 288628 | AE44: 333925 | AF44: 442268 | AG44: 404959 | AH44: 333829 | AI44: 309436 | AJ44: 256210 | AK44: 251817 | AL44: 304621 | AM44: 267265 | AN44: 231139 | AO44: 212478 | AP44: 199994 | AQ44: 234415 | AR44: 307104 | AS44: 210059 | AT44: 165359 | AU44: 149868 | AV44: 139102 | AW44: 146569 | AX44: 143817 | AY44: 162018 | AZ44: 162360
A45: 付费用户增长率 | B45: 0.295 | C45: -0.0221 | D45: -0.2315 | E45: -0.0598 | F45: -0.0936 | G45: -0.0882 | H45: -0.0001 | I45: -0.055 | J45: -0.2244 | K45: -0.0121 | L45: -0.1765 | M45: 0.1394 | N45: 0 | O45: -0.0397 | P45: -0.0448 | Q45: -0.0083 | R45: -0.0406 | S45: 0.1214 | T45: -0.0745 | U45: -0.279 | V45: -0.2151 | W45: -0.0416 | X45: -0.1232 | Y45: 0.0706 | Z45: 0.278 | AA45: 0.2499 | AB45: -0.1023 | AC45: -0.1358 | AD45: 0.077 | AE45: 0.1569 | AF45: 0.3245 | AG45: -0.0844 | AH45: -0.1756 | AI45: -0.0731 | AJ45: -0.172 | AK45: -0.0171 | AL45: 0.2097 | AM45: -0.1226 | AN45: -0.1352 | AO45: -0.0807 | AP45: -0.0588 | AQ45: 0.1721 | AR45: 0.3101 | AS45: -0.316 | AT45: -0.2128 | AU45: -0.0937 | AV45: -0.0718 | AW45: 0.0537 | AX45: -0.0188 | AY45: 0.1266 | AZ45: 0.0021
A46: 纯新增付费用户数 | B46: 43067 | C46: 36829 | D46: 27252 | E46: 23442 | F46: 20277 | G46: 19694 | H46: 28788 | I46: 24346 | J46: 15667 | K46: 14916 | L46: 8230 | M46: 12811 | N46: 31307 | O46: 27961 | P46: 24032 | Q46: 27957 | R46: 21667 | S46: 31815 | T46: 33939 | U46: 19633 | V46: 12417 | W46: 13524 | X46: 10564 | Y46: 14320 | Z46: 19716 | AA46: 30180 | AB46: 25505 | AC46: 19300 | AD46: 22278 | AE46: 35265 | AF46: 58167 | AG46: 33024 | AH46: 21092 | AI46: 22137 | AJ46: 19689 | AK46: 17843 | AL46: 26441 | AM46: 20155 | AN46: 20243 | AO46: 16045 | AP46: 18813 | AQ46: 43367 | AR46: 54035 | AS46: 24234 | AT46: 16921 | AU46: 16812 | AV46: 14916 | AW46: 12328 | AX46: 14817 | AY46: 19290 | AZ46: 20987
A47: 历史转化新增付费用户数 | B47: 162095 | C47: 168689 | D47: 110646 | E47: 94132 | F47: 76878 | G47: 70649 | H47: 75385 | I47: 70196 | J47: 54682 | K47: 53808 | L47: 40788 | M47: 42231 | N47: 62548 | O47: 67805 | P47: 60603 | Q47: 61088 | R47: 56116 | S47: 65587 | T47: 62951 | U47: 39028 | V47: 31229 | W47: 29811 | X47: 24707 | Y47: 27135 | Z47: 42244 | AA47: 62650 | AB47: 58129 | AC47: 47882 | AD47: 52285 | AE47: 60850 | AF47: 87222 | AG47: 88886 | AH47: 73813 | AI47: 65750 | AJ47: 41795 | AK47: 40412 | AL47: 56339 | AM47: 47201 | AN47: 38528 | AO47: 35646 | AP47: 27128 | AQ47: 31989 | AR47: 55051 | AS47: 33682 | AT47: 26381 | AU47: 21233 | AV47: 20231 | AW47: 25669 | AX47: 21400 | AY47: 24493 | AZ47: 27668
A48: 活跃付费用户数 | B48: 423016 | C48: 453254 | D48: 391050 | E48: 348444 | F48: 331969 | G48: 293660 | H48: 252102 | I48: 252519 | J48: 208774 | K48: 197632 | L48: 181502 | M48: 179282 | N48: 192581 | O48: 206961 | P48: 217899 | Q48: 217064 | R48: 213491 | S48: 215028 | T48: 203066 | U48: 164179 | V48: 126077 | W48: 119387 | X48: 113396 | Y48: 111737 | Z48: 114769 | AA48: 118261 | AB48: 131720 | AC48: 127341 | AD48: 127041 | AE48: 130822 | AF48: 150875 | AG48: 173104 | AH48: 156273 | AI48: 148962 | AJ48: 130010 | AK48: 123540 | AL48: 124301 | AM48: 124720 | AN48: 109865 | AO48: 102686 | AP48: 97580 | AQ48: 87745 | AR48: 100503 | AS48: 92441 | AT48: 75096 | AU48: 71973 | AV48: 67964 | AW48: 68554 | AX48: 64837 | AY48: 63745 | AZ48: 67412
A49: 回流付费用户数 | B49: 323379 | C49: 271730 | D49: 186117 | E49: 206317 | F49: 180248 | G49: 171643 | H49: 199333 | I49: 177961 | J49: 128080 | K49: 135907 | L49: 100756 | M49: 143120 | N49: 183819 | O49: 147089 | P49: 127221 | Q49: 120127 | R49: 117584 | S49: 146223 | T49: 124598 | U49: 83285 | V49: 70563 | W49: 67591 | X49: 53260 | Y49: 63001 | Z49: 99551 | AA49: 134235 | AB49: 94666 | AC49: 73388 | AD49: 86918 | AE49: 106708 | AF49: 145686 | AG49: 109765 | AH49: 82489 | AI49: 72482 | AJ49: 60093 | AK49: 66634 | AL49: 93066 | AM49: 71892 | AN49: 59935 | AO49: 55994 | AP49: 54852 | AQ49: 69465 | AR49: 95015 | AS49: 58380 | AT49: 46020 | AU49: 39148 | AV49: 35389 | AW49: 39311 | AX49: 42135 | AY49: 53734 | AZ49: 45568
A50: 纯新增付费用户占比 | B50: 0.0453 | C50: 0.0396 | D50: 0.0381 | E50: 0.0349 | F50: 0.0333 | G50: 0.0354 | H50: 0.0518 | I50: 0.0464 | J50: 0.0385 | K50: 0.0371 | L50: 0.0248 | M50: 0.0339 | N50: 0.0668 | O50: 0.0621 | P50: 0.0559 | Q50: 0.0655 | R50: 0.0529 | S50: 0.0693 | T50: 0.0799 | U50: 0.0641 | V50: 0.0517 | W50: 0.0587 | X50: 0.0523 | Y50: 0.0662 | Z50: 0.0713 | AA50: 0.0874 | AB50: 0.0822 | AC50: 0.072 | AD50: 0.0772 | AE50: 0.1056 | AF50: 0.1315 | AG50: 0.0815 | AH50: 0.0632 | AI50: 0.0715 | AJ50: 0.0768 | AK50: 0.0709 | AL50: 0.0868 | AM50: 0.0754 | AN50: 0.0876 | AO50: 0.0755 | AP50: 0.0941 | AQ50: 0.185 | AR50: 0.176 | AS50: 0.1154 | AT50: 0.1023 | AU50: 0.1122 | AV50: 0.1072 | AW50: 0.0841 | AX50: 0.103 | AY50: 0.1191 | AZ50: 0.1293
A51: 历史转化新增付费用户占比 | B51: 0.1703 | C51: 0.1813 | D51: 0.1547 | E51: 0.14 | F51: 0.1262 | G51: 0.1271 | H51: 0.1357 | I51: 0.1337 | J51: 0.1343 | K51: 0.1338 | L51: 0.1231 | M51: 0.1119 | N51: 0.1334 | O51: 0.1506 | P51: 0.1409 | Q51: 0.1432 | R51: 0.1371 | S51: 0.1429 | T51: 0.1482 | U51: 0.1274 | V51: 0.1299 | W51: 0.1294 | X51: 0.1223 | Y51: 0.1255 | Z51: 0.1528 | AA51: 0.1814 | AB51: 0.1874 | AC51: 0.1787 | AD51: 0.1812 | AE51: 0.1822 | AF51: 0.1972 | AG51: 0.2195 | AH51: 0.2211 | AI51: 0.2125 | AJ51: 0.1631 | AK51: 0.1605 | AL51: 0.1849 | AM51: 0.1766 | AN51: 0.1667 | AO51: 0.1678 | AP51: 0.1356 | AQ51: 0.1365 | AR51: 0.1793 | AS51: 0.1603 | AT51: 0.1595 | AU51: 0.1417 | AV51: 0.1454 | AW51: 0.1751 | AX51: 0.1488 | AY51: 0.1512 | AZ51: 0.1704
A52: 活跃付费用户占比 | B52: 0.4446 | C52: 0.4871 | D52: 0.5469 | E52: 0.5183 | F52: 0.5448 | G52: 0.5285 | H52: 0.4537 | I52: 0.481 | J52: 0.5127 | K52: 0.4913 | L52: 0.5479 | M52: 0.475 | N52: 0.4107 | O52: 0.4596 | P52: 0.5066 | Q52: 0.5088 | R52: 0.5216 | S52: 0.4685 | T52: 0.478 | U52: 0.5361 | V52: 0.5245 | W52: 0.5182 | X52: 0.5614 | Y52: 0.5167 | Z52: 0.4152 | AA52: 0.3423 | AB52: 0.4247 | AC52: 0.4751 | AD52: 0.4402 | AE52: 0.3918 | AF52: 0.3411 | AG52: 0.4275 | AH52: 0.4681 | AI52: 0.4814 | AJ52: 0.5074 | AK52: 0.4906 | AL52: 0.4081 | AM52: 0.4667 | AN52: 0.4753 | AO52: 0.4833 | AP52: 0.4879 | AQ52: 0.3743 | AR52: 0.3273 | AS52: 0.4401 | AT52: 0.4541 | AU52: 0.4802 | AV52: 0.4886 | AW52: 0.4677 | AX52: 0.4508 | AY52: 0.3934 | AZ52: 0.4152
... A71: 按条支付arppu值增长率 | B71: 0.1986 | C71: 0.1544 | D71: -0.1476 | E71: 0.256 | F71: -0.2042 | G71: 0.0455 | H71: 0.0352 | I71: 0.0685 | J71: -0.1942 | K71: 0.0051 | L71: -0.0034 | M71: -0.1177 | N71: 0 | O71: 0.2427 | P71: -0.1849 | Q71: -0.0822 | R71: 0.1439 | S71: 0.0571 | T71: -0.0266 | U71: 0.1157 | V71: -0.1119 | W71: -0.1123 | X71: 0.3148 | Y71: 0.1328 | Z71: -0.3241 | AA71: 0.2318 | AB71: 0.0977 | AC71: 0.0356 | AD71: 0.0022 | AE71: 0.0147 | AF71: -0.0629 | AG71: 0.1455 | AH71: -0.2192 | AI71: 0.0088 | AJ71: 0.0988 | AK71: -0.0416 | AL71: 0 | AM71: 0.1698 | AN71: -0.0873 | AO71: -0.028 | AP71: 0.3592 | AQ71: 0.0896 | AR71: -0.0624 | AS71: 0.1811 | AT71: 0.0775 | AU71: 0.0381 | AV71: -0.1072 | AW71: -0.2056 | AX71: 0.1869 | AY71: 0.2215 | AZ71: -0.1024
A74: 约瑟传说
A75: 活跃在线情况 | B75: 201101 | C75: 201102 | D75: 201103 | E75: 201104 | F75: 201105 | G75: 201106 | H75: 201107 | I75: 201108 | J75: 201109 | K75: 201110 | L75: 201111 | M75: 201112 | N75: 201201 | O75: 201202 | P75: 201203 | Q75: 201204 | R75: 201205 | S75: 201206 | T75: 201207 | U75: 201208 | V75: 201209 | W75: 201210 | X75: 201211 | Y75: 201212 | Z75: 201301 | AA75: 201302 | AB75: 201303 | AC75: 201304 | AD75: 201305 | AE75: 201306 | AF75: 201307 | AG75: 201308 | AH75: 201309 | AI75: 201310 | AJ75: 201311 | AK75: 201312 | AL75: 201401 | AM75: 201402 | AN75: 201403 | AO75: 201404 | AP75: 201405 | AQ75: 201406 | AR75: 201407 | AS75: 201408 | AT75: 201409 | AU75: 201410 | AV75: 201411 | AW75: 201412 | AX75: 201501 | AY75: 201502 | AZ75: 201503
A76: 活跃用户 | B76: 0 | C76: 0 | D76: 0 | E76: 0 | F76: 0 | G76: 0 | H76: 4243041 | I76: 4605577 | J76: 2423211 | K76: 2534908 | L76: 1794138 | M76: 1665484 | N76: 3006820 | O76: 2541497 | P76: 2348413 | Q76: 3535012 | R76: 3115068 | S76: 3374948 | T76: 3895428 | U76: 4008431 | V76: 2435229 | W76: 2444548 | X76: 1730399 | Y76: 1897657 | Z76: 2947368 | AA76: 3079738 | AB76: 2308778 | AC76: 2268731 | AD76: 2089460 | AE76: 2387729 | AF76: 3979432 | AG76: 3531009 | AH76: 2056121 | AI76: 2132995 | AJ76: 1664045 | AK76: 1336817 | AL76: 2061577 | AM76: 2060237 | AN76: 1936115 | AO76: 1932187 | AP76: 2155426 | AQ76: 2507040 | AR76: 3475928 | AS76: 3150670 | AT76: 1529678 | AU76: 1858434 | AV76: 1652894 | AW76: 1394709 | AX76: 1589817 | AY76: 2132994 | AZ76: 1426820
A77: 活跃用户增长率 | B77: 0 | C77: 0 | D77: 0 | E77: 0 | F77: 0 | G77: 0 | H77: 0 | I77: 0.0854 | J77: -0.4739 | K77: 0.0461 | L77: -0.2922 | M77: -0.0717 | N77: =N76/M76-1 -> 0.80537309 | O77: -0.1548 | P77: -0.076 | Q77: 0.5053 | R77: -0.1188 | S77: 0.0834 | T77: 0.1542 | U77: 0.029 | V77: -0.3925 | W77: 0.0038 | X77: -0.2921 | Y77: 0.0967 | Z77: 0.5532 | AA77: 0.0449 | AB77: -0.2503 | AC77: -0.0173 | AD77: -0.079 | AE77: 0.1427 | AF77: 0.6666 | AG77: -0.1127 | AH77: -0.4177 | AI77: 0.0374 | AJ77: -0.2199 | AK77: -0.1966 | AL77: 0.5422 | AM77: -0.0006 | AN77: -0.0602 | AO77: -0.002 | AP77: 0.1155 | AQ77: 0.1631 | AR77: 0.3865 | AS77: -0.0936 | AT77: -0.5145 | AU77: 0.2149 | AV77: -0.1106 | AW77: -0.1562 | AX77: 0.1399 | AY77: 0.3417 | AZ77: -0.3311
A78: 有效活跃用户 | B78: 0 | C78: 0 | D78: 0 | E78: 0 | F78: 0 | G78: 0 | H78: 1615584 | I78: 1901898 | J78: 899502 | K78: 934459 | L78: 691778 | M78: 630651 | N78: 1066 | O78: 493 | P78: 592750 | Q78: 1374986 | R78: 1244311 | S78: 1419263 | T78: 1782889 | U78: 1534539 | V78: 401358 | W78: 677435 | X78: 668480 | Y78: 756073 | Z78: 1118565 | AA78: 1109676 | AB78: 782812 | AC78: 747039 | AD78: 708557 | AE78: 797583 | AF78: 1353575 | AG78: 1182107 | AH78: 666239 | AI78: 711291 | AJ78: 535287 | AK78: 460885 | AL78: 737319 | AM78: 750843 | AN78: 705283 | AO78: 706584 | AP78: 754423 | AQ78: 862607 | AR78: 969710 | AS78: 822794 | AT78: 375606 | AU78: 557784 | AV78: 484786 | AW78: 414348 | AX78: 481421 | AY78: 610315 | AZ78: 378625
A79: 有效活跃用户增长率 | B79: 0 | C79: 0 | D79: 0 | E79: 0 | F79: 0 | G79: 0 | H79: 0 | I79: 0.1772 | J79: -0.5271 | K79: 0.0389 | L79: -0.2597 | M79: -0.0884 | N79: =N78/M78-1 -> -0.99830968 | O79: -0.5375 | P79: 1201.3327 | Q79: 1.3197 | R79: -0.095 | S79: 0.1406 | T79: 0.2562 | U79: -0.1393 | V79: -0.7385 | W79: 0.6879 | X79: -0.0132 | Y79: 0.131 | Z79: 0.4794 | AA79: -0.0079 | AB79: -0.2946 | AC79: -0.0457 | AD79: -0.0515 | AE79: 0.1256 | AF79: 0.6971 | AG79: -0.1267 | AH79: -0.4364 | AI79: 0.0676 | AJ79: -0.2474 | AK79: -0.139 | AL79: 0.5998 | AM79: 0.0183 | AN79: -0.0607 | AO79: 0.0018 | AP79: 0.0677 | AQ79: 0.1434 | AR79: 0.1242 | AS79: -0.1515 | AT79: -0.5435 | AU79: 0.485 | AV79: -0.1309 | AW79: -0.1453 | AX79: 0.1619 | AY79: 0.2677 | AZ79: -0.3796
A80: 新增活跃用户占比 | B80: 0 | C80: 0 | D80: 0 | E80: 0 | F80: 0 | G80: 0 | H80: 1 | I80: 0.6458 | J80: 0.4659 | K80: 0.4647 | L80: 0.3941 | M80: 0.4206 | N80: 0.5529 | O80: 0.5042 | P80: 0.5083 | Q80: 0.6042 | R80: 0.5352 | S80: 0.5101 | T80: 0.56 | U80: 0.5771 | V80: 0.496 | W80: 0.5048 | X80: 0.4746 | Y80: 0.4929 | Z80: 0.5654 | AA80: 0.5547 | AB80: 0.5363 | AC80: 0.5232 | AD80: 0.5196 | AE80: 0.5524 | AF80: 0.6418 | AG80: 0.6154 | AH80: 0.5444 | AI80: 0.5508 | AJ80: 0.5256 | AK80: 0.53 | AL80: 0.5939 | AM80: 0.5874 | AN80: 0.586 | AO80: 0.5886 | AP80: 0.6149 | AQ80: 0.63 | AR80: 0.6736 | AS80: 0.679 | AT80: 0.6173 | AU80: 0.6552 | AV80: 0.6169 | AW80: 0.5876 | AX80: 0.6116 | AY80: 0.6537 | AZ80: 0.6125
A81: 留存用户占比 | B81: 0 | C81: 0 | D81: 0 | E81: 0 | F81: 0 | G81: 0 | H81: 0 | I81: 0.3762 | J81: 0.4878 | K81: 0.3847 | L81: 0.4801 | M81: 0.4212 | N81: 0.242 | O81: 0.3584 | P81: 0.3408 | Q81: 0.2551 | R81: 0.3488 | S81: 0.3392 | T81: 0.3052 | U81: 0.3056 | V81: 0.3774 | W81: 0.3192 | X81: 0.3538 | Y81: 0.293 | Z81: 0.2244 | AA81: 0.2651 | AB81: 0.2869 | AC81: 0.2766 | AD81: 0.2901 | AE81: 0.2468 | AF81: 0.1838 | AG81: 0.2574 | AH81: 0.3138 | AI81: 0.274 | AJ81: 0.3079 | AK81: 0.2924 | AL81: 0.2016 | AM81: 0.2633 | AN81: 0.2757 | AO81: 0.2701 | AP81: 0.2526 | AQ81: 0.2429 | AR81: 0.204 | AS81: 0.2171 | AT81: 0.2717 | AU81: 0.1998 | AV81: 0.2518 | AW81: 0.276 | AX81: 0.2386 | AY81: 0.1988 | AZ81: 0.2683
A82: 回流用户占比 | B82: 0 | C82: 0 | D82: 0 | E82: 0 | F82: 0 | G82: 0 | H82: 0 | I82: 0.0096 | J82: 0.0724 | K82: 0.1689 | L82: 0.1457 | M82: 0.173 | N82: 0.2051 | O82: 0.1374 | P82: 0.151 | Q82: 0.1407 | R82: 0.116 | S82: 0.1507 | T82: 0.1348 | U82: 0.1174 | V82: 0.1265 | W82: 0.176 | X82: 0.1717 | Y82: 0.2141 | Z82: 0.2102 | AA82: 0.1802 | AB82: 0.1768 | AC82: 0.2002 | AD82: 0.1903 | AE82: 0.2008 | AF82: 0.1744 | AG82: 0.1272 | AH82: 0.1418 | AI82: 0.1753 | AJ82: 0.1665 | AK82: 0.1776 | AL82: 0.2045 | AM82: 0.1493 | AN82: 0.1382 | AO82: 0.1413 | AP82: 0.1325 | AQ82: 0.1271 | AR82: 0.1225 | AS82: 0.1039 | AT82: 0.111 | AU82: 0.145 | AV82: 0.1313 | AW82: 0.1364 | AX82: 0.1497 | AY82: 0.1475 | AZ82: 0.1192
A83: 新增注册角色 | B83: 0 | C83: 0 | D83: 0 | E83: 0 | F83: 0 | G83: 0 | H83: 4475043 | I83: 3005179 | J83: 1136820 | K83: 1186994 | L83: 718025 | M83: 706542 | N83: 1822899 | O83: 1412911 | P83: 1306380 | Q83: 2307024 | R83: 1792123 | S83: 1908662 | T83: 2406698 | U83: 2032886 | V83: 1338255 | W83: 1367726 | X83: 906534 | Y83: 1044249 | Z83: 1804322 | AA83: 1878905 | AB83: 1359699 | AC83: 1294983 | AD83: 1189462 | AE83: 1441340 | AF83: 2755309 | AG83: 2354967 | AH83: 1228218 | AI83: 1280481 | AJ83: 961570 | AK83: 772125 | AL83: 1314890 | AM83: 1301764 | AN83: 1240218 | AO83: 1230213 | AP83: 1426855 | AQ83: 1694630 | AR83: 2540337 | AS83: 2256545 | AT83: 1025527 | AU83: 1302851 | AV83: 1102219 | AW83: 891165 | AX83: 1051355 | AY83: 1499558 | AZ83: 947063
A84: 新增注册角色增长率 | B84: 0 | C84: 0 | D84: 0 | E84: 0 | F84: 0 | G84: 0 | H84: 0 | I84: -0.3285 | J84: -0.6217 | K84: 0.0441 | L84: -0.3951 | M84: -0.016 | N84: 0 | O84: -0.2249 | P84: -0.0754 | Q84: 0.766 | R84: -0.2232 | S84: 0.065 | T84: 0.2609 | U84: -0.1553 | V84: -0.3417 | W84: 0.022 | X84: -0.3372 | Y84: 0.1519 | Z84: 0.7279 | AA84: 0.0413 | AB84: -0.2763 | AC84: -0.0476 | AD84: -0.0815 | AE84: 0.2118 | AF84: 0.9116 | AG84: -0.1453 | AH84: -0.4785 | AI84: 0.0426 | AJ84: -0.2491 | AK84: -0.197 | AL84: 0.7029 | AM84: -0.01 | AN84: -0.0473 | AO84: -0.0081 | AP84: 0.1598 | AQ84: 0.1877 | AR84: 0.4991 | AS84: -0.1117 | AT84: -0.5455 | AU84: 0.2704 | AV84: -0.154 | AW84: -0.1915 | AX84: 0.1798 | AY84: 0.4263 | AZ84: -0.3684
A85: 新增活跃用户 | B85: 0 | C85: 0 | D85: 0 | E85: 0 | F85: 0 | G85: 0 | H85: 4243008 | I85: 2974413 | J85: 1128939 | K85: 1178061 | L85: 707148 | M85: 700534 | N85: 1662590 | O85: 1281365 | P85: 1193637 | Q85: 2136017 | R85: 1667149 | S85: 1721589 | T85: 2181331 | U85: 2313149 | V85: 1207944 | W85: 1234009 | X85: 821174 | Y85: 935392 | Z85: 1666562 | AA85: 1708248 | AB85: 1238214 | AC85: 1187059 | AD85: 1085663 | AE85: 1319024 | AF85: 2553952 | AG85: 2173158 | AH85: 1119309 | AI85: 1174788 | AJ85: 874703 | AK85: 708476 | AL85: 1224369 | AM85: 1210181 | AN85: 1134637 | AO85: 1137241 | AP85: 1325370 | AQ85: 1579536 | AR85: 2341218 | AS85: 2139268 | AT85: 944285 | AU85: 1217695 | AV85: 1019593 | AW85: 819536 | AX85: 972391 | AY85: 1394299 | AZ85: 873944
A86: 新增活跃用户增长率 | B86: 0 | C86: 0 | D86: 0 | E86: 0 | F86: 0 | G86: 0 | H86: 0 | I86: -0.299 | J86: -0.6204 | K86: 0.0435 | L86: -0.3997 | M86: -0.0094 | N86: 0 | O86: -0.2293 | P86: -0.0685 | Q86: 0.7895 | R86: -0.2195 | S86: 0.0327 | T86: 0.267 | U86: 0.0604 | V86: -0.4778 | W86: 0.0216 | X86: -0.3345 | Y86: 0.1391 | Z86: 0.7817 | AA86: 0.025 | AB86: -0.2752 | AC86: -0.0413 | AD86: -0.0854 | AE86: 0.2149 | AF86: 0.9362 | AG86: -0.1491 | AH86: -0.4849 | AI86: 0.0496 | AJ86: -0.2554 | AK86: -0.19 | AL86: 0.7282 | AM86: -0.0116 | AN86: -0.0624 | AO86: 0.0023 | AP86: 0.1654 | AQ86: 0.1918 | AR86: 0.4822 | AS86: -0.0863 | AT86: -0.5586 | AU86: 0.2895 | AV86: -0.1627 | AW86: -0.1962 | AX86: 0.1865 | AY86: 0.4339 | AZ86: -0.3732
A87: 留存用户 | B87: 0 | C87: 0 | D87: 0 | E87: 0 | F87: 0 | G87: 0 | H87: 0 | I87: 1732410 | J87: 1182117 | K87: 975163 | L87: 861428 | M87: 701430 | N87: 727605 | O87: 910992 | P87: 800280 | Q87: 901788 | R87: 1086427 | S87: 1144818 | T87: 1188961 | U87: 1224824 | V87: 919144 | W87: 780209 | X87: 612156 | Y87: 556042 | Z87: 661260 | AA87: 816371 | AB87: 662425 | AC87: 627499 | AD87: 606146 | AE87: 589321 | AF87: 731518 | AG87: 908788 | AH87: 645302 | AI87: 584397 | AJ87: 512337 | AK87: 390900 | AL87: 415535 | AM87: 542436 | AN87: 533882 | AO87: 521863 | AP87: 544517 | AQ87: 608939 | AR87: 709043 | AS87: 683991 | AT87: 415549 | AU87: 371259 | AV87: 416275 | AW87: 384895 | AX87: 379403 | AY87: 424040 | AZ87: 382774
A88: 留存用户增长率 | B88: 0 | C88: 0 | D88: 0 | E88: 0 | F88: 0 | G88: 0 | H88: 0 | I88: 0 | J88: -0.3176 | K88: -0.1751 | L88: -0.1166 | M88: -0.1857 | N88: 0 | O88: 0.252 | P88: -0.1215 | Q88: 0.1268 | R88: 0.2047 | S88: 0.0537 | T88: 0.0386 | U88: 0.0302 | V88: -0.2496 | W88: -0.1512 | X88: -0.2154 | Y88: -0.0917 | Z88: 0.1892 | AA88: 0.2346 | AB88: -0.1886 | AC88: -0.0527 | AD88: -0.034 | AE88: -0.0278 | AF88: 0.2413 | AG88: 0.2423 | AH88: -0.2899 | AI88: -0.0944 | AJ88: -0.1233 | AK88: -0.237 | AL88: 0.063 | AM88: 0.3054 | AN88: -0.0158 | AO88: -0.0225 | AP88: 0.0434 | AQ88: 0.1183 | AR88: 0.1644 | AS88: -0.0353 | AT88: -0.3925 | AU88: -0.1066 | AV88: 0.1213 | AW88: -0.0754 | AX88: -0.0143 | AY88: 0.1177 | AZ88: -0.0973
A89: 回流用户 | B89: 0 | C89: 0 | D89: 0 | E89: 0 | F89: 0 | G89: 0 | H89: 33 | I89: 43992 | J89: 175394 | K89: 428076 | L89: 261399 | M89: 288179 | N89: 616625 | O89: 349140 | P89: 354496 | Q89: 497207 | R89: 361492 | S89: 508541 | T89: 525136 | U89: 470458 | V89: 308141 | W89: 430330 | X89: 297069 | Y89: 406223 | Z89: 619546 | AA89: 555119 | AB89: 408139 | AC89: 454173 | AD89: 397651 | AE89: 479384 | AF89: 693962 | AG89: 449063 | AH89: 291510 | AI89: 373810 | AJ89: 277005 | AK89: 237441 | AL89: 421673 | AM89: 307620 | AN89: 267596 | AO89: 273083 | AP89: 285539 | AQ89: 318565 | AR89: 425667 | AS89: 327411 | AT89: 169844 | AU89: 269480 | AV89: 217026 | AW89: 190278 | AX89: 238023 | AY89: 314655 | AZ89: 170102
A90: 回流用户增长率 | B90: 0 | C90: 0 | D90: 0 | E90: 0 | F90: 0 | G90: 0 | H90: 0 | I90: 1332.0909 | J90: 2.987 | K90: 1.4407 | L90: -0.3894 | M90: 0.1024 | N90: 0 | O90: -0.4338 | P90: 0.0153 | Q90: 0.4026 | R90: -0.273 | S90: 0.4068 | T90: 0.0326 | U90: -0.1041 | V90: -0.345 | W90: 0.3965 | X90: -0.3097 | Y90: 0.3674 | Z90: 0.5251 | AA90: -0.104 | AB90: -0.2648 | AC90: 0.1128 | AD90: -0.1245 | AE90: 0.2055 | AF90: 0.4476 | AG90: -0.3529 | AH90: -0.3508 | AI90: 0.2823 | AJ90: -0.259 | AK90: -0.1428 | AL90: 0.7759 | AM90: -0.2705 | AN90: -0.1301 | AO90: 0.0205 | AP90: 0.0456 | AQ90: 0.1157 | AR90: 0.3362 | AS90: -0.2308 | AT90: -0.4813 | AU90: 0.5866 | AV90: -0.1946 | AW90: -0.1232 | AX90: 0.2509 | AY90: 0.322 | AZ90: -0.4594
A91: 流失用户 | B91: 0 | C91: 0 | D91: 0 | E91: 0 | F91: 0 | G91: 0 | H91: 0 | I91: 2510631 | J91: 3423460 | K91: 1448048 | L91: 1673480 | M91: 1092708 | N91: 937879 | O91: 2095828 | P91: 1741217 | Q91: 1446625 | R91: 2448585 | S91: 1970250 | T91: 2185987 | U91: 2670604 | V91: 3089287 | W91: 1655020 | X91: 1832392 | Y91: 1174357 | Z91: 1236397 | AA91: 2130997 | AB91: 2417313 | AC91: 1681279 | AD91: 1662585 | AE91: 1500139 | AF91: 1656211 | AG91: 3070644 | AH91: 2885707 | AI91: 1485116 | AJ91: 1620658 | AK91: 1273145 | AL91: 921282 | AM91: 1519141 | AN91: 1526355 | AO91: 1414252 | AP91: 1387670 | AQ91: 1546487 | AR91: 1797997 | AS91: 2791937 | AT91: 2735121 | AU91: 1158419 | AV91: 1442159 | AW91: 1267999 | AX91: 1015306 | AY91: 1165777 | AZ91: 1750220
... A104: ACU增长率 | B104: 0 | C104: 0 | D104: 0 | E104: 0 | F104: 0 | G104: 0 | H104: 0 | I104: 0.1692 | J104: -0.5597 | K104: 0.1802 | L104: -0.2185 | M104: -0.0927 | N104: 1.0479 | O104: -0.2456 | P104: -0.1864 | Q104: 0.6129 | R104: -0.1503 | S104: 0.2746 | T104: 0.3823 | U104: -0.1307 | V104: -0.527 | W104: -0.0663 | X104: -0.2766 | Y104: 0.0792 | Z104: 0.4965 | AA104: 0.1802 | AB104: -0.4436 | AC104: -0.0231 | AD104: -0.0475 | AE104: 0.3682 | AF104: 0.6909 | AG104: -0.0683 | AH104: -0.5412 | AI104: 0.053 | AJ104: -0.218 | AK104: -0.0768 | AL104: 0.7408 | AM104: 0.0148 | AN104: -0.2387 | AO104: 0.0397 | AP104: -0.0001 | AQ104: 0.2393 | AR104: 0.136 | AS104: -0.1593 | AT104: -0.5972 | AU104: 0.698 | AV104: -0.1693 | AW104: -0.179 | AX104: 0.1803 | AY104: 0.7061 | AZ104: -0.507
A105: 活跃用户日平均在线时长 | N105: 71.053 | O105: 69 | P105: 1525 | Q105: 3131 | R105: 2993 | S105: 3210 | T105: 3645 | U105: 3234 | V105: 1347 | W105: 2182 | X105: 3170 | Y105: 3214 | Z105: 3300 | AA105: 3218 | AB105: 2856 | AC105: 2828 | AD105: 2913 | AE105: 3322 | AF105: 3297 | AG105: 3229 | AH105: 2642 | AI105: 2768 | AJ105: 2740 | AK105: 3085 | AL105: 3245 | AM105: 3134 | AN105: 2659 | AO105: 2734 | AP105: 2606 | AQ105: 2670 | AR105: 2414 | AS105: 2366 | AT105: 2047 | AU105: 2602 | AV105: 2268 | AW105: 2170 | AX105: 2294 | AY105: 2714 | AZ105: 2273
A106: 新增用户日平均在线时长 | N106: 67.97 | O106: 67 | P106: 1768 | Q106: 2967 | R106: 2878 | S106: 3173 | T106: 3595 | U106: 3069 | V106: 1225 | W106: 2181 | X106: 3046 | Y106: 3177 | Z106: 3247 | AA106: 3202 | AB106: 2801 | AC106: 2725 | AD106: 2736 | AE106: 2912 | AF106: 2921 | AG106: 2858 | AH106: 2422 | AI106: 2511 | AJ106: 2465 | AK106: 2733 | AL106: 2930 | AM106: 2845 | AN106: 2496 | AO106: 2639 | AP106: 2473 | AQ106: 2465 | AR106: 2167 | AS106: 2146 | AT106: 1927 | AU106: 2342 | AV106: 2222 | AW106: 2176 | AX106: 2302 | AY106: 2486 | AZ106: 2053
A107: 留存用户日平均在线时长 | N107: 73.7881 | O107: 71 | P107: 1377 | Q107: 3320 | R107: 3084 | S107: 3269 | T107: 3711 | U107: 3368 | V107: 1444 | W107: 2263 | X107: 3377 | Y107: 3376 | Z107: 3563 | AA107: 3328 | AB107: 3019 | AC107: 3042 | AD107: 3192 | AE107: 3893 | AF107: 3992 | AG107: 3708 | AH107: 2894 | AI107: 3142 | AJ107: 3071 | AK107: 3513 | AL107: 3776 | AM107: 3528 | AN107: 2942 | AO107: 2963 | AP107: 2867 | AQ107: 2962 | AR107: 2801 | AS107: 2726 | AT107: 2240 | AU107: 3144 | AV107: 2426 | AW107: 2237 | AX107: 2350 | AY107: 3083 | AZ107: 2564
A108: 回流用户日平均在线时长 | N108: 67.4722 | O108: 66 | P108: 1572 | Q108: 2897 | R108: 2842 | S108: 3027 | T108: 3481 | U108: 3023 | V108: 1200 | W108: 1865 | X108: 2611 | Y108: 2736 | Z108: 2782 | AA108: 2846 | AB108: 2478 | AC108: 2419 | AD108: 2422 | AE108: 2693 | AF108: 2784 | AG108: 2728 | AH108: 2226 | AI108: 2243 | AJ108: 2194 | AK108: 2450 | AL108: 2780 | AM108: 2678 | AN108: 2203 | AO108: 2268 | AP108: 2216 | AQ108: 2441 | AR108: 2150 | AS108: 2080 | AT108: 1762 | AU108: 2111 | AV108: 1776 | AW108: 1797 | AX108: 2009 | AY108: 2455 | AZ108: 1880
A109: 活跃用户月平均登录天数 | N109: 3.21 | O109: 3.01 | P109: 3.09 | Q109: 2.94 | R109: 3.07 | S109: 3.08 | T109: 3.43 | U109: 2.97 | V109: 2.52 | W109: 2.4 | X109: 2.41 | Y109: 2.41 | Z109: 2.27 | AA109: 2.37 | AB109: 2.21 | AC109: 2.1 | AD109: 2.24 | AE109: 2.27 | AF109: 2.4 | AG109: 2.58 | AH109: 2.41 | AI109: 2.41 | AJ109: 2.36 | AK109: 2.49 | AL109: 2.67 | AM109: 2.54 | AN109: 2.71 | AO109: 2.64 | AP109: 2.58 | AQ109: 2.61 | AR109: 2.44 | AS109: 2.3 | AT109: 2.14 | AU109: 2.39 | AV109: 2.51 | AW109: 2.64 | AX109: 2.58 | AY109: 2.51 | AZ109: 2.38
A110: 新增用户月平均登录天数 | N110: 2 | O110: 1.95 | P110: 1.97 | Q110: 1.93 | R110: 1.92 | S110: 1.94 | T110: 2.16 | U110: 1.88 | V110: 1.65 | W110: 1.69 | X110: 1.68 | Y110: 1.67 | Z110: 1.69 | AA110: 1.65 | AB110: 1.65 | AC110: 1.56 | AD110: 1.61 | AE110: 1.6 | AF110: 1.79 | AG110: 1.91 | AH110: 1.76 | AI110: 1.78 | AJ110: 1.72 | AK110: 1.81 | AL110: 1.94 | AM110: 1.88 | AN110: 2.19 | AO110: 2.17 | AP110: 2.1 | AQ110: 2.01 | AR110: 1.85 | AS110: 1.79 | AT110: 1.63 | AU110: 1.96 | AV110: 1.9 | AW110: 1.88 | AX110: 1.9 | AY110: 1.83 | AZ110: 1.74
A111: 留存用户月平均登录天数 | N111: 6.89 | O111: 4.92 | P111: 5.23 | Q111: 5.68 | R111: 5.1 | S111: 5.13 | T111: 6.05 | U111: 5.3 | V111: 3.87 | W111: 3.87 | X111: 3.71 | Y111: 4.15 | Z111: 4.15 | AA111: 4.27 | AB111: 3.55 | AC111: 3.47 | AD111: 3.73 | AE111: 4.18 | AF111: 4.86 | AG111: 4.5 | AH111: 3.84 | AI111: 4.1 | AJ111: 3.84 | AK111: 4.18 | AL111: 5.29 | AM111: 4.34 | AN111: 4.22 | AO111: 4.07 | AP111: 4.1 | AQ111: 4.46 | AR111: 4.66 | AS111: 4.1 | AT111: 3.48 | AU111: 4.23 | AV111: 4.4 | AW111: 4.7 | AX111: 4.79 | AY111: 4.98 | AZ111: 4.08
A112: 回流用户月平均登录天数 | N112: 2.16 | O112: 1.93 | P112: 2.06 | Q112: 2.29 | R112: 2.26 | S112: 2.32 | T112: 2.77 | U112: 2.32 | V112: 1.86 | W112: 1.77 | X112: 1.74 | Y112: 1.75 | Z112: 1.83 | AA112: 1.81 | AB112: 1.73 | AC112: 1.64 | AD112: 1.7 | AE112: 1.76 | AF112: 2.04 | AG112: 1.95 | AH112: 1.77 | AI112: 1.73 | AJ112: 1.66 | AK112: 1.76 | AL112: 2.22 | AM112: 1.97 | AN112: 1.9 | AO112: 1.84 | AP112: 1.91 | AQ112: 2.06 | AR112: 2 | AS112: 1.88 | AT112: 1.66 | AU112: 1.81 | AV112: 1.71 | AW112: 1.73 | AX112: 1.85 | AY112: 2.17 | AZ112: 1.86
A114: 总体支付情况 | B114: 201101 | C114: 201102 | D114: 201103 | E114: 201104 | F114: 201105 | G114: 201106 | H114: 201107 | I114: 201108 | J114: 201109 | K114: 201110 | L114: 201111 | M114: 201112 | N114: 201201 | O114: 201202 | P114: 201203 | Q114: 201204 | R114: 201205 | S114: 201206 | T114: 201207 | U114: 201208 | V114: 201209 | W114: 201210 | X114: 201211 | Y114: 201212 | Z114: 201301 | AA114: 201302 | AB114: 201303 | AC114: 201304 | AD114: 201305 | AE114: 201306 | AF114: 201307 | AG114: 201308 | AH114: 201309 | AI114: 201310 | AJ114: 201311 | AK114: 201312 | AL114: 201401 | AM114: 201402 | AN114: 201403 | AO114: 201404 | AP114: 201405 | AQ114: 201406 | AR114: 201407 | AS114: 201408 | AT114: 201409 | AU114: 201410 | AV114: 201411 | AW114: 201412 | AX114: 201501 | AY114: 201502 | AZ114: 201503
A115: 付费总额 | B115: 0 | C115: 0 | D115: 0 | E115: 0 | F115: 0 | G115: 0 | H115: 0 | I115: 0 | J115: 0 | K115: 0 | L115: 572740 | M115: 783160 | N115: 1005000 | O115: 820060 | P115: 708240 | Q115: 998290 | R115: 1866480 | S115: 1327820 | T115: 1327649.5 | U115: 773088.8 | V115: 639448.5 | W115: 518603.3 | X115: 667374.4 | Y115: 1086461.8 | Z115: 1222845.8 | AA115: 1738525.3 | AB115: 1517401.3 | AC115: 1448959.9 | AD115: 1496311.4 | AE115: 1719669.8 | AF115: 2467651.5 | AG115: 2394789.6 | AH115: 1474838.4 | AI115: 1380298 | AJ115: 1196802.8 | AK115: 1130068 | AL115: 1744956 | AM115: 1796229 | AN115: 1847866 | AO115: 1392828 | AP115: 1539922 | AQ115: 1857568 | AR115: 1458701 | AS115: 1060642 | AT115: 579794 | AU115: 661164 | AV115: 619090 | AW115: 530407 | AX115: 663283 | AY115: 930481 | AZ115: 830145
A116: 付费总额增长率 | B116: 0 | C116: 0 | D116: 0 | E116: 0 | F116: 0 | G116: 0 | H116: 0 | I116: 0 | J116: 0 | K116: 0 | L116: 0 | M116: 0.3674 | N116: =N115/M115-1 -> 0.28326268 | O116: -0.184 | P116: -0.1364 | Q116: 0.4095 | R116: 0.8697 | S116: -0.2886 | T116: -0.0001 | U116: -0.4177 | V116: -0.1729 | W116: -0.189 | X116: 0.2869 | Y116: 0.628 | Z116: 0.1255 | AA116: 0.4217 | AB116: -0.1272 | AC116: -0.0451 | AD116: 0.0327 | AE116: 0.1493 | AF116: 0.435 | AG116: -0.0295 | AH116: -0.3841 | AI116: -0.0641 | AJ116: -0.1329 | AK116: -0.0558 | AL116: 0.5441 | AM116: 0.0294 | AN116: 0.0287 | AO116: -0.2463 | AP116: 0.1056 | AQ116: 0.2063 | AR116: -0.2147 | AS116: -0.2729 | AT116: -0.4534 | AU116: 0.1403 | AV116: -0.0636 | AW116: -0.1432 | AX116: 0.2505 | AY116: 0.4028 | AZ116: -0.1078
A117: 付费用户数 | B117: 0 | C117: 0 | D117: 0 | E117: 0 | F117: 0 | G117: 0 | H117: 0 | I117: 0 | J117: 0 | K117: 0 | L117: 28596 | M117: 33896 | N117: 45617 | O117: 40691 | P117: 37652 | Q117: 55083 | R117: 75546 | S117: 64714 | T117: 65125 | U117: 38051 | V117: 30350 | W117: 25121 | X117: 30916 | Y117: 37131 | Z117: 38202 | AA117: 43189 | AB117: 43657 | AC117: 43258 | AD117: 40890 | AE117: 41915 | AF117: 52880 | AG117: 46875 | AH117: 33202 | AI117: 34629 | AJ117: 31529 | AK117: 28857 | AL117: 34227 | AM117: 31673 | AN117: 32754 | AO117: 28765 | AP117: 32153 | AQ117: 37154 | AR117: 33914 | AS117: 24916 | AT117: 15952 | AU117: 18284 | AV117: 17071 | AW117: 16860 | AX117: 18544 | AY117: 19820 | AZ117: 17773
A118: 付费用户增长率 | B118: 0 | C118: 0 | D118: 0 | E118: 0 | F118: 0 | G118: 0 | H118: 0 | I118: 0 | J118: 0 | K118: 0 | L118: 0 | M118: 0.1853 | N118: =N117/M117-1 -> 0.34579301 | O118: -0.108 | P118: -0.0747 | Q118: 0.463 | R118: 0.3715 | S118: -0.1434 | T118: 0.0064 | U118: -0.4157 | V118: -0.2024 | W118: -0.1723 | X118: 0.2307 | Y118: 0.201 | Z118: 0.0288 | AA118: 0.1305 | AB118: 0.0108 | AC118: -0.0091 | AD118: -0.0547 | AE118: 0.0251 | AF118: 0.2616 | AG118: -0.1136 | AH118: -0.2917 | AI118: 0.043 | AJ118: -0.0895 | AK118: -0.0847 | AL118: 0.1861 | AM118: -0.0746 | AN118: 0.0341 | AO118: -0.1218 | AP118: 0.1178 | AQ118: 0.1555 | AR118: -0.0872 | AS118: -0.2653 | AT118: -0.3598 | AU118: 0.1462 | AV118: -0.0663 | AW118: -0.0124 | AX118: 0.0999 | AY118: 0.0688 | AZ118: -0.1033
A119: 纯新增付费用户数 | B119: 0 | C119: 0 | D119: 0 | E119: 0 | F119: 0 | G119: 0 | H119: 0 | I119: 0 | J119: 0 | K119: 0 | L119: 3374 | M119: 3798 | N119: 7700 | O119: 6126 | P119: 5984 | Q119: 10828 | R119: 11293 | S119: 10993 | T119: 10662 | U119: 4383 | V119: 3031 | W119: 2805 | X119: 2779 | Y119: 2719 | Z119: 4229 | AA119: 4365 | AB119: 5004 | AC119: 3985 | AD119: 3679 | AE119: 4181 | AF119: 7071 | AG119: 5510 | AH119: 3454 | AI119: 3726 | AJ119: 3339 | AK119: 3431 | AL119: 4640 | AM119: 4436 | AN119: 5032 | AO119: 4454 | AP119: 5423 | AQ119: 6958 | AR119: 5906 | AS119: 4054 | AT119: 1718 | AU119: 3440 | AV119: 3004 | AW119: 2656 | AX119: 3304 | AY119: 3438 | AZ119: 2793
A120: 历史转化新增付费用户数 | B120: 0 | C120: 0 | D120: 0 | E120: 0 | F120: 0 | G120: 0 | H120: 0 | I120: 0 | J120: 0 | K120: 0 | L120: 25222 | M120: 19204 | N120: 24878 | O120: 19149 | P120: 15284 | Q120: 25002 | R120: 34400 | S120: 26589 | T120: 25850 | U120: 11222 | V120: 7399 | W120: 6097 | X120: 7286 | Y120: 8608 | Z120: 8852 | AA120: 11947 | AB120: 11644 | AC120: 10863 | AD120: 9276 | AE120: 9195 | AF120: 12344 | AG120: 11292 | AH120: 7250 | AI120: 7189 | AJ120: 5672 | AK120: 4952 | AL120: 6410 | AM120: 6583 | AN120: 7165 | AO120: 5136 | AP120: 6170 | AQ120: 7970 | AR120: 7107 | AS120: 4433 | AT120: 2573 | AU120: 2886 | AV120: 2862 | AW120: 3454 | AX120: 3521 | AY120: 3766 | AZ120: 3628
A121: 活跃付费用户数 | B121: 0 | C121: 0 | D121: 0 | E121: 0 | F121: 0 | G121: 0 | H121: 0 | I121: 0 | J121: 0 | K121: 0 | L121: 0 | M121: 11212 | N121: 12471 | O121: 12940 | P121: 12866 | Q121: 14405 | R121: 21840 | S121: 22182 | T121: 19331 | U121: 15479 | V121: 12277 | W121: 11098 | X121: 11418 | Y121: 16607 | Z121: 16778 | AA121: 16213 | AB121: 17439 | AC121: 18974 | AD121: 18492 | AE121: 18280 | AF121: 19230 | AG121: 20676 | AH121: 16573 | AI121: 16397 | AJ121: 15735 | AK121: 14436 | AL121: 13679 | AM121: 13277 | AN121: 13532 | AO121: 13592 | AP121: 13404 | AQ121: 13634 | AR121: 13115 | AS121: 10919 | AT121: 8597 | AU121: 8405 | AV121: 8518 | AW121: 8210 | AX121: 8141 | AY121: 8392 | AZ121: 8209
A122: 回流付费用户数 | B122: 0 | C122: 0 | D122: 0 | E122: 0 | F122: 0 | G122: 0 | H122: 0 | I122: 0 | J122: 0 | K122: 0 | L122: 0 | M122: 0 | N122: 3196 | O122: 4331 | P122: 5370 | Q122: 8489 | R122: 11110 | S122: 8845 | T122: 13093 | U122: 7412 | V122: 8209 | W122: 5711 | X122: 10102 | Y122: 9101 | Z122: 8191 | AA122: 10594 | AB122: 9511 | AC122: 9330 | AD122: 9387 | AE122: 10212 | AF122: 14181 | AG122: 9352 | AH122: 5902 | AI122: 7295 | AJ122: 6229 | AK122: 5617 | AL122: 8944 | AM122: 6912 | AN122: 6619 | AO122: 5289 | AP122: 6827 | AQ122: 8199 | AR122: 7437 | AS122: 5341 | AT122: 2972 | AU122: 3468 | AV122: 2616 | AW122: 2452 | AX122: 3485 | AY122: 4105 | AZ122: 3064
A123: 纯新增付费用户占比 | B123: 0 | C123: 0 | D123: 0 | E123: 0 | F123: 0 | G123: 0 | H123: 0 | I123: 0 | J123: 0 | K123: 0 | L123: 0.118 | M123: 0.112 | N123: 0.1688 | O123: 0.1505 | P123: 0.1589 | Q123: 0.1966 | R123: 0.1495 | S123: 0.1699 | T123: 0.1637 | U123: 0.1152 | V123: 0.0999 | W123: 0.1117 | X123: 0.0899 | Y123: 0.0732 | Z123: 0.1107 | AA123: 0.1011 | AB123: 0.1146 | AC123: 0.0921 | AD123: 0.09 | AE123: 0.0997 | AF123: 0.1337 | AG123: 0.1175 | AH123: 0.104 | AI123: 0.1076 | AJ123: 0.1059 | AK123: 0.1189 | AL123: 0.1356 | AM123: 0.1401 | AN123: 0.1536 | AO123: 0.1548 | AP123: 0.1687 | AQ123: 0.1873 | AR123: 0.1741 | AS123: 0.1627 | AT123: 0.1077 | AU123: 0.1881 | AV123: 0.176 | AW123: 0.1575 | AX123: 0.1782 | AY123: 0.1735 | AZ123: 0.1571
A124: 历史转化新增付费用户占比 | B124: 0 | C124: 0 | D124: 0 | E124: 0 | F124: 0 | G124: 0 | H124: 0 | I124: 0 | J124: 0 | K124: 0 | L124: 0.882 | M124: 0.5666 | N124: 0.5454 | O124: 0.4706 | P124: 0.4059 | Q124: 0.4539 | R124: 0.4554 | S124: 0.4109 | T124: 0.3969 | U124: 0.2949 | V124: 0.2438 | W124: 0.2427 | X124: 0.2357 | Y124: 0.2318 | Z124: 0.2317 | AA124: 0.2766 | AB124: 0.2667 | AC124: 0.2511 | AD124: 0.2269 | AE124: 0.2194 | AF124: 0.2334 | AG124: 0.2409 | AH124: 0.2184 | AI124: 0.2076 | AJ124: 0.1799 | AK124: 0.1716 | AL124: 0.1873 | AM124: 0.2078 | AN124: 0.2188 | AO124: 0.1786 | AP124: 0.1919 | AQ124: 0.2145 | AR124: 0.2096 | AS124: 0.1779 | AT124: 0.1613 | AU124: 0.1578 | AV124: 0.1677 | AW124: 0.2049 | AX124: 0.1899 | AY124: 0.19 | AZ124: 0.2041
A125: 活跃付费用户占比 | B125: 0 | C125: 0 | D125: 0 | E125: 0 | F125: 0 | G125: 0 | H125: 0 | I125: 0 | J125: 0 | K125: 0 | L125: 0 | M125: 0.3308 | N125: 0.2734 | O125: 0.318 | P125: 0.3417 | Q125: 0.2615 | R125: 0.2891 | S125: 0.3428 | T125: 0.2968 | U125: 0.4068 | V125: 0.4045 | W125: 0.4418 | X125: 0.3693 | Y125: 0.4473 | Z125: 0.4392 | AA125: 0.3754 | AB125: 0.3995 | AC125: 0.4386 | AD125: 0.4522 | AE125: 0.4361 | AF125: 0.3637 | AG125: 0.4411 | AH125: 0.4992 | AI125: 0.4735 | AJ125: 0.4991 | AK125: 0.5003 | AL125: 0.3997 | AM125: 0.4192 | AN125: 0.4131 | AO125: 0.4725 | AP125: 0.4169 | AQ125: 0.367 | AR125: 0.3867 | AS125: 0.4382 | AT125: 0.5389 | AU125: 0.4597 | AV125: 0.499 | AW125: 0.487 | AX125: 0.439 | AY125: 0.4234 | AZ125: 0.4619
A126: 回流付费用户占比 | B126: 0 | C126: 0 | D126: 0 | E126: 0 | F126: 0 | G126: 0 | H126: 0 | I126: 0 | J126: 0 | K126: 0 | L126: 0 | M126: 0 | N126: 0.0701 | O126: 0.1064 | P126: 0.1426 | Q126: 0.1541 | R126: 0.1471 | S126: 0.1367 | T126: 0.201 | U126: 0.1948 | V126: 0.2705 | W126: 0.2273 | X126: 0.3268 | Y126: 0.2451 | Z126: 0.2144 | AA126: 0.2453 | AB126: 0.2179 | AC126: 0.2157 | AD126: 0.2296 | AE126: 0.2436 | AF126: 0.2682 | AG126: 0.1995 | AH126: 0.1778 | AI126: 0.2107 | AJ126: 0.1976 | AK126: 0.1946 | AL126: 0.2613 | AM126: 0.2182 | AN126: 0.2021 | AO126: 0.1839 | AP126: 0.2123 | AQ126: 0.2207 | AR126: 0.2193 | AS126: 0.2144 | AT126: 0.1863 | AU126: 0.1897 | AV126: 0.1532 | AW126: 0.1454 | AX126: 0.1879 | AY126: 0.2071 | AZ126: 0.1724
A127: 付费渗透率 | B127: 0 | C127: 0 | D127: 0 | E127: 0 | F127: 0 | G127: 0 | H127: 0 | I127: 0 | J127: 0 | K127: 0 | L127: 0.0159 | M127: 0.0204 | N127: 0.0152 | O127: 0.016 | P127: 0.016 | Q127: 0.0156 | R127: 0.0243 | S127: 0.0192 | T127: 0.0167 | U127: 0.0095 | V127: 0.0125 | W127: 0.0103 | X127: 0.0179 | Y127: 0.0196 | Z127: 0.013 | AA127: 0.014 | AB127: 0.0189 | AC127: 0.0191 | AD127: 0.0196 | AE127: 0.0176 | AF127: 0.0133 | AG127: 0.0133 | AH127: 0.0161 | AI127: 0.0162 | AJ127: 0.0189 | AK127: 0.0216 | AL127: 0.0166 | AM127: 0.0154 | AN127: 0.0169 | AO127: 0.0149 | AP127: 0.0149 | AQ127: 0.0148 | AR127: 0.0098 | AS127: 0.0079 | AT127: 0.0104 | AU127: 0.0098 | AV127: 0.0103 | AW127: 0.0121 | AX127: 0.0117 | AY127: 0.0093 | AZ127: 0.0125
A128: 付费渗透率增长率 | B128: 0 | C128: 0 | D128: 0 | E128: 0 | F128: 0 | G128: 0 | H128: 0 | I128: 0 | J128: 0 | K128: 0 | L128: 0 | M128: 0.283 | N128: =N127/M127-1 -> -0.25490196 | O128: 0.0526 | P128: 0 | Q128: -0.025 | R128: 0.5577 | S128: -0.2099 | T128: -0.1302 | U128: -0.4311 | V128: 0.3158 | W128: -0.176 | X128: 0.7379 | Y128: 0.095 | Z128: -0.3367 | AA128: 0.0769 | AB128: 0.35 | AC128: 0.0106 | AD128: 0.0262 | AE128: -0.102 | AF128: -0.2443 | AG128: 0 | AH128: 0.2105 | AI128: 0.0062 | AJ128: 0.1667 | AK128: 0.1429 | AL128: -0.2315 | AM128: -0.0723 | AN128: 0.0974 | AO128: -0.1183 | AP128: 0 | AQ128: -0.0067 | AR128: -0.3378 | AS128: -0.1939 | AT128: 0.3165 | AU128: -0.0577 | AV128: 0.051 | AW128: 0.1748 | AX128: -0.0331 | AY128: -0.2051 | AZ128: 0.3441
A129: 付费用户arppu值 | B129: 0 | C129: 0 | D129: 0 | E129: 0 | F129: 0 | G129: 0 | H129: 0 | I129: 0 | J129: 0 | K129: 0 | L129: 20.0287 | M129: 23.1048 | N129: 22.0313 | O129: 20.1534 | P129: 18.8102 | Q129: 18.1234 | R129: 24.7065 | S129: 20.5183 | T129: 20.3862 | U129: 20.3172 | V129: 21.0691 | W129: 20.6442 | X129: 21.5867 | Y129: 29.2602 | Z129: 32.01 | AA129: 40.2539 | AB129: 34.7573 | AC129: 33.4958 | AD129: 36.5936 | AE129: 41.0276 | AF129: 46.6651 | AG129: 51.0888 | AH129: 44.4202 | AI129: 39.8596 | AJ129: 37.9588 | AK129: 39.161 | AL129: 50.9819 | AM129: 56.7117 | AN129: 56.4165 | AO129: 48.4209 | AP129: 47.8936 | AQ129: 49.9964 | AR129: 43.0118 | AS129: 42.5687 | AT129: 36.3462 | AU129: 36.1608 | AV129: 36.2656 | AW129: 31.4595 | AX129: 35.7681 | AY129: 46.9466 | AZ129: 46.7082
A130: 付费用户arppu值增长率 | B130: 0 | C130: 0 | D130: 0 | E130: 0 | F130: 0 | G130: 0 | H130: 0 | I130: 0 | J130: 0 | K130: 0 | L130: 0 | M130: 0.1536 | N130: =N129/M129-1 -> -0.046462207 | O130: -0.0852 | P130: -0.0666 | Q130: -0.0365 | R130: 0.3632 | S130: -0.1695 | T130: -0.0064 | U130: -0.0034 | V130: 0.037 | W130: -0.0202 | X130: 0.0457 | Y130: 0.3555 | Z130: 0.094 | AA130: 0.2575 | AB130: -0.1365 | AC130: -0.0363 | AD130: 0.0925 | AE130: 0.1212 | AF130: 0.1374 | AG130: 0.0948 | AH130: -0.1305 | AI130: -0.1027 | AJ130: -0.0477 | AK130: 0.0317 | AL130: 0.3019 | AM130: 0.1124 | AN130: -0.0052 | AO130: -0.1417 | AP130: -0.0109 | AQ130: 0.0439 | AR130: -0.1397 | AS130: -0.0103 | AT130: -0.1462 | AU130: -0.0051 | AV130: 0.0029 | AW130: -0.1325 | AX130: 0.137 | AY130: 0.3125 | AZ130: -0.0051
A131: 包月支付情况 | B131: 201101 | C131: 201102 | D131: 201103 | E131: 201104 | F131: 201105 | G131: 201106 | H131: 201107 | I131: 201108 | J131: 201109 | K131: 201110 | L131: 201111 | M131: 201112 | N131: 201201 | O131: 201202 | P131: 201203 | Q131: 201204 | R131: 201205 | S131: 201206 | T131: 201207 | U131: 201208 | V131: 201209 | W131: 201210 | X131: 201211 | Y131: 201212 | Z131: 201301 | AA131: 201302 | AB131: 201303 | AC131: 201304 | AD131: 201305 | AE131: 201306 | AF131: 201307 | AG131: 201308 | AH131: 201309 | AI131: 201310 | AJ131: 201311 | AK131: 201312 | AL131: 201401 | AM131: 201402 | AN131: 201403 | AO131: 201404 | AP131: 201405 | AQ131: 201406 | AR131: 201407 | AS131: 201408 | AT131: 201409 | AU131: 201410 | AV131: 201411 | AW131: 201412 | AX131: 201501 | AY131: 201502 | AZ131: 201503
A132: 包月支付总额 | B132: 0 | C132: 0 | D132: 0 | E132: 0 | F132: 0 | G132: 0 | H132: 0 | I132: 0 | J132: 0 | K132: 0 | L132: 572740 | M132: 783160 | N132: 1005000 | O132: 820060 | P132: 708240 | Q132: 998290 | R132: 1866480 | S132: 1327820 | T132: 1221320 | U132: 474250 | V132: 362330 | W132: 307490 | X132: 351190 | Y132: 412180 | Z132: 691550 | AA132: 651350 | AB132: 583850 | AC132: 463440 | AD132: 386000 | AE132: 597200 | AF132: 578260 | AG132: 528210 | AH132: 337180 | AI132: 350700 | AJ132: 329440 | AK132: 332740 | AL132: 538660 | AM132: 432960 | AN132: 438580 | AO132: 354980 | AP132: 377880 | AQ132: 462170 | AR132: 408010 | AS132: 298940 | AT132: 182020 | AU132: 210030 | AV132: 222210 | AW132: 204630 | AX132: 306470 | AY132: 412340 | AZ132: 315070
A133: 包月支付总额增长率 | B133: 0 | C133: 0 | D133: 0 | E133: 0 | F133: 0 | G133: 0 | H133: 0 | I133: 0 | J133: 0 | K133: 0 | L133: 0 | M133: 0.3674 | N133: 0 | O133: -0.184 | P133: -0.1364 | Q133: 0.4095 | R133: 0.8697 | S133: -0.2886 | T133: -0.0802 | U133: -0.6117 | V133: -0.236 | W133: -0.1514 | X133: 0.1421 | Y133: 0.1737 | Z133: 0.6778 | AA133: -0.0581 | AB133: -0.1036 | AC133: -0.2062 | AD133: -0.1671 | AE133: 0.5472 | AF133: -0.0317 | AG133: -0.0866 | AH133: -0.3617 | AI133: 0.0401 | AJ133: -0.0606 | AK133: 0.01 | AL133: 0.6189 | AM133: -0.1962 | AN133: 0.013 | AO133: -0.1906 | AP133: 0.0645 | AQ133: 0.2231 | AR133: -0.1172 | AS133: -0.2673 | AT133: -0.3911 | AU133: 0.1539 | AV133: 0.058 | AW133: -0.0791 | AX133: 0.4977 | AY133: 0.3454 | AZ133: -0.2359
A134: 包月支付用户数 | B134: 0 | C134: 0 | D134: 0 | E134: 0 | F134: 0 | G134: 0 | H134: 0 | I134: 0 | J134: 0 | K134: 0 | L134: 28596 | M134: 33896 | N134: 45617 | O134: 40691 | P134: 37652 | Q134: 55083 | R134: 75546 | S134: 64714 | T134: 64008 | U134: 30163 | V134: 23544 | W134: 20923 | X134: 25262 | Y134: 27503 | Z134: 30171 | AA134: 24828 | AB134: 28628 | AC134: 26130 | AD134: 23372 | AE134: 29441 | AF134: 32138 | AG134: 29436 | AH134: 20488 | AI134: 20755 | AJ134: 20463 | AK134: 19930 | AL134: 21253 | AM134: 19001 | AN134: 22087 | AO134: 18915 | AP134: 20852 | AQ134: 25803 | AR134: 23241 | AS134: 16427 | AT134: 11322 | AU134: 13290 | AV134: 13075 | AW134: 13008 | AX134: 15240 | AY134: 15670 | AZ134: 13739
A135: 包月支付用户数增长率 | B135: 0 | C135: 0 | D135: 0 | E135: 0 | F135: 0 | G135: 0 | H135: 0 | I135: 0 | J135: 0 | K135: 0 | L135: 0 | M135: 0.1853 | N135: 0 | O135: -0.108 | P135: -0.0747 | Q135: 0.463 | R135: 0.3715 | S135: -0.1434 | T135: -0.0109 | U135: -0.5288 | V135: -0.2194 | W135: -0.1113 | X135: 0.2074 | Y135: 0.0887 | Z135: 0.097 | AA135: -0.1771 | AB135: 0.1531 | AC135: -0.0873 | AD135: -0.1055 | AE135: 0.2597 | AF135: 0.0916 | AG135: -0.0841 | AH135: -0.304 | AI135: 0.013 | AJ135: -0.0141 | AK135: -0.026 | AL135: 0.0664 | AM135: -0.106 | AN135: 0.1624 | AO135: -0.1436 | AP135: 0.1024 | AQ135: 0.2374 | AR135: -0.0993 | AS135: -0.2932 | AT135: -0.3108 | AU135: 0.1738 | AV135: -0.0162 | AW135: -0.0051 | AX135: 0.1716 | AY135: 0.0282 | AZ135: -0.1232
A136: 包月支付arppu值 | B136: 0 | C136: 0 | D136: 0 | E136: 0 | F136: 0 | G136: 0 | H136: 0 | I136: 0 | J136: 0 | K136: 0 | L136: 20.0287 | M136: 23.1048 | N136: 22.0313 | O136: 20.1534 | P136: 18.8102 | Q136: 18.1234 | R136: 24.7065 | S136: 20.5183 | T136: 19.0807 | U136: 15.7229 | V136: 15.3895 | W136: 14.6963 | X136: 13.9019 | Y136: 14.9867 | Z136: 22.921 | AA136: 26.2345 | AB136: 20.3944 | AC136: 17.7359 | AD136: 16.5155 | AE136: 20.2846 | AF136: 17.993 | AG136: 17.9444 | AH136: 16.4574 | AI136: 16.8971 | AJ136: 16.0993 | AK136: 16.6954 | AL136: 25.3451 | AM136: 22.7862 | AN136: 19.8569 | AO136: 18.7671 | AP136: 18.122 | AQ136: 17.9115 | AR136: 17.5556 | AS136: 18.1981 | AT136: 16.0767 | AU136: 15.8036 | AV136: 16.995 | AW136: 15.7311 | AX136: 20.1096 | AY136: 26.314 | AZ136: 22.9325
A137: 包月支付arppu值增长率 | B137: 0 | C137: 0 | D137: 0 | E137: 0 | F137: 0 | G137: 0 | H137: 0 | I137: 0 | J137: 0 | K137: 0 | L137: 0 | M137: 0.1536 | N137: 0 | O137: -0.0852 | P137: -0.0666 | Q137: -0.0365 | R137: 0.3632 | S137: -0.1695 | T137: -0.0701 | U137: -0.176 | V137: -0.0212 | W137: -0.045 | X137: -0.0541 | Y137: 0.078 | Z137: 0.5294 | AA137: 0.1446 | AB137: -0.2226 | AC137: -0.1304 | AD137: -0.0688 | AE137: 0.2282 | AF137: -0.113 | AG137: -0.0027 | AH137: -0.0829 | AI137: 0.0267 | AJ137: -0.0472 | AK137: 0.037 | AL137: 0.5181 | AM137: -0.101 | AN137: -0.1286 | AO137: -0.0549 | AP137: -0.0344 | AQ137: -0.0116 | AR137: -0.0199 | AS137: 0.0366 | AT137: -0.1166 | AU137: -0.017 | AV137: 0.0754 | AW137: -0.0744 | AX137: 0.2783 | AY137: 0.3085 | AZ137: -0.1285
A138: 按条支付情况 | B138: 201101 | C138: 201102 | D138: 201103 | E138: 201104 | F138: 201105 | G138: 201106 | H138: 201107 | I138: 201108 | J138: 201109 | K138: 201110 | L138: 201111 | M138: 201112 | N138: 201201 | O138: 201202 | P138: 201203 | Q138: 201204 | R138: 201205 | S138: 201206 | T138: 201207 | U138: 201208 | V138: 201209 | W138: 201210 | X138: 201211 | Y138: 201212 | Z138: 201301 | AA138: 201302 | AB138: 201303 | AC138: 201304 | AD138: 201305 | AE138: 201306 | AF138: 201307 | AG138: 201308 | AH138: 201309 | AI138: 201310 | AJ138: 201311 | AK138: 201312 | AL138: 201401 | AM138: 201402 | AN138: 201403 | AO138: 201404 | AP138: 201405 | AQ138: 201406 | AR138: 201407 | AS138: 201408 | AT138: 201409 | AU138: 201410 | AV138: 201411 | AW138: 201412 | AX138: 201501 | AY138: 201502 | AZ138: 201503
A139: 按条支付总额 | B139: 0 | C139: 0 | D139: 0 | E139: 0 | F139: 0 | G139: 0 | H139: 0 | I139: 0 | J139: 0 | K139: 0 | L139: 0 | M139: 0 | N139: 0 | O139: 0 | P139: 0 | Q139: 0 | R139: 0 | S139: 0 | T139: 106329.5 | U139: 298838.8 | V139: 277118.5 | W139: 211113.3 | X139: 316184.4 | Y139: 674281.8 | Z139: 531295.8 | AA139: 1087175.3 | AB139: 933551.3 | AC139: 985519.9 | AD139: 1110311.4 | AE139: 1122469.8 | AF139: 1889391.5 | AG139: 1866579.6 | AH139: 1137658.4 | AI139: 1029598 | AJ139: 867362.8 | AK139: 797328 | AL139: 1206296 | AM139: 1363269 | AN139: 1409286 | AO139: 1037848 | AP139: 1162042 | AQ139: 1395398 | AR139: 1050691 | AS139: 761702 | AT139: 397774 | AU139: 451134 | AV139: 396880 | AW139: 325777 | AX139: 356813 | AY139: 518141 | AZ139: 515075
A140: 按条支付总额增长率 | B140: 0 | C140: 0 | D140: 0 | E140: 0 | F140: 0 | G140: 0 | H140: 0 | I140: 0 | J140: 0 | K140: 0 | L140: 0 | M140: 0 | N140: 0 | O140: 0 | P140: 0 | Q140: 0 | R140: 0 | S140: 0 | T140: 0 | U140: 1.8105 | V140: -0.0727 | W140: -0.2382 | X140: 0.4977 | Y140: 1.1326 | Z140: -0.2121 | AA140: 1.0463 | AB140: -0.1413 | AC140: 0.0557 | AD140: 0.1266 | AE140: 0.011 | AF140: 0.6832 | AG140: -0.0121 | AH140: -0.3905 | AI140: -0.095 | AJ140: -0.1576 | AK140: -0.0807 | AL140: 0.5129 | AM140: 0.1301 | AN140: 0.0338 | AO140: -0.2636 | AP140: 0.1197 | AQ140: 0.2008 | AR140: -0.247 | AS140: -0.275 | AT140: -0.4778 | AU140: 0.1341 | AV140: -0.1203 | AW140: -0.1792 | AX140: 0.0953 | AY140: 0.4521 | AZ140: -0.0059
A141: 按条支付用户数 | B141: 0 | C141: 0 | D141: 0 | E141: 0 | F141: 0 | G141: 0 | H141: 0 | I141: 0 | J141: 0 | K141: 0 | L141: 0 | M141: 0 | N141: 0 | O141: 0 | P141: 0 | Q141: 0 | R141: 0 | S141: 0 | T141: 4646 | U141: 13979 | V141: 11990 | W141: 7979 | X141: 12285 | Y141: 19231 | Z141: 17664 | AA141: 29603 | AB141: 26690 | AC141: 28918 | AD141: 27251 | AE141: 25236 | AF141: 35334 | AG141: 31763 | AH141: 20334 | AI141: 21600 | AJ141: 18947 | AK141: 16073 | AL141: 22207 | AM141: 20347 | AN141: 19433 | AO141: 16951 | AP141: 19672 | AQ141: 22163 | AR141: 19352 | AS141: 14515 | AT141: 7511 | AU141: 8632 | AV141: 7472 | AW141: 6964 | AX141: 7308 | AY141: 8642 | AZ141: 7555
A142: 按条支付用户数增长率 | B142: 0 | C142: 0 | D142: 0 | E142: 0 | F142: 0 | G142: 0 | H142: 0 | I142: 0 | J142: 0 | K142: 0 | L142: 0 | M142: 0 | N142: 0 | O142: 0 | P142: 0 | Q142: 0 | R142: 0 | S142: 0 | T142: 0 | U142: 2.0088 | V142: -0.1423 | W142: -0.3345 | X142: 0.5397 | Y142: 0.5654 | Z142: -0.0815 | AA142: 0.6759 | AB142: -0.0984 | AC142: 0.0835 | AD142: -0.0576 | AE142: -0.0739 | AF142: 0.4001 | AG142: -0.1011 | AH142: -0.3598 | AI142: 0.0623 | AJ142: -0.1228 | AK142: -0.1517 | AL142: 0.3816 | AM142: -0.0838 | AN142: -0.0449 | AO142: -0.1277 | AP142: 0.1605 | AQ142: 0.1266 | AR142: -0.1268 | AS142: -0.2499 | AT142: -0.4825 | AU142: 0.1492 | AV142: -0.1344 | AW142: -0.068 | AX142: 0.0494 | AY142: 0.1825 | AZ142: -0.1258
... A144: 按条支付arppu值增长率 | B144: 0 | C144: 0 | D144: 0 | E144: 0 | F144: 0 | G144: 0 | H144: 0 | I144: 0 | J144: 0 | K144: 0 | L144: 0 | M144: 0 | N144: 0 | O144: 0 | P144: 0 | Q144: 0 | R144: 0 | S144: 0 | T144: 0 | U144: -0.0659 | V144: 0.0811 | W144: 0.1448 | X144: -0.0273 | Y144: 0.3623 | Z144: -0.1422 | AA144: 0.221 | AB144: -0.0476 | AC144: -0.0257 | AD144: 0.1955 | AE144: 0.0917 | AF144: 0.2022 | AG144: 0.099 | AH144: -0.0479 | AI144: -0.148 | AJ144: -0.0396 | AK144: 0.0836 | AL144: 0.095 | AM144: 0.2334 | AN144: 0.0824 | AO144: -0.1557 | AP144: -0.0352 | AQ144: 0.0658 | AR144: -0.1377 | AS144: -0.0335 | AT144: 0.0092 | AU144: -0.0131 | AV144: 0.0163 | AW144: -0.1193 | AX144: 0.0437 | AY144: 0.228 | AZ144: 0.1371
A147: 功夫派
A148: 活跃在线情况 | B148: 201101 | C148: 201102 | D148: 201103 | E148: 201104 | F148: 201105 | G148: 201106 | H148: 201107 | I148: 201108 | J148: 201109 | K148: 201110 | L148: 201111 | M148: 201112 | N148: 201201 | O148: 201202 | P148: 201203 | Q148: 201204 | R148: 201205 | S148: 201206 | T148: 201207 | U148: 201208 | V148: 201209 | W148: 201210 | X148: 201211 | Y148: 201212 | Z148: 201301 | AA148: 201302 | AB148: 201303 | AC148: 201304 | AD148: 201305 | AE148: 201306 | AF148: 201307 | AG148: 201308 | AH148: 201309 | AI148: 201310 | AJ148: 201311 | AK148: 201312 | AL148: 201401 | AM148: 201402 | AN148: 201403 | AO148: 201404 | AP148: 201405 | AQ148: 201406 | AR148: 201407 | AS148: 201408 | AT148: 201409 | AU148: 201410 | AV148: 201411 | AW148: 201412 | AX148: 201501 | AY148: 201502 | AZ148: 201503
A149: 活跃用户 | B149: 3170138 | C149: 3195227 | D149: 2344714 | E149: 2310482 | F149: 1970100 | G149: 2080925 | H149: 2673484 | I149: 2841313 | J149: 1920492 | K149: 2257729 | L149: 1988642 | M149: 2067822 | N149: 3327442 | O149: 2528982 | P149: 2459276 | Q149: 3008380 | R149: 2785116 | S149: 3348610 | T149: 4105161 | U149: 5069130 | V149: 2812118 | W149: 2836095 | X149: 2004711 | Y149: 2026972 | Z149: 2830233 | AA149: 2924908 | AB149: 2012839 | AC149: 1950171 | AD149: 2114475 | AE149: 2754515 | AF149: 3626497 | AG149: 3485424 | AH149: 1904168 | AI149: 1795751 | AJ149: 1529554 | AK149: 1504222 | AL149: 2744532 | AM149: 1995226 | AN149: 1559851 | AO149: 1812401 | AP149: 1704938 | AQ149: 1727730 | AR149: 2727460 | AS149: 3065624 | AT149: 1516118 | AU149: 1448975 | AV149: 1243088 | AW149: 1016587 | AX149: 1363757 | AY149: 2080760 | AZ149: 1100970
A150: 活跃用户增长率 | B150: 0.2027 | C150: 0.0079 | D150: -0.2662 | E150: -0.0146 | F150: -0.1473 | G150: 0.0563 | H150: 0.2848 | I150: 0.0628 | J150: -0.3241 | K150: 0.1756 | L150: -0.1192 | M150: 0.0398 | N150: 0 | O150: -0.24 | P150: -0.0276 | Q150: 0.2233 | R150: -0.0742 | S150: 0.2023 | T150: 0.2259 | U150: 0.2348 | V150: -0.4452 | W150: 0.0085 | X150: -0.2931 | Y150: 0.0111 | Z150: 0.3963 | AA150: 0.0335 | AB150: -0.3118 | AC150: -0.0311 | AD150: 0.0843 | AE150: 0.3027 | AF150: 0.3166 | AG150: -0.0389 | AH150: -0.4537 | AI150: -0.0569 | AJ150: -0.1482 | AK150: -0.0166 | AL150: 0.8246 | AM150: -0.273 | AN150: -0.2182 | AO150: 0.1619 | AP150: -0.0593 | AQ150: 0.0134 | AR150: 0.5786 | AS150: 0.124 | AT150: -0.5054 | AU150: -0.0443 | AV150: -0.1421 | AW150: -0.1822 | AX150: 0.3415 | AY150: 0.5258 | AZ150: -0.4709
A151: 有效活跃用户 | B151: 0 | C151: 0 | D151: 0 | E151: 0 | F151: 0 | G151: 0 | H151: 0 | I151: 1214357 | J151: 879339 | K151: 1096720 | L151: 932738 | M151: 939115 | N151: 1550190 | O151: 1101802 | P151: 1023541 | Q151: 1273421 | R151: 1171370 | S151: 1427603 | T151: 1844665 | U151: 2137113 | V151: 1212144 | W151: 1165320 | X151: 828068 | Y151: 875234 | Z151: 1294517 | AA151: 1334229 | AB151: 821824 | AC151: 714099 | AD151: 766642 | AE151: 1088436 | AF151: 1407244 | AG151: 1345998 | AH151: 670146 | AI151: 655244 | AJ151: 580089 | AK151: 577195 | AL151: 926283 | AM151: 655834 | AN151: 505972 | AO151: 607612 | AP151: 564287 | AQ151: 535930 | AR151: 822806 | AS151: 931068 | AT151: 407682 | AU151: 416765 | AV151: 335093 | AW151: 289030 | AX151: 365783 | AY151: 513959 | AZ151: 232708
A152: 有效活跃用户增长率 | B152: 0 | C152: 0 | D152: 0 | E152: 0 | F152: 0 | G152: 0 | H152: 0 | I152: 0 | J152: -0.2759 | K152: 0.2472 | L152: -0.1495 | M152: 0.0068 | N152: =N151/M151-1 -> 0.65069241 | O152: -0.2892 | P152: -0.071 | Q152: 0.2441 | R152: -0.0801 | S152: 0.2187 | T152: 0.2921 | U152: 0.1585 | V152: -0.4328 | W152: -0.0386 | X152: -0.2894 | Y152: 0.057 | Z152: 0.4791 | AA152: 0.0307 | AB152: -0.384 | AC152: -0.1311 | AD152: 0.0736 | AE152: 0.4197 | AF152: 0.2929 | AG152: -0.0435 | AH152: -0.5021 | AI152: -0.0222 | AJ152: -0.1147 | AK152: -0.005 | AL152: 0.6048 | AM152: -0.292 | AN152: -0.2285 | AO152: 0.2009 | AP152: -0.0713 | AQ152: -0.0503 | AR152: 0.5353 | AS152: 0.1316 | AT152: -0.5621 | AU152: 0.0223 | AV152: -0.196 | AW152: -0.1375 | AX152: 0.2656 | AY152: 0.4051 | AZ152: -0.5472
A153: 新增活跃用户占比 | B153: 0.5133 | C153: 0.5425 | D153: 0.4051 | E153: 0.3782 | F153: 0.3495 | G153: 0.3809 | H153: 0.4213 | I153: 0.4497 | J153: 0.3811 | K153: 0.4168 | L153: 0.3714 | M153: 0.3927 | N153: 0.4854 | O153: 0.461 | P153: 0.4721 | Q153: 0.5186 | R153: 0.4997 | S153: 0.525 | T153: 0.5715 | U153: 0.6262 | V153: 0.455 | W153: 0.4768 | X153: 0.4571 | Y153: 0.4532 | Z153: 0.5075 | AA153: 0.5076 | AB153: 0.4575 | AC153: 0.4785 | AD153: 0.4937 | AE153: 0.5146 | AF153: 0.6015 | AG153: 0.5917 | AH153: 0.4854 | AI153: 0.4911 | AJ153: 0.4779 | AK153: 0.4828 | AL153: 0.5761 | AM153: 0.5336 | AN153: 0.5302 | AO153: 0.5364 | AP153: 0.5506 | AQ153: 0.5669 | AR153: 0.6638 | AS153: 0.6685 | AT153: 0.5614 | AU153: 0.5651 | AV153: 0.564 | AW153: 0.5518 | AX153: 0.6024 | AY153: 0.644 | AZ153: 0.611
...

Sheet 历史新
A1: 赛尔号付费情况 | C1: 2011-01 | D1: 2011-02 | E1: 2011-03 | F1: 2011-04 | G1: 2011-05 | H1: 2011-06 | I1: 2011-07 | J1: 2011-08 | K1: 2011-09 | L1: 2011-10 | M1: 2011-11 | N1: 2011-12 | O1: 2012-01 | P1: 2012-02 | Q1: 2012-03 | R1: 2012-04 | S1: 2012-05 | T1: 2012-06 | U1: 2012-07 | V1: 2012-08 | W1: 2012-09 | X1: 2012-10 | Y1: 2012-11 | Z1: 2012-12 | AA1: 2013-01 | AB1: 2013-02 | AC1: 2013-03 | AD1: 2013-04 | AE1: 2013-05 | AF1: 2013-06 | AG1: 2013-07 | AH1: 2013-08 | AI1: 2013-09 | AJ1: 2013-10 | AK1: 2013-11 | AL1: 2013-12 | AM1: 2014-01 | AN1: 2014-02 | AO1: 2014-03 | AP1: 2014-04 | AQ1: 2014-05 | AR1: 2014-06 | AS1: 2014-07 | AT1: 2014-08 | AU1: 2014-09 | AV1: 2014-10 | AW1: 2014-11 | AX1: 2014-12 | AY1: 2015-01 | AZ1: 2015-02 | BA1: 2015-03 | BB1: 2015-04 | BC1: 2015-05 | BD1: 2015-06 | BE1: 42186 | BF1: 42217 | BG1: 42248 | BH1: 42278 | BI1: 42309 | BJ1: 42339 | BK1: 42370 | BL1: 42401 | BM1: 42430 | BN1: 42461 | BO1: 42491 | BP1: 42522 | BQ1: 42552 | BR1: 42583
A2: 基本情况 | B2: 付费总额(元) | C2: 32214859 | D2: 36949986 | E2: 24005069 | F2: 25795219 | G2: 21735492 | H2: 19577851 | I2: 18607239 | J2: 18931392 | K2: 12353432 | L2: 11307711 | M2: 9372817.6 | N2: 10696623 | O2: 15156367 | P2: 17263013 | Q2: 12623948 | R2: 12140136 | S2: 13911665 | T2: 15265537 | U2: 13980393 | V2: 10276391 | W2: 7163760.5 | X2: 6029393 | Y2: 6621080.3 | Z2: 7351451.2 | AA2: 7984752.9 | AB2: 14206733 | AC2: 12739961 | AD2: 10407097 | AE2: 11495323 | AF2: 13880407 | AG2: 17709614 | AH2: 18916039 | AI2: 13205883 | AJ2: 11444374 | AK2: 9746767 | AL2: 9059788.8 | AM2: 12090917 | AN2: 13703873 | AO2: 9294771 | AP2: 7861986.6 | AQ2: 8734578.7 | AR2: 10963177 | AS2: 14529713 | AT2: 11165684 | AU2: 8918814.1 | AV2: 8007658.3 | AW2: 7077513.9 | AX2: 7449654.6 | AY2: 8070608.1 | AZ2: 10725468 | BA2: 9692354 | BB2: 8902157 | BC2: 9133285.9 | BD2: 9508313.7 | BE2: 11068460 | BF2: 11295530 | BG2: 8613110.1 | BH2: 7274075.9 | BI2: 5861264.1 | BJ2: 5416807.5 | BK2: 7145626.2 | BL2: 11250348 | BM2: 6492509.4 | BN2: 7859361 | BO2: 7016380.1 | BP2: 8398391.5 | BQ2: 8183185.7 | BR2: 7342280.3
B3: 付费总额(元)增长率 | C3: 0.4329 | D3: 0.147 | E3: -0.3503 | F3: 0.0746 | G3: -0.1574 | H3: -0.0993 | I3: -0.0496 | J3: 0.0174 | K3: -0.3475 | L3: -0.0847 | M3: -0.1711 | N3: 0.1412 | O3: 0.4169 | P3: 0.139 | Q3: -0.2687 | R3: -0.0383 | S3: 0.1459 | T3: 0.0973 | U3: -0.0842 | V3: -0.2649 | W3: -0.3029 | X3: -0.1583 | Y3: 0.0981 | Z3: 0.1103 | AA3: 0.0861 | AB3: 0.7792 | AC3: -0.1032 | AD3: -0.1831 | AE3: 0.1046 | AF3: 0.2075 | AG3: 0.2759 | AH3: 0.0681 | AI3: -0.3019 | AJ3: -0.1334 | AK3: -0.1483 | AL3: -0.0705 | AM3: 0.3346 | AN3: 0.1334 | AO3: -0.3217 | AP3: -0.1541 | AQ3: 0.111 | AR3: 0.2551 | AS3: 0.3253 | AT3: -0.2315 | AU3: -0.2012 | AV3: -0.1022 | AW3: -0.1162 | AX3: 0.0526 | AY3: 0.0834 | AZ3: 0.329 | BA3: -0.0963 | BB3: -0.0815 | BC3: 0.026 | BD3: 0.0411 | BE3: 0.1641 | BF3: 0.0205 | BG3: -0.2375 | BH3: -0.1555 | BI3: -0.1942 | BJ3: -0.0758 | BK3: 0.3192 | BL3: 0.5744 | BM3: -0.4229 | BN3: 0.2105 | BO3: -0.1073 | BP3: 0.197 | BQ3: -0.0256 | BR3: -0.1028
B4: 付费用户数 | C4: 957284 | D4: 932330 | E4: 716691 | F4: 673953 | G4: 610889 | H4: 556999 | I4: 558064 | J4: 526920 | K4: 408315 | L4: 403490 | M4: 332193 | N4: 378643 | O4: 471363 | P4: 451441 | Q4: 432716 | R4: 427927 | S4: 410245 | T4: 460645 | U4: 426112 | V4: 307253 | W4: 241154 | X4: 231225 | Y4: 202597 | Z4: 217340 | AA4: 278146 | AB4: 346606 | AC4: 311137 | AD4: 269279 | AE4: 289529 | AF4: 335981 | AG4: 445616 | AH4: 407443 | AI4: 335073 | AJ4: 310416 | AK4: 256856 | AL4: 252149 | AM4: 304621 | AN4: 267265 | AO4: 231139 | AP4: 212478 | AQ4: 199994 | AR4: 234415 | AS4: 307103 | AT4: 210058 | AU4: 165359 | AV4: 149868 | AW4: 139102 | AX4: 146569 | AY4: 143817 | AZ4: 162018 | BA4: 162360 | BB4: 146274 | BC4: 147164 | BD4: 156898 | BE4: 181953 | BF4: 179473 | BG4: 123819 | BH4: 122626 | BI4: 85624 | BJ4: 99822 | BK4: 110179 | BL4: 124663 | BM4: 99637 | BN4: 103431 | BO4: 103106 | BP4: 128996 | BQ4: 115664 | BR4: 107797
B5: 付费用户数增长率 | C5: 0.2964 | D5: -0.0261 | E5: -0.2313 | F5: -0.0596 | G5: -0.0936 | H5: -0.0882 | I5: 0.0019 | J5: -0.0558 | K5: -0.2251 | L5: -0.0118 | M5: -0.1767 | N5: 0.1398 | O5: 0.2449 | P5: -0.0423 | Q5: -0.0415 | R5: -0.0111 | S5: -0.0413 | T5: 0.1229 | U5: -0.075 | V5: -0.2789 | W5: -0.2151 | X5: -0.0412 | Y5: -0.1238 | Z5: 0.0728 | AA5: 0.2798 | AB5: 0.2461 | AC5: -0.1023 | AD5: -0.1345 | AE5: 0.0752 | AF5: 0.1604 | AG5: 0.3263 | AH5: -0.0857 | AI5: -0.1776 | AJ5: -0.0736 | AK5: -0.1725 | AL5: -0.0183 | AM5: 0.2081 | AN5: -0.1226 | AO5: -0.1352 | AP5: -0.0807 | AQ5: -0.0588 | AR5: 0.1721 | AS5: 0.3101 | AT5: -0.316 | AU5: -0.2128 | AV5: -0.0937 | AW5: -0.0718 | AX5: 0.0537 | AY5: -0.0188 | AZ5: 0.1266 | BA5: 0.0021 | BB5: -0.0991 | BC5: 0.0061 | BD5: 0.0661 | BE5: 0.1597 | BF5: -0.0136 | BG5: -0.3101 | BH5: -0.0096 | BI5: -0.3017 | BJ5: 0.1658 | BK5: 0.1038 | BL5: 0.1315 | BM5: -0.2007 | BN5: 0.0381 | BO5: -0.0031 | BP5: 0.2511 | BQ5: -0.1034 | BR5: -0.068
B6: arppu值 | C6: 33.65 | D6: 39.63 | E6: 33.49 | F6: 38.27 | G6: 35.58 | H6: 35.15 | I6: 33.34 | J6: 35.93 | K6: 30.25 | L6: 28.02 | M6: 28.21 | N6: 28.25 | O6: 32.15 | P6: 38.24 | Q6: 29.17 | R6: 28.37 | S6: 33.91 | T6: 33.14 | U6: 32.81 | V6: 33.45 | W6: 29.71 | X6: 26.08 | Y6: 32.68 | Z6: 33.82 | AA6: 28.71 | AB6: 40.99 | AC6: 40.95 | AD6: 38.65 | AE6: 39.7 | AF6: 41.31 | AG6: 39.74 | AH6: 46.43 | AI6: 39.41 | AJ6: 36.87 | AK6: 37.95 | AL6: 35.93 | AM6: 39.69 | AN6: 51.27 | AO6: 40.21 | AP6: 37 | AQ6: 43.67 | AR6: 46.77 | AS6: 47.31 | AT6: 53.16 | AU6: 53.94 | AV6: 53.43 | AW6: 50.88 | AX6: 50.83 | AY6: 56.12 | AZ6: 66.2 | BA6: 59.7 | BB6: 60.86 | BC6: 62.06 | BD6: 60.6 | BE6: 60.83 | BF6: 62.94 | BG6: 69.56 | BH6: 59.32 | BI6: 68.45 | BJ6: 54.26 | BK6: 64.85 | BL6: 90.25 | BM6: 65.16 | BN6: 75.99 | BO6: 68.05 | BP6: 65.11 | BQ6: 70.75 | BR6: 68.11
B7: arppu值增长率 | C7: 0.1051 | D7: 0.1777 | E7: -0.1549 | F7: 0.1427 | G7: -0.0703 | H7: -0.0121 | I7: -0.0515 | J7: 0.0777 | K7: -0.1581 | L7: -0.0737 | M7: 0.0068 | N7: 0.0014 | O7: 0.1381 | P7: 0.1894 | Q7: -0.2372 | R7: -0.0274 | S7: 0.1953 | T7: -0.0227 | U7: -0.01 | V7: 0.0195 | W7: -0.1118 | X7: -0.1222 | Y7: 0.2531 | Z7: 0.0349 | AA7: -0.1511 | AB7: 0.4277 | AC7: -0.001 | AD7: -0.0562 | AE7: 0.0272 | AF7: 0.0406 | AG7: -0.038 | AH7: 0.1683 | AI7: -0.1512 | AJ7: -0.0645 | AK7: 0.0293 | AL7: -0.0532 | AM7: 0.1046 | AN7: 0.2918 | AO7: -0.2157 | AP7: -0.0798 | AQ7: 0.1803 | AR7: 0.071 | AS7: 0.0115 | AT7: 0.1237 | AU7: 0.0147 | AV7: -0.0095 | AW7: -0.0477 | AX7: -0.001 | AY7: 0.1041 | AZ7: 0.1796 | BA7: -0.0982 | BB7: 0.0194 | BC7: 0.0197 | BD7: -0.0235 | BE7: 0.0038 | BF7: 0.0347 | BG7: 0.1052 | BH7: -0.1472 | BI7: 0.1539 | BJ7: -0.2073 | BK7: 0.1952 | BL7: 0.3917 | BM7: -0.278 | BN7: 0.1662 | BO7: -0.1045 | BP7: -0.0432 | BQ7: 0.0866 | BR7: -0.0373
A8: 包月 | B8: 包月支付总额(不含短信包月续费) | C8: 0 | D8: 0 | E8: 0 | F8: 0 | G8: 0 | H8: 0 | I8: 0 | J8: 0 | K8: 0 | L8: 0 | M8: 0 | N8: 0 | O8: 0 | P8: 0 | Q8: 0 | R8: 0 | S8: 0 | T8: 0 | U8: 0 | V8: 0 | W8: 0 | X8: 0 | Y8: 0 | Z8: 0 | AA8: 0 | AB8: 0 | AC8: 0 | AD8: 0 | AE8: 0 | AF8: 0 | AG8: 0 | AH8: 0 | AI8: 0 | AJ8: 0 | AK8: 0 | AL8: 0 | AM8: 3051990 | AN8: 4775820 | AO8: 2750860 | AP8: 1833460 | AQ8: 2035390 | AR8: 2023410 | AS8: 3790550 | AT8: 1964010 | AU8: 1835430 | AV8: 1638490 | AW8: 1341600 | AX8: 2048200 | AY8: 2335670 | AZ8: 2103060 | BA8: 1873430 | BB8: 2024280 | BC8: 1629040 | BD8: 1951320 | BE8: 2027310 | BF8: 2264030 | BG8: 1391370 | BH8: 1029380 | BI8: 765070 | BJ8: 1439810 | BK8: 2487620 | BL8: 2240270 | BM8: 1293060 | BN8: 1689380 | BO8: 1496610 | BP8: 1498740 | BQ8: 1495350 | BR8: 1364340
B9: 包月支付总额(不含短信包月续费)增长率 | C9: 0 | D9: 0 | E9: 0 | F9: 0 | G9: 0 | H9: 0 | I9: 0 | J9: 0 | K9: 0 | L9: 0 | M9: 0 | N9: 0 | O9: 0 | P9: 0 | Q9: 0 | R9: 0 | S9: 0 | T9: 0 | U9: 0 | V9: 0 | W9: 0 | X9: 0 | Y9: 0 | Z9: 0 | AA9: 0 | AB9: 0 | AC9: 0 | AD9: 0 | AE9: 0 | AF9: 0 | AG9: 0 | AH9: 0 | AI9: 0 | AJ9: 0 | AK9: 0 | AL9: 0 | AM9: 0 | AN9: 0.5648 | AO9: -0.424 | AP9: -0.3335 | AQ9: 0.1101 | AR9: -0.0059 | AS9: 0.8733 | AT9: -0.4819 | AU9: -0.0655 | AV9: -0.1073 | AW9: -0.1812 | AX9: 0.5267 | AY9: 0.1404 | AZ9: -0.0996 | BA9: -0.1092 | BB9: 0.0805 | BC9: -0.1952 | BD9: 0.1978 | BE9: 0.0389 | BF9: 0.1168 | BG9: -0.3854 | BH9: -0.2602 | BI9: -0.2568 | BJ9: 0.8819 | BK9: 0.7277 | BL9: -0.0994 | BM9: -0.4228 | BN9: 0.3065 | BO9: -0.1141 | BP9: 0.0014 | BQ9: -0.0023 | BR9: -0.0876
B10: 包月支付用户数(不含短信包月续费) | C10: 0 | D10: 0 | E10: 0 | F10: 0 | G10: 0 | H10: 0 | I10: 0 | J10: 0 | K10: 0 | L10: 0 | M10: 0 | N10: 0 | O10: 0 | P10: 0 | Q10: 0 | R10: 0 | S10: 0 | T10: 0 | U10: 0 | V10: 0 | W10: 0 | X10: 0 | Y10: 0 | Z10: 0 | AA10: 0 | AB10: 0 | AC10: 0 | AD10: 0 | AE10: 0 | AF10: 0 | AG10: 0 | AH10: 0 | AI10: 0 | AJ10: 0 | AK10: 0 | AL10: 0 | AM10: 135573 | AN10: 126248 | AO10: 107726 | AP10: 82730 | AQ10: 95746 | AR10: 120997 | AS10: 186137 | AT10: 106710 | AU10: 93291 | AV10: 85766 | AW10: 73176 | AX10: 64140 | AY10: 70795 | AZ10: 70812 | BA10: 68774 | BB10: 71586 | BC10: 68870 | BD10: 73121 | BE10: 87274 | BF10: 94287 | BG10: 47486 | BH10: 40839 | BI10: 29989 | BJ10: 35510 | BK10: 50448 | BL10: 47080 | BM10: 35271 | BN10: 40768 | BO10: 38185 | BP10: 51327 | BQ10: 44849 | BR10: 42062
B11: 包月支付用户数(不含短信包月续费)增长率 | C11: 0 | D11: 0 | E11: 0 | F11: 0 | G11: 0 | H11: 0 | I11: 0 | J11: 0 | K11: 0 | L11: 0 | M11: 0 | N11: 0 | O11: 0 | P11: 0 | Q11: 0 | R11: 0 | S11: 0 | T11: 0 | U11: 0 | V11: 0 | W11: 0 | X11: 0 | Y11: 0 | Z11: 0 | AA11: 0 | AB11: 0 | AC11: 0 | AD11: 0 | AE11: 0 | AF11: 0 | AG11: 0 | AH11: 0 | AI11: 0 | AJ11: 0 | AK11: 0 | AL11: 0 | AM11: 0 | AN11: -0.0688 | AO11: -0.1467 | AP11: -0.232 | AQ11: 0.1573 | AR11: 0.2637 | AS11: 0.5384 | AT11: -0.4267 | AU11: -0.1258 | AV11: -0.0807 | AW11: -0.1468 | AX11: -0.1235 | AY11: 0.1038 | AZ11: 0.0002 | BA11: -0.0288 | BB11: 0.0409 | BC11: -0.0379 | BD11: 0.0617 | BE11: 0.1936 | BF11: 0.0804 | BG11: -0.4964 | BH11: -0.14 | BI11: -0.2657 | BJ11: 0.1841 | BK11: 0.4207 | BL11: -0.0668 | BM11: -0.2508 | BN11: 0.1559 | BO11: -0.0634 | BP11: 0.3442 | BQ11: -0.1262 | BR11: -0.0621
B12: 包月支付arppu值 | C12: 0 | D12: 0 | E12: 0 | F12: 0 | G12: 0 | H12: 0 | I12: 0 | J12: 0 | K12: 0 | L12: 0 | M12: 0 | N12: 0 | O12: 0 | P12: 0 | Q12: 0 | R12: 0 | S12: 0 | T12: 0 | U12: 0 | V12: 0 | W12: 0 | X12: 0 | Y12: 0 | Z12: 0 | AA12: 0 | AB12: 0 | AC12: 0 | AD12: 0 | AE12: 0 | AF12: 0 | AG12: 0 | AH12: 0 | AI12: 0 | AJ12: 0 | AK12: 0 | AL12: 0 | AM12: 22.51 | AN12: 37.83 | AO12: 25.54 | AP12: 22.16 | AQ12: 21.26 | AR12: 16.72 | AS12: 20.36 | AT12: 18.41 | AU12: 19.67 | AV12: 19.1 | AW12: 18.33 | AX12: 31.93 | AY12: 32.99 | AZ12: 29.7 | BA12: 27.24 | BB12: 28.28 | BC12: 23.65 | BD12: 26.69 | BE12: 23.23 | BF12: 24.01 | BG12: 29.3 | BH12: 25.21 | BI12: 25.51 | BJ12: 40.55 | BK12: 49.31 | BL12: 47.58 | BM12: 36.66 | BN12: 41.44 | BO12: 39.19 | BP12: 29.2 | BQ12: 33.34 | BR12: 32.44
B13: 包月支付arppu值增长率 | C13: 0 | D13: 0 | E13: 0 | F13: 0 | G13: 0 | H13: 0 | I13: 0 | J13: 0 | K13: 0 | L13: 0 | M13: 0 | N13: 0 | O13: 0 | P13: 0 | Q13: 0 | R13: 0 | S13: 0 | T13: 0 | U13: 0 | V13: 0 | W13: 0 | X13: 0 | Y13: 0 | Z13: 0 | AA13: 0 | AB13: 0 | AC13: 0 | AD13: 0 | AE13: 0 | AF13: 0 | AG13: 0 | AH13: 0 | AI13: 0 | AJ13: 0 | AK13: 0 | AL13: 0 | AM13: 0 | AN13: 0.6806 | AO13: -0.3249 | AP13: -0.1323 | AQ13: -0.0406 | AR13: -0.2135 | AS13: 0.2177 | AT13: -0.0958 | AU13: 0.0684 | AV13: -0.029 | AW13: -0.0403 | AX13: 0.742 | AY13: 0.0332 | AZ13: -0.0997 | BA13: -0.0828 | BB13: 0.0382 | BC13: -0.1637 | BD13: 0.1285 | BE13: -0.1296 | BF13: 0.0336 | BG13: 0.2203 | BH13: -0.1396 | BI13: 0.0119 | BJ13: 0.5896 | BK13: 0.216 | BL13: -0.0351 | BM13: -0.2295 | BN13: 0.1304 | BO13: -0.0543 | BP13: -0.2549 | BQ13: 0.1418 | BR13: -0.027
A14: 按条 | B14: 按条支付总额 | C14: 17766949 | D14: 22405856 | E14: 13212059 | F14: 18513769 | G14: 12812602 | H14: 11956261 | I14: 11763459 | J14: 11931262 | K14: 6941441.6 | L14: 6617011.3 | M14: 5578247.6 | N14: 6561753.3 | O14: 8884187.3 | P14: 10157363 | Q14: 7190958 | R14: 6592405.9 | S14: 8424365.1 | T14: 10550947 | U14: 8903102.7 | V14: 7210871.3 | W14: 4411230.5 | X14: 3683313 | Y14: 4223180.3 | Z14: 4870491.2 | AA14: 5255412.9 | AB14: 9122983.2 | AC14: 8797610.7 | AD14: 7642726.9 | AE14: 8390992.7 | AF14: 9484066.6 | AG14: 11847464 | AH14: 14133199 | AI14: 8415542.7 | AJ14: 8205714.4 | AK14: 6857337 | AL14: 6221738.8 | AM14: 8623866.8 | AN14: 8524023.1 | AO14: 6129691 | AP14: 5608866.6 | AQ14: 6265888.7 | AR14: 8607507.4 | AS14: 10406683 | AT14: 8969543.7 | AU14: 6849504.1 | AV14: 6133798.3 | AW14: 5494963.9 | AX14: 5163074.6 | AY14: 5493428.1 | AZ14: 8378107.6 | BA14: 7570004 | BB14: 6683807 | BC14: 7306665.9 | BD14: 7374563.7 | BE14: 8856600.1 | BF14: 8856009.7 | BG14: 7054060.1 | BH14: 6082365.9 | BI14: 4938984.1 | BJ14: 3823997.5 | BK14: 4509266.2 | BL14: 8870107.9 | BM14: 5061629.4 | BN14: 6034661 | BO14: 5386670.1 | BP14: 6768781.5 | BQ14: 6559215.7 | BR14: 5851180.3
B15: 按条支付总额增长率 | C15: 0.5171 | D15: 0.2611 | E15: -0.4103 | F15: 0.4013 | G15: -0.3079 | H15: -0.0668 | I15: -0.0161 | J15: 0.0143 | K15: -0.4182 | L15: -0.0467 | M15: -0.157 | N15: 0.1763 | O15: 0.3539 | P15: 0.1433 | Q15: -0.292 | R15: -0.0832 | S15: 0.2779 | T15: 0.2524 | U15: -0.1562 | V15: -0.1901 | W15: -0.3883 | X15: -0.165 | Y15: 0.1466 | Z15: 0.1533 | AA15: 0.079 | AB15: 0.7359 | AC15: -0.0357 | AD15: -0.1313 | AE15: 0.0979 | AF15: 0.1303 | AG15: 0.2492 | AH15: 0.1929 | AI15: -0.4046 | AJ15: -0.0249 | AK15: -0.1643 | AL15: -0.0927 | AM15: 0.3861 | AN15: -0.0116 | AO15: -0.2809 | AP15: -0.085 | AQ15: 0.1171 | AR15: 0.3737 | AS15: 0.209 | AT15: -0.1381 | AU15: -0.2364 | AV15: -0.1045 | AW15: -0.1041 | AX15: -0.0604 | AY15: 0.064 | AZ15: 0.5251 | BA15: -0.0965 | BB15: -0.1171 | BC15: 0.0932 | BD15: 0.0093 | BE15: 0.201 | BF15: -0.0001 | BG15: -0.2035 | BH15: -0.1377 | BI15: -0.188 | BJ15: -0.2258 | BK15: 0.1792 | BL15: 0.9671 | BM15: -0.4294 | BN15: 0.1922 | BO15: -0.1074 | BP15: 0.2566 | BQ15: -0.031 | BR15: -0.1079
B16: 按条支付用户数 | C16: 459600 | D16: 502099 | E16: 347330 | F16: 387499 | G16: 336992 | H16: 300789 | I16: 285884 | J16: 271362 | K16: 195927 | L16: 185822 | M16: 157180 | N16: 209547 | O16: 265166 | P16: 243960 | Q16: 211902 | R16: 211656 | S16: 236455 | T16: 280136 | U16: 242851 | V16: 176301 | W16: 121442 | X16: 114226 | Y16: 99610 | Z16: 101409 | AA16: 161901 | AB16: 228154 | AC16: 200426 | AD16: 168131 | AE16: 184190 | AF16: 205177 | AG16: 273511 | AH16: 284825 | AI16: 217206 | AJ16: 209945 | AK16: 159670 | AL16: 151158 | AM16: 209509 | AN16: 177024 | AO16: 139472 | AP16: 131292 | AQ16: 107909 | AR16: 136046 | AS16: 175424 | AT16: 128016 | AU16: 90731 | AV16: 78270 | AW16: 78533 | AX16: 92884 | AY16: 83265 | AZ16: 103962 | BA16: 104656 | BB16: 88819 | BC16: 90547 | BD16: 102211 | BE16: 120513 | BF16: 115578 | BG16: 83526 | BH16: 86850 | BI16: 55038 | BJ16: 69127 | BK16: 70264 | BL16: 90768 | BM16: 69164 | BN16: 72175 | BO16: 72331 | BP16: 93118 | BQ16: 83310 | BR16: 75888
B17: 按条支付用户数增长率 | C17: 0.2656 | D17: 0.0925 | E17: -0.3082 | F17: 0.1157 | G17: -0.1303 | H17: -0.1074 | I17: -0.0496 | J17: -0.0508 | K17: -0.278 | L17: -0.0516 | M17: -0.1541 | N17: 0.3332 | O17: 0.2654 | P17: -0.08 | Q17: -0.1314 | R17: -0.0012 | S17: 0.1172 | T17: 0.1847 | U17: -0.1331 | V17: -0.274 | W17: -0.3112 | X17: -0.0594 | Y17: -0.128 | Z17: 0.0181 | AA17: 0.5965 | AB17: 0.4092 | AC17: -0.1215 | AD17: -0.1611 | AE17: 0.0955 | AF17: 0.1139 | AG17: 0.333 | AH17: 0.0414 | AI17: -0.2374 | AJ17: -0.0334 | AK17: -0.2395 | AL17: -0.0533 | AM17: 0.386 | AN17: -0.1551 | AO17: -0.2121 | AP17: -0.0586 | AQ17: -0.1781 | AR17: 0.2607 | AS17: 0.2894 | AT17: -0.2702 | AU17: -0.2913 | AV17: -0.1373 | AW17: 0.0034 | AX17: 0.1827 | AY17: -0.1036 | AZ17: 0.2486 | BA17: 0.0067 | BB17: -0.1513 | BC17: 0.0195 | BD17: 0.1288 | BE17: 0.1791 | BF17: -0.0409 | BG17: -0.2773 | BH17: 0.0398 | BI17: -0.3663 | BJ17: 0.256 | BK17: 0.0164 | BL17: 0.2918 | BM17: -0.238 | BN17: 0.0435 | BO17: 0.0022 | BP17: 0.2874 | BQ17: -0.1053 | BR17: -0.0891
B18: 按条支付arppu值 | C18: 38.66 | D18: 44.62 | E18: 38.04 | F18: 47.78 | G18: 38.02 | H18: 39.75 | I18: 41.15 | J18: 43.97 | K18: 35.43 | L18: 35.61 | M18: 35.49 | N18: 31.31 | O18: 33.5 | P18: 41.64 | Q18: 33.94 | R18: 31.15 | S18: 35.63 | T18: 37.66 | U18: 36.66 | V18: 40.9 | W18: 36.32 | X18: 32.25 | Y18: 42.4 | Z18: 48.03 | AA18: 32.46 | AB18: 39.99 | AC18: 43.89 | AD18: 45.46 | AE18: 45.56 | AF18: 46.22 | AG18: 43.32 | AH18: 49.62 | AI18: 38.74 | AJ18: 39.09 | AK18: 42.95 | AL18: 41.16 | AM18: 41.16 | AN18: 48.15 | AO18: 43.95 | AP18: 42.72 | AQ18: 58.07 | AR18: 63.27 | AS18: 59.32 | AT18: 70.07 | AU18: 75.49 | AV18: 78.37 | AW18: 69.97 | AX18: 55.59 | AY18: 65.98 | AZ18: 80.59 | BA18: 72.33 | BB18: 75.25 | BC18: 80.69 | BD18: 72.15 | BE18: 73.49 | BF18: 76.62 | BG18: 84.45 | BH18: 70.03 | BI18: 89.74 | BJ18: 55.32 | BK18: 64.18 | BL18: 97.72 | BM18: 73.18 | BN18: 83.61 | BO18: 74.47 | BP18: 72.69 | BQ18: 78.73 | BR18: 77.1
B19: 按条支付arppu值增长率 | C19: 0.1988 | D19: 0.1542 | E19: -0.1475 | F19: 0.256 | G19: -0.2043 | H19: 0.0455 | I19: 0.0352 | J19: 0.0685 | K19: -0.1942 | L19: 0.0051 | M19: -0.0034 | N19: -0.1178 | O19: 0.0699 | P19: 0.243 | Q19: -0.1849 | R19: -0.0822 | S19: 0.1438 | T19: 0.057 | U19: -0.0266 | V19: 0.1157 | W19: -0.112 | X19: -0.1121 | Y19: 0.3147 | Z19: 0.1328 | AA19: -0.3242 | AB19: 0.232 | AC19: 0.0975 | AD19: 0.0358 | AE19: 0.0022 | AF19: 0.0145 | AG19: -0.0627 | AH19: 0.1454 | AI19: -0.2193 | AJ19: 0.009 | AK19: 0.0987 | AL19: -0.0417 | AM19: 0 | AN19: 0.1698 | AO19: -0.0872 | AP19: -0.028 | AQ19: 0.3593 | AR19: 0.0895 | AS19: -0.0624 | AT19: 0.1812 | AU19: 0.0774 | AV19: 0.0382 | AW19: -0.1072 | AX19: -0.2055 | AY19: 0.1869 | AZ19: 0.2214 | BA19: -0.1025 | BB19: 0.0404 | BC19: 0.0723 | BD19: -0.1058 | BE19: 0.0186 | BF19: 0.0426 | BG19: 0.1022 | BH19: -0.1708 | BI19: 0.2815 | BJ19: -0.3836 | BK19: 0.1602 | BL19: 0.5226 | BM19: -0.2511 | BN19: 0.1425 | BO19: -0.1093 | BP19: -0.0239 | BQ19: 0.0831 | BR19: -0.0207
A20: 用户类型 | B20: 纯新增付费用户数 | C20: 45778 | D20: 38546 | E20: 27970 | F20: 25777 | G20: 20804 | H20: 20173 | I20: 29756 | J20: 25109 | K20: 16012 | L20: 15209 | M20: 10639 | N20: 13043 | O20: 32145 | P20: 28391 | Q20: 24666 | R20: 28341 | S20: 22067 | T20: 32378 | U20: 34428 | V20: 19989 | W20: 12577 | X20: 13718 | Y20: 10737 | Z20: 14572 | AA20: 20208 | AB20: 30575 | AC20: 25806 | AD20: 19643 | AE20: 22578 | AF20: 36082 | AG20: 59528 | AH20: 33794 | AI20: 21441 | AJ20: 22500 | AK20: 19903 | AL20: 17986 | AM20: 26502 | AN20: 20182 | AO20: 20300 | AP20: 16092 | AQ20: 18887 | AR20: 43483 | AS20: 54193 | AT20: 24299 | AU20: 16964 | AV20: 16849 | AW20: 14974 | AX20: 12353 | AY20: 14859 | AZ20: 19348 | BA20: 21040 | BB20: 20169 | BC20: 20754 | BD20: 19662 | BE20: 28874 | BF20: 21791 | BG20: 10654 | BH20: 10193 | BI20: 6512 | BJ20: 6953 | BK20: 14503 | BL20: 17761 | BM20: 16935 | BN20: 17249 | BO20: 16072 | BP20: 16665 | BQ20: 21989 | BR20: 17431
B21: 历史转化新增付费用户数 | C21: 161368 | D21: 165843 | E21: 109899 | F21: 91802 | G21: 76424 | H21: 70185 | I21: 75136 | J21: 69408 | K21: 54012 | L21: 53572 | M21: 38304 | N21: 42115 | O21: 61273 | P21: 65944 | Q21: 60102 | R21: 59569 | S21: 55237 | T21: 64904 | U21: 61966 | V21: 38302 | W21: 30809 | X21: 29582 | Y21: 24400 | Z21: 26978 | AA21: 41848 | AB21: 61461 | AC21: 57486 | AD21: 47461 | AE21: 51703 | AF21: 60551 | AG21: 86628 | AH21: 87604 | AI21: 72939 | AJ21: 65349 | AK21: 45897 | AL21: 43309 | AM21: 60183 | AN21: 49550 | AO21: 40628 | AP21: 37183 | AQ21: 28340 | AR21: 33624 | AS21: 56960 | AT21: 34438 | AU21: 26989 | AV21: 21822 | AW21: 20634 | AX21: 26180 | AY21: 21818 | AZ21: 24939 | BA21: 28127 | BB21: 25372 | BC21: 25231 | BD21: 26997 | BE21: 29457 | BF21: 29618 | BG21: 20120 | BH21: 18211 | BI21: 10406 | BJ21: 16937 | BK21: 15659 | BL21: 19461 | BM21: 16959 | BN21: 16070 | BO21: 16560 | BP21: 19384 | BQ21: 15516 | BR21: 15834
B22: 连续两月付费用户数 | C22: 426486 | D22: 458123 | E22: 392917 | F22: 350199 | G22: 333631 | H22: 295111 | I22: 253516 | J22: 254838 | K22: 210532 | L22: 198803 | M22: 182697 | N22: 180191 | O22: 193857 | P22: 209095 | Q22: 219154 | R22: 219609 | S22: 214747 | T22: 215957 | U22: 204591 | V22: 165452 | W22: 127020 | X22: 120148 | Y22: 114154 | Z22: 112349 | AA22: 115803 | AB22: 119848 | AC22: 132783 | AD22: 128344 | AE22: 128202 | AF22: 131725 | AG22: 152761 | AH22: 176087 | AI22: 158386 | AJ22: 150049 | AK22: 130906 | AL22: 124077 | AM22: 124586 | AN22: 124720 | AO22: 109865 | AP22: 102686 | AQ22: 97580 | AR22: 87745 | AS22: 100503 | AT22: 92441 | AU22: 75096 | AV22: 71973 | AW22: 67952 | AX22: 68592 | AY22: 64837 | AZ22: 63745 | BA22: 67412 | BB22: 63749 | BC22: 61242 | BD22: 63063 | BE22: 64784 | BF22: 65604 | BG22: 58219 | BH22: 56176 | BI22: 47407 | BJ22: 44515 | BK22: 44669 | BL22: 47310 | BM22: 43527 | BN22: 41699 | BO22: 42847 | BP22: 46932 | BQ22: 46590 | BR22: 43540
B23: 回流付费用户数 | C23: 323652 | D23: 269818 | E23: 185905 | F23: 206175 | G23: 180030 | H23: 171530 | I23: 199656 | J23: 177565 | K23: 127759 | L23: 135906 | M23: 100553 | N23: 143294 | O23: 184088 | P23: 148011 | Q23: 128794 | R23: 120408 | S23: 118194 | T23: 147406 | U23: 125127 | V23: 83510 | W23: 70748 | X23: 67777 | Y23: 53306 | Z23: 63441 | AA23: 100287 | AB23: 134722 | AC23: 95062 | AD23: 73831 | AE23: 87046 | AF23: 107623 | AG23: 146699 | AH23: 109958 | AI23: 82307 | AJ23: 72518 | AK23: 60150 | AL23: 66777 | AM23: 93350 | AN23: 72813 | AO23: 60346 | AP23: 56517 | AQ23: 55187 | AR23: 69563 | AS23: 95447 | AT23: 58880 | AU23: 46310 | AV23: 39319 | AW23: 35583 | AX23: 39444 | AY23: 42304 | AZ23: 53987 | BA23: 45781 | BB23: 38913 | BC23: 39938 | BD23: 48753 | BE23: 60867 | BF23: 63497 | BG23: 36581 | BH23: 39533 | BI23: 21631 | BJ23: 31417 | BK23: 35348 | BL23: 40131 | BM23: 22216 | BN23: 28413 | BO23: 27627 | BP23: 46015 | BQ23: 31569 | BR23: 30992
B24: 新增用户中的付费用户数 | C24: 45778 | D24: 38546 | E24: 27970 | F24: 25777 | G24: 20804 | H24: 20173 | I24: 29756 | J24: 25109 | K24: 16012 | L24: 15209 | M24: 10639 | N24: 13043 | O24: 32145 | P24: 28391 | Q24: 24666 | R24: 28341 | S24: 22067 | T24: 32378 | U24: 34428 | V24: 19989 | W24: 12577 | X24: 13718 | Y24: 10737 | Z24: 14572 | AA24: 20208 | AB24: 30575 | AC24: 25806 | AD24: 19643 | AE24: 22578 | AF24: 36082 | AG24: 59528 | AH24: 33794 | AI24: 21441 | AJ24: 22500 | AK24: 19903 | AL24: 17986 | AM24: 26502 | AN24: 20182 | AO24: 20300 | AP24: 16092 | AQ24: 18887 | AR24: 43483 | AS24: 54193 | AT24: 24299 | AU24: 16964 | AV24: 16849 | AW24: 14974 | AX24: 12353 | AY24: 14859 | AZ24: 19348 | BA24: 21040 | BB24: 20169 | BC24: 20754 | BD24: 19662 | BE24: 28874 | BF24: 21791 | BG24: 10654 | BH24: 10193 | BI24: 6512 | BJ24: 6953 | BK24: 14503 | BL24: 17761 | BM24: 16935 | BN24: 17249 | BO24: 16072 | BP24: 16665 | BQ24: 21989 | BR24: 17431
B25: 留存用户中的付费用户数 | C25: 837398 | D25: 840951 | E25: 646479 | F25: 605562 | G25: 549164 | H25: 492151 | I25: 473540 | J25: 460429 | K25: 351974 | L25: 345412 | M25: 284942 | N25: 315601 | O25: 364604 | P25: 379318 | Q25: 361240 | R25: 348372 | S25: 342540 | T25: 365825 | U25: 336609 | V25: 242461 | W25: 183476 | X25: 169106 | Y25: 146911 | Z25: 150882 | AA25: 192091 | AB25: 246611 | AC25: 227821 | AD25: 198053 | AE25: 213866 | AF25: 232627 | AG25: 306275 | AH25: 324449 | AI25: 268915 | AJ25: 241372 | AK25: 191431 | AL25: 186957 | AM25: 217228 | AN25: 202583 | AO25: 162738 | AP25: 151674 | AQ25: 133634 | AR25: 141953 | AS25: 195119 | AT25: 151292 | AU25: 114629 | AV25: 99849 | AW25: 92478 | AX25: 102139 | AY25: 92280 | AZ25: 102914 | BA25: 105889 | BB25: 94572 | BC25: 94608 | BD25: 105739 | BE25: 113731 | BF25: 120098 | BG25: 87490 | BH25: 87435 | BI25: 58641 | BJ25: 70720 | BK25: 68780 | BL25: 82258 | BM25: 62117 | BN25: 61840 | BO25: 63183 | BP25: 82177 | BQ25: 65723 | BR25: 68198
B26: 回流用户中的付费用户数 | C26: 58390 | D26: 35442 | E26: 19791 | F26: 25817 | G26: 22712 | H26: 26617 | I26: 38420 | J26: 23221 | K26: 17739 | L26: 21699 | M26: 14373 | N26: 28665 | O26: 57982 | P26: 23126 | Q26: 24111 | R26: 28233 | S26: 20168 | T26: 38916 | U26: 31590 | V26: 18912 | W26: 14587 | X26: 18520 | Y26: 13456 | Z26: 21868 | AA26: 38001 | AB26: 50711 | AC26: 36165 | AD26: 29687 | AE26: 31478 | AF26: 48155 | AG26: 61820 | AH26: 30612 | AI26: 20656 | AJ26: 22403 | AK26: 19590 | AL26: 20912 | AM26: 39384 | AN26: 20955 | AO26: 22834 | AP26: 18642 | AQ26: 21062 | AR26: 28544 | AS26: 38374 | AT26: 17333 | AU26: 13374 | AV26: 15399 | AW26: 13198 | AX26: 13188 | AY26: 18556 | AZ26: 22048 | BA26: 15396 | BB26: 15780 | BC26: 16206 | BD26: 17670 | BE26: 26242 | BF26: 24391 | BG26: 11937 | BH26: 11796 | BI26: 7195 | BJ26: 8593 | BK26: 14664 | BL26: 13073 | BM26: 8385 | BN26: 12554 | BO26: 12269 | BP26: 19076 | BQ26: 17331 | BR26: 11320
A27: 付费率 | B27: 付费率 | C27: 0.0896 | D27: 0.0944 | E27: 0.0886 | F27: 0.0815 | G27: 0.0806 | H27: 0.0734 | I27: 0.0627 | J27: 0.0591 | K27: 0.0569 | L27: 0.055 | M27: 0.0571 | N27: 0.062 | O27: 0.0427 | P27: 0.0501 | Q27: 0.0524 | R27: 0.044 | S27: 0.05 | T27: 0.0505 | U27: 0.041 | V27: 0.0298 | W27: 0.0337 | X27: 0.0307 | Y27: 0.0347 | Z27: 0.0333 | AA27: 0.0371 | AB27: 0.0383 | AC27: 0.0401 | AD27: 0.0364 | AE27: 0.0382 | AF27: 0.0358 | AG27: 0.0337 | AH27: 0.0343 | AI27: 0.0404 | AJ27: 0.036 | AK27: 0.0361 | AL27: 0.0419 | AM27: 0.0367 | AN27: 0.038 | AO27: 0.0362 | AP27: 0.0348 | AQ27: 0.0301 | AR27: 0.026 | AS27: 0.0238 | AT27: 0.0191 | AU27: 0.0238 | AV27: 0.0198 | AW27: 0.0223 | AX27: 0.0274 | AY27: 0.0238 | AZ27: 0.0208 | BA27: 0.0286 | BB27: 0.0251 | BC27: 0.0236 | BD27: 0.0229 | BE27: 0.0181 | BF27: 0.0196 | BG27: 0.0205 | BH27: 0.0202 | BI27: 0.0198 | BJ27: 0.0265 | BK27: 0.0193 | BL27: 0.0186 | BM27: 0.0209 | BN27: 0.0191 | BO27: 0.0207 | BP27: 0.0253 | BQ27: 0.0173 | BR27: 0.0174
B28: 付费率增长率 | C28: 0.0147 | D28: 0.0536 | E28: -0.0614 | F28: -0.0801 | G28: -0.011 | H28: -0.0893 | I28: -0.1458 | J28: -0.0574 | K28: -0.0372 | L28: -0.0334 | M28: 0.0382 | N28: 0.0858 | O28: -0.3113 | P28: 0.1733 | Q28: 0.0459 | R28: -0.1603 | S28: 0.1364 | T28: 0.01 | U28: -0.1881 | V28: -0.2732 | W28: 0.1309 | X28: -0.089 | Y28: 0.1303 | Z28: -0.0403 | AA28: 0.1141 | AB28: 0.0323 | AC28: 0.047 | AD28: -0.0923 | AE28: 0.0495 | AF28: -0.0628 | AG28: -0.0587 | AH28: 0.0178 | AI28: 0.1778 | AJ28: -0.1089 | AK28: 0.0028 | AL28: 0.1607 | AM28: -0.1241 | AN28: 0.0354 | AO28: -0.0474 | AP28: -0.0387 | AQ28: -0.1351 | AR28: -0.1362 | AS28: -0.0846 | AT28: -0.1975 | AU28: 0.2461 | AV28: -0.1681 | AW28: 0.1263 | AX28: 0.2287 | AY28: -0.1314 | AZ28: -0.1261 | BA28: 0.375 | BB28: -0.1224 | BC28: -0.0598 | BD28: -0.0297 | BE28: -0.2096 | BF28: 0.0829 | BG28: 0.0459 | BH28: -0.0146 | BI28: -0.0198 | BJ28: 0.3384 | BK28: -0.2717 | BL28: -0.0363 | BM28: 0.1237 | BN28: -0.0861 | BO28: 0.0838 | BP28: 0.2222 | BQ28: -0.3162 | BR28: 0.0058
B29: 新增用户付费率 | C29: 0.0141 | D29: 0.0151 | E29: 0.0163 | F29: 0.014 | G29: 0.0139 | H29: 0.0131 | I29: 0.0126 | J29: 0.0096 | K29: 0.0089 | L29: 0.0085 | M29: 0.009 | N29: 0.0087 | O29: 0.0067 | P29: 0.0086 | Q29: 0.0081 | R29: 0.0069 | S29: 0.0074 | T29: 0.0095 | U29: 0.0075 | V29: 0.0043 | W29: 0.0047 | X29: 0.0046 | Y29: 0.0052 | Z29: 0.0058 | AA29: 0.0066 | AB29: 0.0074 | AC29: 0.008 | AD29: 0.0067 | AE29: 0.0078 | AF29: 0.0089 | AG29: 0.009 | AH29: 0.0064 | AI29: 0.0066 | AJ29: 0.0064 | AK29: 0.0074 | AL29: 0.0079 | AM29: 0.0071 | AN29: 0.0068 | AO29: 0.0074 | AP29: 0.0061 | AQ29: 0.0062 | AR29: 0.0088 | AS29: 0.0074 | AT29: 0.0042 | AU29: 0.0052 | AV29: 0.0045 | AW29: 0.0052 | AX29: 0.0051 | AY29: 0.0051 | AZ29: 0.0046 | BA29: 0.0074 | BB29: 0.0072 | BC29: 0.0071 | BD29: 0.0061 | BE29: 0.0052 | BF29: 0.0048 | BG29: 0.0043 | BH29: 0.0041 | BI29: 0.0039 | BJ29: 0.0049 | BK29: 0.0054 | BL29: 0.0053 | BM29: 0.0079 | BN29: 0.0071 | BO29: 0.0077 | BP29: 0.0078 | BQ29: 0.0066 | BR29: 0.006
B30: 留存用户付费率 | C30: 0.145 | D30: 0.1329 | E30: 0.1168 | F30: 0.1145 | G30: 0.1074 | H30: 0.0998 | I30: 0.0939 | J30: 0.0878 | K30: 0.0775 | L30: 0.0791 | M30: 0.0745 | N30: 0.0927 | O30: 0.0911 | P30: 0.079 | Q30: 0.0874 | R30: 0.0822 | S30: 0.0799 | T30: 0.0863 | U30: 0.0759 | V30: 0.0548 | W30: 0.05 | X30: 0.0507 | Y30: 0.0509 | Z30: 0.0559 | AA30: 0.0643 | AB30: 0.0722 | AC30: 0.0679 | AD30: 0.0608 | AE30: 0.0631 | AF30: 0.0643 | AG30: 0.0667 | AH30: 0.0609 | AI30: 0.0668 | AJ30: 0.0649 | AK30: 0.0577 | AL30: 0.0687 | AM30: 0.0776 | AN30: 0.0672 | AO30: 0.0643 | AP30: 0.0617 | AQ30: 0.0542 | AR30: 0.0515 | AS30: 0.0496 | AT30: 0.0359 | AU30: 0.0394 | AV30: 0.0377 | AW30: 0.0382 | AX30: 0.0497 | AY30: 0.0463 | AZ30: 0.0466 | BA30: 0.0523 | BB30: 0.0456 | BC30: 0.0415 | BD30: 0.0433 | BE30: 0.04 | BF30: 0.0352 | BG30: 0.0334 | BH30: 0.0366 | BI30: 0.0313 | BJ30: 0.0482 | BK30: 0.0429 | BL30: 0.0381 | BM30: 0.0334 | BN30: 0.0328 | BO30: 0.0318 | BP30: 0.0445 | BQ30: 0.0331 | BR30: 0.0313
B31: 回流用户付费率 | C31: 0.0355 | D31: 0.0356 | E31: 0.0238 | F31: 0.0227 | G31: 0.0235 | H31: 0.0237 | I31: 0.0258 | J31: 0.0222 | K31: 0.0211 | L31: 0.0183 | M31: 0.0176 | N31: 0.0236 | O31: 0.0259 | P31: 0.0254 | Q31: 0.0224 | R31: 0.0209 | S31: 0.0214 | T31: 0.0263 | U31: 0.0237 | V31: 0.016 | W31: 0.0177 | X31: 0.015 | Y31: 0.0156 | Z31: 0.0167 | AA31: 0.0264 | AB31: 0.033 | AC31: 0.0307 | AD31: 0.0247 | AE31: 0.0247 | AF31: 0.0285 | AG31: 0.0311 | AH31: 0.0238 | AI31: 0.02 | AJ31: 0.016 | AK31: 0.0178 | AL31: 0.0203 | AM31: 0.0226 | AN31: 0.0203 | AO31: 0.0206 | AP31: 0.0185 | AQ31: 0.0188 | AR31: 0.0216 | AS31: 0.0237 | AT31: 0.0166 | AU31: 0.0169 | AV31: 0.0127 | AW31: 0.0144 | AX31: 0.0149 | AY31: 0.0164 | AZ31: 0.0165 | BA31: 0.0189 | BB31: 0.0163 | BC31: 0.0156 | BD31: 0.0152 | BE31: 0.0159 | BF31: 0.0201 | BG31: 0.013 | BH31: 0.0101 | BI31: 0.0091 | BJ31: 0.0096 | BK31: 0.0104 | BL31: 0.0112 | BM31: 0.0109 | BN31: 0.0113 | BO31: 0.0134 | BP31: 0.0174 | BQ31: 0.0126 | BR31: 0.0103
A32: 分类用户占比 | B32: 纯新增付费用户占比 | C32: 0.0478 | D32: 0.0413 | E32: 0.039 | F32: 0.0382 | G32: 0.0341 | H32: 0.0362 | I32: 0.0533 | J32: 0.0477 | K32: 0.0392 | L32: 0.0377 | M32: 0.032 | N32: 0.0344 | O32: 0.0682 | P32: 0.0629 | Q32: 0.057 | R32: 0.0662 | S32: 0.0538 | T32: 0.0703 | U32: 0.0808 | V32: 0.0651 | W32: 0.0522 | X32: 0.0593 | Y32: 0.053 | Z32: 0.067 | AA32: 0.0727 | AB32: 0.0882 | AC32: 0.0829 | AD32: 0.0729 | AE32: 0.078 | AF32: 0.1074 | AG32: 0.1336 | AH32: 0.0829 | AI32: 0.064 | AJ32: 0.0725 | AK32: 0.0775 | AL32: 0.0713 | AM32: 0.087 | AN32: 0.0755 | AO32: 0.0878 | AP32: 0.0757 | AQ32: 0.0944 | AR32: 0.1855 | AS32: 0.1765 | AT32: 0.1157 | AU32: 0.1026 | AV32: 0.1124 | AW32: 0.1076 | AX32: 0.0843 | AY32: 0.1033 | AZ32: 0.1194 | BA32: 0.1296 | BB32: 0.1379 | BC32: 0.141 | BD32: 0.1253 | BE32: 0.1587 | BF32: 0.1214 | BG32: 0.086 | BH32: 0.0831 | BI32: 0.0761 | BJ32: 0.0697 | BK32: 0.1316 | BL32: 0.1425 | BM32: 0.17 | BN32: 0.1668 | BO32: 0.1559 | BP32: 0.1292 | BQ32: 0.1901 | BR32: 0.1617
B33: 历史转化新增付费用户占比 | C33: 0.1686 | D33: 0.1779 | E33: 0.1533 | F33: 0.1362 | G33: 0.1251 | H33: 0.126 | I33: 0.1346 | J33: 0.1317 | K33: 0.1323 | L33: 0.1328 | M33: 0.1153 | N33: 0.1112 | O33: 0.13 | P33: 0.1461 | Q33: 0.1389 | R33: 0.1392 | S33: 0.1346 | T33: 0.1409 | U33: 0.1454 | V33: 0.1247 | W33: 0.1278 | X33: 0.1279 | Y33: 0.1204 | Z33: 0.1241 | AA33: 0.1505 | AB33: 0.1773 | AC33: 0.1848 | AD33: 0.1763 | AE33: 0.1786 | AF33: 0.1802 | AG33: 0.1944 | AH33: 0.215 | AI33: 0.2177 | AJ33: 0.2105 | AK33: 0.1787 | AL33: 0.1718 | AM33: 0.1976 | AN33: 0.1854 | AO33: 0.1758 | AP33: 0.175 | AQ33: 0.1417 | AR33: 0.1434 | AS33: 0.1855 | AT33: 0.1639 | AU33: 0.1632 | AV33: 0.1456 | AW33: 0.1483 | AX33: 0.1786 | AY33: 0.1517 | AZ33: 0.1539 | BA33: 0.1732 | BB33: 0.1735 | BC33: 0.1714 | BD33: 0.1721 | BE33: 0.1619 | BF33: 0.165 | BG33: 0.1625 | BH33: 0.1485 | BI33: 0.1215 | BJ33: 0.1697 | BK33: 0.1421 | BL33: 0.1561 | BM33: 0.1702 | BN33: 0.1554 | BO33: 0.1606 | BP33: 0.1503 | BQ33: 0.1341 | BR33: 0.1469
B34: 连续两月付费用户占比 | C34: 0.4455 | D34: 0.4914 | E34: 0.5482 | F34: 0.5196 | G34: 0.5461 | H34: 0.5298 | I34: 0.4543 | J34: 0.4836 | K34: 0.5156 | L34: 0.4927 | M34: 0.55 | N34: 0.4759 | O34: 0.4113 | P34: 0.4632 | Q34: 0.5065 | R34: 0.5132 | S34: 0.5235 | T34: 0.4688 | U34: 0.4801 | V34: 0.5385 | W34: 0.5267 | X34: 0.5196 | Y34: 0.5635 | Z34: 0.5169 | AA34: 0.4163 | AB34: 0.3458 | AC34: 0.4268 | AD34: 0.4766 | AE34: 0.4428 | AF34: 0.3921 | AG34: 0.3428 | AH34: 0.4322 | AI34: 0.4727 | AJ34: 0.4834 | AK34: 0.5096 | AL34: 0.4921 | AM34: 0.409 | AN34: 0.4667 | AO34: 0.4753 | AP34: 0.4833 | AQ34: 0.4879 | AR34: 0.3743 | AS34: 0.3273 | AT34: 0.4401 | AU34: 0.4541 | AV34: 0.4802 | AW34: 0.4885 | AX34: 0.468 | AY34: 0.4508 | AZ34: 0.3934 | BA34: 0.4152 | BB34: 0.4358 | BC34: 0.4161 | BD34: 0.4019 | BE34: 0.356 | BF34: 0.3655 | BG34: 0.4702 | BH34: 0.4581 | BI34: 0.5537 | BJ34: 0.4459 | BK34: 0.4054 | BL34: 0.3795 | BM34: 0.4369 | BN34: 0.4032 | BO34: 0.4156 | BP34: 0.3638 | BQ34: 0.4028 | BR34: 0.4039
B35: 回流付费用户占比 | C35: 0.3381 | D35: 0.2894 | E35: 0.2594 | F35: 0.3059 | G35: 0.2947 | H35: 0.308 | I35: 0.3578 | J35: 0.337 | K35: 0.3129 | L35: 0.3368 | M35: 0.3027 | N35: 0.3784 | O35: 0.3905 | P35: 0.3279 | Q35: 0.2976 | R35: 0.2814 | S35: 0.2881 | T35: 0.32 | U35: 0.2936 | V35: 0.2718 | W35: 0.2934 | X35: 0.2931 | Y35: 0.2631 | Z35: 0.2919 | AA35: 0.3606 | AB35: 0.3887 | AC35: 0.3055 | AD35: 0.2742 | AE35: 0.3006 | AF35: 0.3203 | AG35: 0.3292 | AH35: 0.2699 | AI35: 0.2456 | AJ35: 0.2336 | AK35: 0.2342 | AL35: 0.2648 | AM35: 0.3064 | AN35: 0.2724 | AO35: 0.2611 | AP35: 0.266 | AQ35: 0.2759 | AR35: 0.2968 | AS35: 0.3108 | AT35: 0.2803 | AU35: 0.2801 | AV35: 0.2624 | AW35: 0.2558 | AX35: 0.2691 | AY35: 0.2942 | AZ35: 0.3332 | BA35: 0.282 | BB35: 0.266 | BC35: 0.2714 | BD35: 0.3107 | BE35: 0.3345 | BF35: 0.3538 | BG35: 0.2954 | BH35: 0.3224 | BI35: 0.2526 | BJ35: 0.3147 | BK35: 0.3208 | BL35: 0.3219 | BM35: 0.223 | BN35: 0.2747 | BO35: 0.2679 | BP35: 0.3567 | BQ35: 0.2729 | BR35: 0.2875
A36: 分类用户付费额 | B36: 纯新增付费用户付费额 | C36: 1261586.4 | D36: 1297319.9 | E36: 888300.2 | F36: 909847.9 | G36: 772880.5 | H36: 762601.8 | I36: 1063194.2 | J36: 864577.9 | K36: 506858.3 | L36: 428185.4 | M36: 312334 | N36: 373334.3 | O36: 999814.2 | P36: 994765.5 | Q36: 745645.6 | R36: 833245.7 | S36: 748421.2 | T36: 1033989.1 | U36: 1135513.4 | V36: 645973.9 | W36: 387462.5 | X36: 422464.9 | Y36: 341584.5 | Z36: 479606.5 | AA36: 670031.2 | AB36: 1201120.3 | AC36: 1060640.7 | AD36: 750245.8 | AE36: 900914.7 | AF36: 1512508 | AG36: 2403907 | AH36: 1502729.2 | AI36: 884359 | AJ36: 873760.6 | AK36: 743755.5 | AL36: 672905.2 | AM36: 984817.9 | AN36: 945362.4 | AO36: 766148 | AP36: 622742.2 | AQ36: 783423.2 | AR36: 1676208.4 | AS36: 2346728.2 | AT36: 1094061.6 | AU36: 703787.7 | AV36: 694767.7 | AW36: 646384.8 | AX36: 569549.5 | AY36: 736555.5 | AZ36: 1032315.1 | BA36: 1015593.7 | BB36: 948218.8 | BC36: 1004950.4 | BD36: 988939.2 | BE36: 1440482.8 | BF36: 1108640.2 | BG36: 556698.3 | BH36: 523291.5 | BI36: 374639.6 | BJ36: 405442.8 | BK36: 739198.1 | BL36: 1152869.7 | BM36: 928066.9 | BN36: 1036483.7 | BO36: 942786.9 | BP36: 972828.2 | BQ36: 1246893.4 | BR36: 1053218.3
B37: 历史转化新增付费用户付费额 | C37: 3297254 | D37: 3910301.8 | E37: 2464242.2 | F37: 2144254.1 | G37: 1826025.7 | H37: 1650887 | I37: 1747766.5 | J37: 1648764.9 | K37: 1146226.3 | L37: 1095372.4 | M37: 754033.3 | N37: 863718.4 | O37: 1314436.5 | P37: 1713129.9 | Q37: 1277597 | R37: 1296597.7 | S37: 1318092.2 | T37: 1490463.9 | U37: 1463772.8 | V37: 853989.8 | W37: 703859.9 | X37: 642813.2 | Y37: 579340.8 | Z37: 647640.4 | AA37: 948444.4 | AB37: 1683918.5 | AC37: 1687078.4 | AD37: 1268263.6 | AE37: 1466344.3 | AF37: 1685048.5 | AG37: 2408578.9 | AH37: 2290660.5 | AI37: 1802106.1 | AJ37: 1380733.8 | AK37: 1114087.7 | AL37: 981493.2 | AM37: 1170250.6 | AN37: 1315257.5 | AO37: 981999.8 | AP37: 803812.6 | AQ37: 782737.6 | AR37: 1047329.9 | AS37: 1832779.5 | AT37: 1152988.4 | AU37: 927806.8 | AV37: 679816.1 | AW37: 693102.1 | AX37: 694935.1 | AY37: 760890 | AZ37: 834267.2 | BA37: 997687 | BB37: 897373.4 | BC37: 923977.5 | BD37: 934027.4 | BE37: 1001722.8 | BF37: 1156489.5 | BG37: 707752.1 | BH37: 578470.5 | BI37: 424166.2 | BJ37: 425433.7 | BK37: 541801.8 | BL37: 868541.5 | BM37: 720674.9 | BN37: 749487.1 | BO37: 722753 | BP37: 809158 | BQ37: 689253.4 | BR37: 727492.6
B38: 连续两月付费用户付费额 | C38: 19157728 | D38: 23158072 | E38: 15305685 | F38: 16414871 | G38: 13918919 | H38: 12246755 | I38: 10123530 | J38: 11227651 | K38: 7327710 | L38: 6615247.5 | M38: 6006706.6 | N38: 6136002.5 | O38: 7673607 | P38: 9657866.5 | Q38: 7383623.2 | R38: 7031831 | S38: 8486085 | T38: 8709822.7 | U38: 7738715.4 | V38: 6436979.3 | W38: 4031320.7 | X38: 3340989 | Y38: 4093114.9 | Z38: 4264601.6 | AA38: 3927873.5 | AB38: 6680143.3 | AC38: 6544062.6 | AD38: 6107888.9 | AE38: 6209552.1 | AF38: 6917496.4 | AG38: 7852308.4 | AH38: 10754892 | AI38: 7356944.1 | AJ38: 6799531.4 | AK38: 5896416.8 | AL38: 5283258.8 | AM38: 6467809.9 | AN38: 7801277.2 | AO38: 5230776.6 | AP38: 4597155.9 | AQ38: 4999224.1 | AR38: 5094709.1 | AS38: 5906438.3 | AT38: 6437859.4 | AU38: 5025287.7 | AV38: 4883942.3 | AW38: 4197095.9 | AX38: 4409886.3 | AY38: 4397083.8 | AZ38: 5573267.8 | BA38: 5017027.6 | BB38: 5015700.6 | BC38: 5024331.9 | BD38: 5086333.5 | BE38: 5450713.9 | BF38: 5717770.4 | BG38: 5289512.7 | BH38: 4428861.8 | BI38: 3817236.6 | BJ38: 3229310 | BK38: 3678776.1 | BL38: 6036134.8 | BM38: 3318265.9 | BN38: 4041177.1 | BO38: 3501647.8 | BP38: 3824205.2 | BQ38: 4146454 | BR38: 3601263.3
B39: 回流付费用户付费额 | C39: 8498289.8 | D39: 8584292.3 | E39: 5346840.8 | F39: 6326246.8 | G39: 5217667.2 | H39: 4917607.3 | I39: 5672747.9 | J39: 5190398.4 | K39: 3372637 | L39: 3168906 | M39: 2299743.7 | N39: 3323568.1 | O39: 5168509.6 | P39: 4897250.8 | Q39: 3217082.2 | R39: 2978461.5 | S39: 3359066.7 | T39: 4031261.4 | U39: 3642391.1 | V39: 2339448.3 | W39: 2041117.4 | X39: 1623125.9 | Y39: 1607040.1 | Z39: 1959602.7 | AA39: 2438403.8 | AB39: 4641551.1 | AC39: 3448179 | AD39: 2280698.6 | AE39: 2918511.6 | AF39: 3765353.7 | AG39: 5044819.5 | AH39: 4367757.7 | AI39: 3162473.5 | AJ39: 2390348.6 | AK39: 1992507 | AL39: 2122131.6 | AM39: 3468038.4 | AN39: 3641976 | AO39: 2315846.6 | AP39: 1838275.9 | AQ39: 2169193.8 | AR39: 3144930 | AS39: 4443766.7 | AT39: 2480774.3 | AU39: 2261931.9 | AV39: 1751431.1 | AW39: 1540091.1 | AX39: 1775283.7 | AY39: 2176088.8 | AZ39: 3285627.5 | BA39: 2662045.7 | BB39: 2078712.5 | BC39: 2180089.1 | BD39: 2533132.3 | BE39: 3220957.6 | BF39: 3337267.3 | BG39: 2087915.6 | BH39: 1785158.3 | BI39: 1252987.2 | BJ39: 1356621 | BK39: 2185850.2 | BL39: 3192801.9 | BM39: 1525501.7 | BN39: 2032213.1 | BO39: 1849192.4 | BP39: 2792200.1 | BQ39: 2100584.9 | BR39: 1960306.1
B40: 新增用户付费额 | C40: 1261586.4 | D40: 1297319.9 | E40: 888300.2 | F40: 909847.9 | G40: 772880.5 | H40: 762601.8 | I40: 1063194.2 | J40: 864577.9 | K40: 506858.3 | L40: 428185.4 | M40: 312334 | N40: 373334.3 | O40: 999814.2 | P40: 994765.5 | Q40: 745645.6 | R40: 833245.7 | S40: 748421.2 | T40: 1033989.1 | U40: 1135513.4 | V40: 645973.9 | W40: 387462.5 | X40: 422464.9 | Y40: 341584.5 | Z40: 479606.5 | AA40: 670031.2 | AB40: 1201120.3 | AC40: 1060640.7 | AD40: 750245.8 | AE40: 900914.7 | AF40: 1512508 | AG40: 2403907 | AH40: 1502729.2 | AI40: 884359 | AJ40: 873760.6 | AK40: 743755.5 | AL40: 672905.2 | AM40: 984817.9 | AN40: 945362.4 | AO40: 766148 | AP40: 622742.2 | AQ40: 783423.2 | AR40: 1676208.4 | AS40: 2346728.2 | AT40: 1094061.6 | AU40: 703787.7 | AV40: 694767.7 | AW40: 646384.8 | AX40: 569549.5 | AY40: 736555.5 | AZ40: 1032315.1 | BA40: 1015593.7 | BB40: 948218.8 | BC40: 1004950.4 | BD40: 988939.2 | BE40: 1440482.8 | BF40: 1108640.2 | BG40: 556698.3 | BH40: 523291.5 | BI40: 374639.6 | BJ40: 405442.8 | BK40: 739198.1 | BL40: 1152869.7 | BM40: 928066.9 | BN40: 1036483.7 | BO40: 942786.9 | BP40: 972828.2 | BQ40: 1246893.4 | BR40: 1053218.3
B41: 留存用户付费额 | C41: 29468389 | D41: 34505396 | E41: 22361263 | F41: 23998101 | G41: 20116905 | H41: 17855650 | I41: 16295356 | J41: 17288638 | K41: 11199116 | L41: 10200452 | M41: 8533392.9 | N41: 9481483.7 | O41: 12578272 | P41: 15357715 | Q41: 11078870 | R41: 10405179 | S41: 12376832 | T41: 13011985 | U41: 11756286 | V41: 8923824.7 | W41: 6133791 | X41: 4928619.2 | Y41: 5642744.7 | Z41: 6021140.5 | AA41: 6198751.6 | AB41: 11494783 | AC41: 10469441 | AD41: 8686012.3 | AE41: 9512046.7 | AF41: 10719101 | AG41: 13370984 | AH41: 16270182 | AI41: 11424748 | AJ41: 9741578.8 | AK41: 8216955.5 | AL41: 7551563.5 | AM41: 9726627.2 | AN41: 11755816 | AO41: 7558115.3 | AP41: 6429427.7 | AQ41: 7002450.1 | AR41: 7971919.1 | AS41: 10358958 | AT41: 9256622.8 | AU41: 7464392.3 | AV41: 6555498.4 | AW41: 5762391.2 | AX41: 6142102.1 | AY41: 6391484.3 | AZ41: 8454708.4 | BA41: 7752358 | BB41: 7082354.1 | BC41: 7243627.6 | BD41: 7561407 | BE41: 8274276.2 | BF41: 8922413 | BG41: 7349121 | BH41: 6088991.8 | BI41: 4995529.1 | BJ41: 4464033.2 | BK41: 5550696.1 | BL41: 9134545.3 | BM41: 4898545.5 | BN41: 5956197.5 | BO41: 5212200.6 | BP41: 6243528.1 | BQ41: 5867001.8 | BR41: 5490960.7
B42: 回流用户付费额 | C42: 1325412.9 | D42: 970579.8 | E42: 526945.8 | F42: 716124.8 | G42: 660226.3 | H42: 776028.9 | I42: 1081878.9 | J42: 593506.3 | K42: 417727.2 | L42: 463973.6 | M42: 301010.7 | N42: 624575.3 | O42: 1409391.1 | P42: 700991.8 | Q42: 568182.1 | R42: 667352.9 | S42: 526026.8 | T42: 979832.9 | U42: 848733.4 | V42: 442312.7 | W42: 331067 | X42: 372718.9 | Y42: 314531.1 | Z42: 542954.2 | AA42: 830340.1 | AB42: 1319029.5 | AC42: 991379.1 | AD42: 746898.8 | AE42: 861711.3 | AF42: 1454297.5 | AG42: 1751689.5 | AH42: 953518.5 | AI42: 649965.7 | AJ42: 581475 | AK42: 519934 | AL42: 562340.1 | AM42: 1156261.7 | AN42: 760254.4 | AO42: 710417.7 | AP42: 542875.7 | AQ42: 675779.4 | AR42: 1103113.9 | AS42: 1621727.5 | AT42: 641024.3 | AU42: 543485.2 | AV42: 573609.1 | AW42: 476298.5 | AX42: 542663.7 | AY42: 754850.1 | AZ42: 1055178.2 | BA42: 717188.2 | BB42: 708446.7 | BC42: 723024.6 | BD42: 814649.8 | BE42: 1215278.4 | BF42: 1126895.1 | BG42: 563421 | BH42: 525828.1 | BI42: 350039.7 | BJ42: 394648.6 | BK42: 727727.7 | BL42: 842023.4 | BM42: 538282.8 | BN42: 740843.5 | BO42: 738390.4 | BP42: 1067094.8 | BQ42: 956301.2 | BR42: 684261.1
A43: ARPPU值 | B43: 纯新增付费用户ARPPU值 | C43: 27.56 | D43: 33.66 | E43: 31.76 | F43: 35.3 | G43: 37.15 | H43: 37.8 | I43: 35.73 | J43: 34.43 | K43: 31.65 | L43: 28.15 | M43: 29.36 | N43: 28.62 | O43: 31.1 | P43: 35.04 | Q43: 30.23 | R43: 29.4 | S43: 33.92 | T43: 31.93 | U43: 32.98 | V43: 32.32 | W43: 30.81 | X43: 30.8 | Y43: 31.81 | Z43: 32.91 | AA43: 33.16 | AB43: 39.28 | AC43: 41.1 | AD43: 38.19 | AE43: 39.9 | AF43: 41.92 | AG43: 40.38 | AH43: 44.47 | AI43: 41.25 | AJ43: 38.83 | AK43: 37.37 | AL43: 37.41 | AM43: 37.16 | AN43: 46.84 | AO43: 37.74 | AP43: 38.7 | AQ43: 41.48 | AR43: 38.55 | AS43: 43.3 | AT43: 45.02 | AU43: 41.49 | AV43: 41.23 | AW43: 43.17 | AX43: 46.11 | AY43: 49.57 | AZ43: 53.36 | BA43: 48.27 | BB43: 47.01 | BC43: 48.42 | BD43: 50.3 | BE43: 49.89 | BF43: 50.88 | BG43: 52.25 | BH43: 51.34 | BI43: 57.53 | BJ43: 58.31 | BK43: 50.97 | BL43: 64.91 | BM43: 54.8 | BN43: 60.09 | BO43: 58.66 | BP43: 58.38 | BQ43: 56.71 | BR43: 60.42
B44: 历史转化新增付费用户ARPPU值 | C44: 20.43 | D44: 23.58 | E44: 22.42 | F44: 23.36 | G44: 23.89 | H44: 23.52 | I44: 23.26 | J44: 23.75 | K44: 21.22 | L44: 20.45 | M44: 19.69 | N44: 20.51 | O44: 21.45 | P44: 25.98 | Q44: 21.26 | R44: 21.77 | S44: 23.86 | T44: 22.96 | U44: 23.62 | V44: 22.3 | W44: 22.85 | X44: 21.73 | Y44: 23.74 | Z44: 24.01 | AA44: 22.66 | AB44: 27.4 | AC44: 29.35 | AD44: 26.72 | AE44: 28.36 | AF44: 27.83 | AG44: 27.8 | AH44: 26.15 | AI44: 24.71 | AJ44: 21.13 | AK44: 24.27 | AL44: 22.66 | AM44: 19.44 | AN44: 26.54 | AO44: 24.17 | AP44: 21.62 | AQ44: 27.62 | AR44: 31.15 | AS44: 32.18 | AT44: 33.48 | AU44: 34.38 | AV44: 31.15 | AW44: 33.59 | AX44: 26.54 | AY44: 34.87 | AZ44: 33.45 | BA44: 35.47 | BB44: 35.37 | BC44: 36.62 | BD44: 34.6 | BE44: 34.01 | BF44: 39.05 | BG44: 35.18 | BH44: 31.76 | BI44: 40.76 | BJ44: 25.12 | BK44: 34.6 | BL44: 44.63 | BM44: 42.5 | BN44: 46.64 | BO44: 43.64 | BP44: 41.74 | BQ44: 44.42 | BR44: 45.94
B45: 连续两月付费用户ARPPU值 | C45: 44.92 | D45: 50.55 | E45: 38.95 | F45: 46.87 | G45: 41.72 | H45: 41.5 | I45: 39.93 | J45: 44.06 | K45: 34.81 | L45: 33.28 | M45: 32.88 | N45: 34.05 | O45: 39.58 | P45: 46.19 | Q45: 33.69 | R45: 32.02 | S45: 39.52 | T45: 40.33 | U45: 37.83 | V45: 38.91 | W45: 31.74 | X45: 27.81 | Y45: 35.86 | Z45: 37.96 | AA45: 33.92 | AB45: 55.74 | AC45: 49.28 | AD45: 47.59 | AE45: 48.44 | AF45: 52.51 | AG45: 51.4 | AH45: 61.08 | AI45: 46.45 | AJ45: 45.32 | AK45: 45.04 | AL45: 42.58 | AM45: 51.91 | AN45: 62.55 | AO45: 47.61 | AP45: 44.77 | AQ45: 51.23 | AR45: 58.06 | AS45: 58.77 | AT45: 69.64 | AU45: 66.92 | AV45: 67.86 | AW45: 61.77 | AX45: 64.29 | AY45: 67.82 | AZ45: 87.43 | BA45: 74.42 | BB45: 78.68 | BC45: 82.04 | BD45: 80.65 | BE45: 84.14 | BF45: 87.16 | BG45: 90.86 | BH45: 78.84 | BI45: 80.52 | BJ45: 72.54 | BK45: 82.36 | BL45: 127.59 | BM45: 76.23 | BN45: 96.91 | BO45: 81.72 | BP45: 81.48 | BQ45: 89 | BR45: 82.71
B46: 回流付费用户ARPPU值 | C46: 26.26 | D46: 31.82 | E46: 28.76 | F46: 30.68 | G46: 28.98 | H46: 28.67 | I46: 28.41 | J46: 29.23 | K46: 26.4 | L46: 23.32 | M46: 22.87 | N46: 23.19 | O46: 28.08 | P46: 33.09 | Q46: 24.98 | R46: 24.74 | S46: 28.42 | T46: 27.35 | U46: 29.11 | V46: 28.01 | W46: 28.85 | X46: 23.95 | Y46: 30.15 | Z46: 30.89 | AA46: 24.31 | AB46: 34.45 | AC46: 36.27 | AD46: 30.89 | AE46: 33.53 | AF46: 34.99 | AG46: 34.39 | AH46: 39.72 | AI46: 38.42 | AJ46: 32.96 | AK46: 33.13 | AL46: 31.78 | AM46: 37.15 | AN46: 50.02 | AO46: 38.38 | AP46: 32.53 | AQ46: 39.31 | AR46: 45.21 | AS46: 46.56 | AT46: 42.13 | AU46: 48.84 | AV46: 44.54 | AW46: 43.28 | AX46: 45.01 | AY46: 51.44 | AZ46: 60.86 | BA46: 58.15 | BB46: 53.42 | BC46: 54.59 | BD46: 51.96 | BE46: 52.92 | BF46: 52.56 | BG46: 57.08 | BH46: 45.16 | BI46: 57.93 | BJ46: 43.18 | BK46: 61.84 | BL46: 79.56 | BM46: 68.67 | BN46: 71.52 | BO46: 66.93 | BP46: 60.68 | BQ46: 66.54 | BR46: 63.25
B47: 新增用户ARPPU值 | C47: 27.56 | D47: 33.66 | E47: 31.76 | F47: 35.3 | G47: 37.15 | H47: 37.8 | I47: 35.73 | J47: 34.43 | K47: 31.65 | L47: 28.15 | M47: 29.36 | N47: 28.62 | O47: 31.1 | P47: 35.04 | Q47: 30.23 | R47: 29.4 | S47: 33.92 | T47: 31.93 | U47: 32.98 | V47: 32.32 | W47: 30.81 | X47: 30.8 | Y47: 31.81 | Z47: 32.91 | AA47: 33.16 | AB47: 39.28 | AC47: 41.1 | AD47: 38.19 | AE47: 39.9 | AF47: 41.92 | AG47: 40.38 | AH47: 44.47 | AI47: 41.25 | AJ47: 38.83 | AK47: 37.37 | AL47: 37.41 | AM47: 37.16 | AN47: 46.84 | AO47: 37.74 | AP47: 38.7 | AQ47: 41.48 | AR47: 38.55 | AS47: 43.3 | AT47: 45.02 | AU47: 41.49 | AV47: 41.23 | AW47: 43.17 | AX47: 46.11 | AY47: 49.57 | AZ47: 53.36 | BA47: 48.27 | BB47: 47.01 | BC47: 48.42 | BD47: 50.3 | BE47: 49.89 | BF47: 50.88 | BG47: 52.25 | BH47: 51.34 | BI47: 57.53 | BJ47: 58.31 | BK47: 50.97 | BL47: 64.91 | BM47: 54.8 | BN47: 60.09 | BO47: 58.66 | BP47: 58.38 | BQ47: 56.71 | BR47: 60.42
B48: 留存用户ARPPU值 | C48: 35.19 | D48: 41.03 | E48: 34.59 | F48: 39.63 | G48: 36.63 | H48: 36.28 | I48: 34.41 | J48: 37.55 | K48: 31.82 | L48: 29.53 | M48: 29.95 | N48: 30.04 | O48: 34.5 | P48: 40.49 | Q48: 30.67 | R48: 29.87 | S48: 36.13 | T48: 35.57 | U48: 34.93 | V48: 36.81 | W48: 33.43 | X48: 29.15 | Y48: 38.41 | Z48: 39.91 | AA48: 32.27 | AB48: 46.61 | AC48: 45.95 | AD48: 43.86 | AE48: 44.48 | AF48: 46.08 | AG48: 43.66 | AH48: 50.15 | AI48: 42.48 | AJ48: 40.36 | AK48: 42.92 | AL48: 40.39 | AM48: 44.78 | AN48: 58.03 | AO48: 46.44 | AP48: 42.39 | AQ48: 52.4 | AR48: 56.16 | AS48: 53.09 | AT48: 61.18 | AU48: 65.12 | AV48: 65.65 | AW48: 62.31 | AX48: 60.13 | AY48: 69.26 | AZ48: 82.15 | BA48: 73.21 | BB48: 74.89 | BC48: 76.56 | BD48: 71.51 | BE48: 72.75 | BF48: 74.29 | BG48: 84 | BH48: 69.64 | BI48: 85.19 | BJ48: 63.12 | BK48: 80.7 | BL48: 111.05 | BM48: 78.86 | BN48: 96.32 | BO48: 82.49 | BP48: 75.98 | BQ48: 89.27 | BR48: 80.51
B49: 回流用户ARPPU值 | C49: 22.7 | D49: 27.39 | E49: 26.63 | F49: 27.74 | G49: 29.07 | H49: 29.16 | I49: 28.16 | J49: 25.56 | K49: 23.55 | L49: 21.38 | M49: 20.94 | N49: 21.79 | O49: 24.31 | P49: 30.31 | Q49: 23.57 | R49: 23.64 | S49: 26.08 | T49: 25.18 | U49: 26.87 | V49: 23.39 | W49: 22.7 | X49: 20.13 | Y49: 23.37 | Z49: 24.83 | AA49: 21.85 | AB49: 26.01 | AC49: 27.41 | AD49: 25.16 | AE49: 27.38 | AF49: 30.2 | AG49: 28.34 | AH49: 31.15 | AI49: 31.47 | AJ49: 25.96 | AK49: 26.54 | AL49: 26.89 | AM49: 29.36 | AN49: 36.28 | AO49: 31.11 | AP49: 29.12 | AQ49: 32.09 | AR49: 38.65 | AS49: 42.26 | AT49: 36.98 | AU49: 40.64 | AV49: 37.25 | AW49: 36.09 | AX49: 41.15 | AY49: 40.68 | AZ49: 47.86 | BA49: 46.58 | BB49: 44.9 | BC49: 44.61 | BD49: 46.1 | BE49: 46.31 | BF49: 46.2 | BG49: 47.2 | BH49: 44.58 | BI49: 48.65 | BJ49: 45.93 | BK49: 49.63 | BL49: 64.41 | BM49: 64.2 | BN49: 59.01 | BO49: 60.18 | BP49: 55.94 | BQ49: 55.18 | BR49: 60.45
B50: 1
B51: 2
A52: 赛尔号活跃情况 | C52: 2011-01 | D52: 2011-02 | E52: 2011-03 | F52: 2011-04 | G52: 2011-05 | H52: 2011-06 | I52: 2011-07 | J52: 2011-08 | K52: 2011-09 | L52: 2011-10 | M52: 2011-11 | N52: 2011-12 | O52: 2012-01 | P52: 2012-02 | Q52: 2012-03 | R52: 2012-04 | S52: 2012-05 | T52: 2012-06 | U52: 2012-07 | V52: 2012-08 | W52: 2012-09 | X52: 2012-10 | Y52: 2012-11 | Z52: 2012-12 | AA52: 2013-01 | AB52: 2013-02 | AC52: 2013-03 | AD52: 2013-04 | AE52: 2013-05 | AF52: 2013-06 | AG52: 2013-07 | AH52: 2013-08 | AI52: 2013-09 | AJ52: 2013-10 | AK52: 2013-11 | AL52: 2013-12 | AM52: 2014-01 | AN52: 2014-02 | AO52: 2014-03 | AP52: 2014-04 | AQ52: 2014-05 | AR52: 2014-06 | AS52: 2014-07 | AT52: 2014-08 | AU52: 2014-09 | AV52: 2014-10 | AW52: 2014-11 | AX52: 2014-12 | AY52: 2015-01 | AZ52: 2015-02 | BA52: 2015-03 | BB52: 42095 | BC52: 42125 | BD52: 42156 | BE52: 42186 | BF52: 42217 | BG52: 42248 | BH52: 42278 | BI52: 42309 | BJ52: 42339 | BK52: 42370 | BL52: 42401 | BM52: 42430 | BN52: 42461 | BO52: 42491 | BP52: 42522 | BQ52: 42552 | BR52: 42583
A53: 基本情况 | B53: 活跃用户 | C53: 10679060 | D53: 9880147 | E53: 8087431 | F53: 8271173 | G53: 7580424 | H53: 7591640 | I53: 8898732 | J53: 8913903 | K53: 7176807 | L53: 7341309 | M53: 5816303 | N53: 6110993 | O53: 11034122 | P53: 9010783 | Q53: 8260490 | R53: 9721155 | S53: 8197388 | T53: 9117619 | U53: 10387635 | V53: 10298946 | W53: 7157943 | X53: 7540848 | Y53: 5833443 | Z53: 6523696 | AA53: 7493941 | AB53: 9061008 | AC53: 7759542 | AD53: 7397781 | AE53: 7579168 | AF53: 9384143 | AG53: 13227005 | AH53: 11866512 | AI53: 8291170 | AJ53: 8623055 | AK53: 7110393 | AL53: 6018438 | AM53: 8290071 | AN53: 7033913 | AO53: 6389881 | AP53: 6109562 | AQ53: 6646426 | AR53: 9025892 | AS53: 12908482 | AT53: 11002398 | AU53: 6943137 | AV53: 7577095 | AW53: 6224519 | AX53: 5342486 | AY53: 6039670 | AZ53: 7788706 | BA53: 5668656 | BB53: 5839002 | BC53: 6243449 | BD53: 6857571 | BE53: 10053296 | BF53: 9145826 | BG53: 6034601 | BH53: 6061079 | BI53: 4315715 | BJ53: 3771377 | BK53: 5703925 | BL53: 6703027 | BM53: 4762248 | BN53: 5414168 | BO53: 4979716 | BP53: 5088996 | BQ53: 6684506 | BR53: 6187050
B54: 活跃用户增长率 | C54: 0.2765 | D54: -0.0748 | E54: -0.1814 | F54: 0.0227 | G54: -0.0835 | H54: 0.0015 | I54: 0.1722 | J54: 0.0017 | K54: -0.1949 | L54: 0.0229 | M54: -0.2077 | N54: 0.0507 | O54: 0.8056 | P54: -0.1834 | Q54: -0.0833 | R54: 0.1768 | S54: -0.1567 | T54: 0.1123 | U54: 0.1393 | V54: -0.0085 | W54: -0.305 | X54: 0.0535 | Y54: -0.2264 | Z54: 0.1183 | AA54: 0.1487 | AB54: 0.2091 | AC54: -0.1436 | AD54: -0.0466 | AE54: 0.0245 | AF54: 0.2381 | AG54: 0.4095 | AH54: -0.1029 | AI54: -0.3013 | AJ54: 0.04 | AK54: -0.1754 | AL54: -0.1536 | AM54: 0.3774 | AN54: -0.1515 | AO54: -0.0916 | AP54: -0.0439 | AQ54: 0.0879 | AR54: 0.358 | AS54: 0.4302 | AT54: -0.1477 | AU54: -0.3689 | AV54: 0.0913 | AW54: -0.1785 | AX54: -0.1417 | AY54: 0.1305 | AZ54: 0.2896 | BA54: -0.2722 | BB54: 0.0301 | BC54: 0.0693 | BD54: 0.0984 | BE54: 0.466 | BF54: -0.0903 | BG54: -0.3402 | BH54: 0.0044 | BI54: -0.288 | BJ54: -0.1261 | BK54: 0.5124 | BL54: 0.1752 | BM54: -0.2895 | BN54: 0.1369 | BO54: -0.0802 | BP54: 0.0219 | BQ54: 0.3135 | BR54: -0.0744
B55: 有效活跃用户 | C55: 0 | D55: 0 | E55: 0 | F55: 0 | G55: 0 | H55: 0 | I55: 0 | J55: 0 | K55: 0 | L55: 0 | M55: 0 | N55: 0 | O55: 0 | P55: 0 | Q55: 0 | R55: 0 | S55: 0 | T55: 0 | U55: 0 | V55: 0 | W55: 0 | X55: 0 | Y55: 0 | Z55: 0 | AA55: 0 | AB55: 0 | AC55: 0 | AD55: 0 | AE55: 0 | AF55: 0 | AG55: 0 | AH55: 0 | AI55: 0 | AJ55: 0 | AK55: 0 | AL55: 0 | AM55: 0 | AN55: 0 | AO55: 0 | AP55: 0 | AQ55: 926381 | AR55: 4501180 | AS55: 6605478 | AT55: 5022467 | AU55: 2730113 | AV55: 2809427 | AW55: 2400265 | AX55: 2064633 | AY55: 2354765 | AZ55: 2995687 | BA55: 2249439 | BB55: 2380117 | BC55: 2555367 | BD55: 2604272 | BE55: 3926354 | BF55: 3746458 | BG55: 2039085 | BH55: 1924247 | BI55: 1271014 | BJ55: 1084966 | BK55: 2159394 | BL55: 2638424 | BM55: 1811700 | BN55: 1883515 | BO55: 1697382 | BP55: 1770724 | BQ55: 2290131 | BR55: 2231718
B56: 有效活跃用户增长率 | C56: 0 | D56: 0 | E56: 0 | F56: 0 | G56: 0 | H56: 0 | I56: 0 | J56: 0 | K56: 0 | L56: 0 | M56: 0 | N56: 0 | O56: 0 | P56: 0 | Q56: 0 | R56: 0 | S56: 0 | T56: 0 | U56: 0 | V56: 0 | W56: 0 | X56: 0 | Y56: 0 | Z56: 0 | AA56: 0 | AB56: 0 | AC56: 0 | AD56: 0 | AE56: 0 | AF56: 0 | AG56: 0 | AH56: 0 | AI56: 0 | AJ56: 0 | AK56: 0 | AL56: 0 | AM56: 0 | AN56: 0 | AO56: 0 | AP56: 0 | AQ56: 0 | AR56: 3.8589 | AS56: 0.4675 | AT56: -0.2397 | AU56: -0.4564 | AV56: 0.0291 | AW56: -0.1456 | AX56: -0.1398 | AY56: 0.1405 | AZ56: 0.2722 | BA56: -0.2491 | BB56: 0.0581 | BC56: 0.0736 | BD56: 0.0191 | BE56: 0.5077 | BF56: -0.0458 | BG56: -0.4557 | BH56: -0.0563 | BI56: -0.3395 | BJ56: -0.1464 | BK56: 0.9903 | BL56: 0.2218 | BM56: -0.3133 | BN56: 0.0396 | BO56: -0.0988 | BP56: 0.0432 | BQ56: 0.2933 | BR56: -0.0255
B57: 新增活跃用户 | C57: 3256904 | D57: 2558596 | E57: 1721069 | F57: 1842163 | G57: 1499518 | H57: 1539015 | I57: 2366199 | J57: 2623520 | K57: 1795420 | L57: 1787517 | M57: 1177400 | N57: 1492447 | O57: 4797256 | P57: 3301892 | Q57: 3050035 | R57: 4132643 | S57: 2966107 | T57: 3399027 | U57: 4619054 | V57: 4687180 | W57: 2662129 | X57: 2971793 | Y57: 2080550 | Z57: 2520178 | AA57: 3067741 | AB57: 4110786 | AC57: 3222656 | AD57: 2940286 | AE57: 2912107 | AF57: 4076748 | AG57: 6647242 | AH57: 5256274 | AI57: 3234794 | AJ57: 3503276 | AK57: 2696251 | AL57: 2266631 | AM57: 3750622 | AN57: 2988574 | AO57: 2748061 | AP57: 2640339 | AQ57: 3059214 | AR57: 4949525 | AS57: 7360407 | AT57: 5748137 | AU57: 3238155 | AV57: 3717233 | AW57: 2885138 | AX57: 2399970 | AY57: 2913043 | AZ57: 4238236 | BA57: 2828980 | BB57: 2799943 | BC57: 2927049 | BD57: 3249013 | BE57: 5559856 | BF57: 4516067 | BG57: 2495368 | BH57: 2508219 | BI57: 1650193 | BJ57: 1411262 | BK57: 2695028 | BL57: 3372906 | BM57: 2131206 | BN57: 2419053 | BO57: 2080827 | BP57: 2147256 | BQ57: 3322397 | BR57: 2913258
B58: 新增活跃用户增长率 | C58: 0.7895 | D58: -0.2144 | E58: -0.3273 | F58: 0.0704 | G58: -0.186 | H58: 0.0263 | I58: 0.5375 | J58: 0.1087 | K58: -0.3156 | L58: -0.0044 | M58: -0.3413 | N58: 0.2676 | O58: 2.2144 | P58: -0.3117 | Q58: -0.0763 | R58: 0.3549 | S58: -0.2823 | T58: 0.146 | U58: 0.3589 | V58: 0.0147 | W58: -0.432 | X58: 0.1163 | Y58: -0.2999 | Z58: 0.2113 | AA58: 0.2173 | AB58: 0.34 | AC58: -0.216 | AD58: -0.0876 | AE58: -0.0096 | AF58: 0.3999 | AG58: 0.6305 | AH58: -0.2093 | AI58: -0.3846 | AJ58: 0.083 | AK58: -0.2304 | AL58: -0.1593 | AM58: 0.6547 | AN58: -0.2032 | AO58: -0.0805 | AP58: -0.0392 | AQ58: 0.1586 | AR58: 0.6179 | AS58: 0.4871 | AT58: -0.219 | AU58: -0.4367 | AV58: 0.1479 | AW58: -0.2238 | AX58: -0.1682 | AY58: 0.2138 | AZ58: 0.4549 | BA58: -0.3325 | BB58: -0.0103 | BC58: 0.0454 | BD58: 0.11 | BE58: 0.7112 | BF58: -0.1877 | BG58: -0.4474 | BH58: 0.0051 | BI58: -0.3421 | BJ58: -0.1448 | BK58: 0.9097 | BL58: 0.2515 | BM58: -0.3681 | BN58: 0.1351 | BO58: -0.1398 | BP58: 0.0319 | BQ58: 0.5473 | BR58: -0.1231
B59: 留存用户 | C59: 5776495 | D59: 6326681 | E59: 5536522 | F59: 5289541 | G59: 5115106 | H59: 4930833 | I59: 5045004 | J59: 5243039 | K59: 4540015 | L59: 4365701 | M59: 3823037 | N59: 3404515 | O59: 4001505 | P59: 4799034 | Q59: 4134678 | R59: 4237546 | S59: 4287870 | T59: 4241299 | U59: 4436982 | V59: 4428419 | W59: 3669631 | X59: 3336959 | Y59: 2888212 | Z59: 2697633 | AA59: 2987462 | AB59: 3414968 | AC59: 3357562 | AD59: 3254847 | AE59: 3390393 | AF59: 3618904 | AG59: 4593255 | AH59: 5325991 | AI59: 4026131 | AJ59: 3717764 | AK59: 3315802 | AL59: 2722088 | AM59: 2798950 | AN59: 3014774 | AO59: 2532106 | AP59: 2460202 | AQ59: 2464583 | AR59: 2756046 | AS59: 3931546 | AT59: 4210503 | AU59: 2911881 | AV59: 2645155 | AW59: 2422974 | AX59: 2056544 | AY59: 1994651 | AZ59: 2210395 | BA59: 2025906 | BB59: 2072959 | BC59: 2278519 | BD59: 2442710 | BE59: 2846751 | BF59: 3416403 | BG59: 2617482 | BH59: 2387065 | BI59: 1871139 | BJ59: 1467641 | BK59: 1603573 | BL59: 2158369 | BM59: 1860336 | BN59: 1884575 | BO59: 1985761 | BP59: 1847158 | BQ59: 1983122 | BR59: 2179173
B60: 留存用户增长率 | C60: 0.0337 | D60: 0.0952 | E60: -0.1249 | F60: -0.0446 | G60: -0.033 | H60: -0.036 | I60: 0.0232 | J60: 0.0393 | K60: -0.1341 | L60: -0.0384 | M60: -0.1243 | N60: -0.1095 | O60: 0.1754 | P60: 0.1993 | Q60: -0.1384 | R60: 0.0249 | S60: 0.0119 | T60: -0.0109 | U60: 0.0461 | V60: -0.0019 | W60: -0.1713 | X60: -0.0907 | Y60: -0.1345 | Z60: -0.066 | AA60: 0.1074 | AB60: 0.1431 | AC60: -0.0168 | AD60: -0.0306 | AE60: 0.0416 | AF60: 0.0674 | AG60: 0.2692 | AH60: 0.1595 | AI60: -0.2441 | AJ60: -0.0766 | AK60: -0.1081 | AL60: -0.1791 | AM60: 0.0282 | AN60: 0.0771 | AO60: -0.1601 | AP60: -0.0284 | AQ60: 0.0018 | AR60: 0.1183 | AS60: 0.4265 | AT60: 0.071 | AU60: -0.3084 | AV60: -0.0916 | AW60: -0.084 | AX60: -0.1512 | AY60: -0.0301 | AZ60: 0.1082 | BA60: -0.0835 | BB60: 0.0232 | BC60: 0.0992 | BD60: 0.0721 | BE60: 0.1654 | BF60: 0.2001 | BG60: -0.2338 | BH60: -0.088 | BI60: -0.2161 | BJ60: -0.2156 | BK60: 0.0926 | BL60: 0.346 | BM60: -0.1381 | BN60: 0.013 | BO60: 0.0537 | BP60: -0.0698 | BQ60: 0.0736 | BR60: 0.0989
B61: 回流用户 | C61: 1645661 | D61: 994870 | E61: 829840 | F61: 1139469 | G61: 965800 | H61: 1121792 | I61: 1487529 | J61: 1047344 | K61: 841372 | L61: 1188091 | M61: 815866 | N61: 1214031 | O61: 2235361 | P61: 909857 | Q61: 1075777 | R61: 1350966 | S61: 943411 | T61: 1477293 | U61: 1331599 | V61: 1183347 | W61: 826183 | X61: 1232096 | Y61: 864681 | Z61: 1305885 | AA61: 1438738 | AB61: 1535254 | AC61: 1179324 | AD61: 1202648 | AE61: 1276668 | AF61: 1688491 | AG61: 1986508 | AH61: 1284247 | AI61: 1030245 | AJ61: 1402015 | AK61: 1098340 | AL61: 1029719 | AM61: 1740499 | AN61: 1030565 | AO61: 1109714 | AP61: 1009021 | AQ61: 1122629 | AR61: 1320409 | AS61: 1616529 | AT61: 1043758 | AU61: 793101 | AV61: 1214707 | AW61: 916421 | AX61: 885806 | AY61: 1131976 | AZ61: 1340075 | BA61: 813770 | BB61: 966100 | BC61: 1037881 | BD61: 1165848 | BE61: 1646689 | BF61: 1213356 | BG61: 921751 | BH61: 1165795 | BI61: 794383 | BJ61: 892474 | BK61: 1405324 | BL61: 1171752 | BM61: 770706 | BN61: 1110540 | BO61: 913128 | BP61: 1094582 | BQ61: 1378987 | BR61: 1094619
B62: 回流用户增长率 | C62: 0.7193 | D62: -0.3955 | E62: -0.1659 | F62: 0.3731 | G62: -0.1524 | H62: 0.1615 | I62: 0.326 | J62: -0.2959 | K62: -0.1967 | L62: 0.4121 | M62: -0.3133 | N62: 0.488 | O62: 0.8413 | P62: -0.593 | Q62: 0.1824 | R62: 0.2558 | S62: -0.3017 | T62: 0.5659 | U62: -0.0986 | V62: -0.1113 | W62: -0.3018 | X62: 0.4913 | Y62: -0.2982 | Z62: 0.5103 | AA62: 0.1017 | AB62: 0.0671 | AC62: -0.2318 | AD62: 0.0198 | AE62: 0.0615 | AF62: 0.3226 | AG62: 0.1765 | AH62: -0.3535 | AI62: -0.1978 | AJ62: 0.3609 | AK62: -0.2166 | AL62: -0.0625 | AM62: 0.6903 | AN62: -0.4079 | AO62: 0.0768 | AP62: -0.0907 | AQ62: 0.1126 | AR62: 0.1762 | AS62: 0.2243 | AT62: -0.3543 | AU62: -0.2401 | AV62: 0.5316 | AW62: -0.2456 | AX62: -0.0334 | AY62: 0.2779 | AZ62: 0.1838 | BA62: -0.3927 | BB62: 0.1872 | BC62: 0.0743 | BD62: 0.1233 | BE62: 0.4124 | BF62: -0.2632 | BG62: -0.2403 | BH62: 0.2648 | BI62: -0.3186 | BJ62: 0.1235 | BK62: 0.5746 | BL62: -0.1662 | BM62: -0.3423 | BN62: 0.4409 | BO62: -0.1778 | BP62: 0.1987 | BQ62: 0.2598 | BR62: -0.2062
A63: 用户占比 | B63: 新增活跃用户占比 | C63: 0.305 | D63: 0.259 | E63: 0.2128 | F63: 0.2227 | G63: 0.1978 | H63: 0.2027 | I63: 0.2659 | J63: 0.2943 | K63: 0.2502 | L63: 0.2435 | M63: 0.2024 | N63: 0.2442 | O63: 0.4348 | P63: 0.3664 | Q63: 0.3692 | R63: 0.4251 | S63: 0.3618 | T63: 0.3728 | U63: 0.4447 | V63: 0.4551 | W63: 0.3719 | X63: 0.3941 | Y63: 0.3567 | Z63: 0.3863 | AA63: 0.4094 | AB63: 0.4537 | AC63: 0.4153 | AD63: 0.3975 | AE63: 0.3842 | AF63: 0.4344 | AG63: 0.5026 | AH63: 0.443 | AI63: 0.3901 | AJ63: 0.4063 | AK63: 0.3792 | AL63: 0.3766 | AM63: 0.4524 | AN63: 0.4249 | AO63: 0.4301 | AP63: 0.4322 | AQ63: 0.4603 | AR63: 0.5484 | AS63: 0.5702 | AT63: 0.5224 | AU63: 0.4664 | AV63: 0.4906 | AW63: 0.4635 | AX63: 0.4492 | AY63: 0.4823 | AZ63: 0.5442 | BA63: 0.4991 | BB63: 0.4795 | BC63: 0.4688 | BD63: 0.4738 | BE63: 0.553 | BF63: 0.4938 | BG63: 0.4135 | BH63: 0.4138 | BI63: 0.3824 | BJ63: 0.3742 | BK63: 0.4725 | BL63: 0.5032 | BM63: 0.4475 | BN63: 0.4468 | BO63: 0.4179 | BP63: 0.4219 | BQ63: 0.497 | BR63: 0.4709
B64: 留存用户占比 | C64: 0.5409 | D64: 0.6403 | E64: 0.6846 | F64: 0.6395 | G64: 0.6748 | H64: 0.6495 | I64: 0.5669 | J64: 0.5882 | K64: 0.6326 | L64: 0.5947 | M64: 0.6573 | N64: 0.5571 | O64: 0.3626 | P64: 0.5326 | Q64: 0.5005 | R64: 0.4359 | S64: 0.5231 | T64: 0.4652 | U64: 0.4271 | V64: 0.43 | W64: 0.5127 | X64: 0.4425 | Y64: 0.4951 | Z64: 0.4135 | AA64: 0.3987 | AB64: 0.3769 | AC64: 0.4327 | AD64: 0.44 | AE64: 0.4473 | AF64: 0.3856 | AG64: 0.3473 | AH64: 0.4488 | AI64: 0.4856 | AJ64: 0.4311 | AK64: 0.4663 | AL64: 0.4523 | AM64: 0.3376 | AN64: 0.4286 | AO64: 0.3963 | AP64: 0.4027 | AQ64: 0.3708 | AR64: 0.3053 | AS64: 0.3046 | AT64: 0.3827 | AU64: 0.4194 | AV64: 0.3491 | AW64: 0.3893 | AX64: 0.3849 | AY64: 0.3303 | AZ64: 0.2838 | BA64: 0.3574 | BB64: 0.355 | BC64: 0.3649 | BD64: 0.3562 | BE64: 0.2832 | BF64: 0.3735 | BG64: 0.4337 | BH64: 0.3938 | BI64: 0.4336 | BJ64: 0.3892 | BK64: 0.2811 | BL64: 0.322 | BM64: 0.3906 | BN64: 0.3481 | BO64: 0.3988 | BP64: 0.363 | BQ64: 0.2967 | BR64: 0.3522
B65: 回流用户占比 | C65: 0.1541 | D65: 0.1007 | E65: 0.1026 | F65: 0.1378 | G65: 0.1274 | H65: 0.1478 | I65: 0.1672 | J65: 0.1175 | K65: 0.1172 | L65: 0.1618 | M65: 0.1403 | N65: 0.1987 | O65: 0.2026 | P65: 0.101 | Q65: 0.1302 | R65: 0.139 | S65: 0.1151 | T65: 0.162 | U65: 0.1282 | V65: 0.1149 | W65: 0.1154 | X65: 0.1634 | Y65: 0.1482 | Z65: 0.2002 | AA65: 0.192 | AB65: 0.1694 | AC65: 0.152 | AD65: 0.1626 | AE65: 0.1684 | AF65: 0.1799 | AG65: 0.1502 | AH65: 0.1082 | AI65: 0.1243 | AJ65: 0.1626 | AK65: 0.1545 | AL65: 0.1711 | AM65: 0.2099 | AN65: 0.1465 | AO65: 0.1737 | AP65: 0.1652 | AQ65: 0.1689 | AR65: 0.1463 | AS65: 0.1252 | AT65: 0.0949 | AU65: 0.1142 | AV65: 0.1603 | AW65: 0.1472 | AX65: 0.1658 | AY65: 0.1874 | AZ65: 0.1721 | BA65: 0.1436 | BB65: 0.1655 | BC65: 0.1662 | BD65: 0.17 | BE65: 0.1638 | BF65: 0.1327 | BG65: 0.1527 | BH65: 0.1923 | BI65: 0.1841 | BJ65: 0.2366 | BK65: 0.2464 | BL65: 0.1748 | BM65: 0.1618 | BN65: 0.2051 | BO65: 0.1834 | BP65: 0.2151 | BQ65: 0.2063 | BR65: 0.1769
A66: 流失用户 | B66: 流失用户 | C66: 2589142 | D66: 4352379 | E66: 4343625 | F66: 2797890 | G66: 3156067 | H66: 2649591 | I66: 2546636 | J66: 3655693 | K66: 4373888 | L66: 2811106 | M66: 3518272 | N66: 2411788 | O66: 2109488 | P66: 6235088 | Q66: 4876105 | R66: 4022944 | S66: 5433285 | T66: 3956089 | U66: 4680637 | V66: 5959216 | W66: 6629315 | X66: 3820984 | Y66: 4652636 | Z66: 3135810 | AA66: 3536234 | AB66: 4078973 | AC66: 5703446 | AD66: 4504695 | AE66: 4007388 | AF66: 3960264 | AG66: 4790888 | AH66: 7901014 | AI66: 7840381 | AJ66: 4573406 | AK66: 5307253 | AL66: 4388305 | AM66: 3219488 | AN66: 5275297 | AO66: 4501807 | AP66: 3929679 | AQ66: 3644979 | AR66: 3890380 | AS66: 5094346 | AT66: 8697979 | AU66: 8090517 | AV66: 4297982 | AW66: 5154121 | AX66: 4167975 | AY66: 3347835 | AZ66: 3829275 | BA66: 5762800 | BB66: 3595697 | BC66: 3560483 | BD66: 3800739 | BE66: 4010820 | BF66: 6636893 | BG66: 6528344 | BH66: 3647536 | BI66: 4189940 | BJ66: 2848074 | BK66: 2167804 | BL66: 3545556 | BM66: 4842691 | BN66: 2877673 | BO66: 3428407 | BP66: 3132558 | BQ66: 3105874 | BR66: 4505333
B67: 流失用户增长率 | C67: -0.2377 | D67: 0.681 | E67: -0.002 | F67: -0.3559 | G67: 0.128 | H67: -0.1605 | I67: -0.0389 | J67: 0.4355 | K67: 0.1965 | L67: -0.3573 | M67: 0.2516 | N67: -0.3145 | O67: -0.1253 | P67: 1.9557 | Q67: -0.218 | R67: -0.175 | S67: 0.3506 | T67: -0.2719 | U67: 0.1831 | V67: 0.2732 | W67: 0.1124 | X67: -0.4236 | Y67: 0.2177 | Z67: -0.326 | AA67: 0.1277 | AB67: 0.1535 | AC67: 0.3983 | AD67: -0.2102 | AE67: -0.1104 | AF67: -0.0118 | AG67: 0.2097 | AH67: 0.6492 | AI67: -0.0077 | AJ67: -0.4167 | AK67: 0.1605 | AL67: -0.1731 | AM67: -0.2663 | AN67: 0.6386 | AO67: -0.1466 | AP67: -0.1271 | AQ67: -0.0724 | AR67: 0.0673 | AS67: 0.3095 | AT67: 0.7074 | AU67: -0.0698 | AV67: -0.4688 | AW67: 0.1992 | AX67: -0.1913 | AY67: -0.1968 | AZ67: 0.1438 | BA67: 0.5049 | BB67: -0.3761 | BC67: -0.0098 | BD67: 0.0675 | BE67: 0.0553 | BF67: 0.6547 | BG67: -0.0164 | BH67: -0.4413 | BI67: 0.1487 | BJ67: -0.3203 | BK67: -0.2389 | BL67: 0.6356 | BM67: 0.3658 | BN67: -0.4058 | BO67: 0.1914 | BP67: -0.0863 | BQ67: -0.0085 | BR67: 0.4506
B68: 上月新增活跃用户本月流失数 | C68: 0 | D68: 0 | E68: 0 | F68: 0 | G68: 0 | H68: 0 | I68: 0 | J68: 0 | K68: 0 | L68: 0 | M68: 0 | N68: 0 | O68: 0 | P68: 0 | Q68: 0 | R68: 0 | S68: 0 | T68: 0 | U68: 0 | V68: 0 | W68: 0 | X68: 0 | Y68: 0 | Z68: 0 | AA68: 0 | AB68: 0 | AC68: 0 | AD68: 0 | AE68: 0 | AF68: 0 | AG68: 0 | AH68: 0 | AI68: 0 | AJ68: 0 | AK68: 0 | AL68: 0 | AM68: 1672269 | AN68: 2941838 | AO68: 2421893 | AP68: 2142407 | AQ68: 2031787 | AR68: 2249965 | AS68: 3308755 | AT68: 5672783 | AU68: 4794316 | AV68: 2467230 | AW68: 2984850 | AX68: 2310670 | AY68: 1888105 | AZ68: 2306148 | BA68: 3605657 | BB68: 2121172 | BC68: 2058622 | BD68: 2154218 | BE68: 2362083 | BF68: 4234300 | BG68: 3753140 | BH68: 1919784 | BI68: 2090720 | BJ68: 1351272 | BK68: 1037443 | BL68: 1883026 | BM68: 2661085 | BN68: 1502423 | BO68: 1755474 | BP68: 1564219 | BQ68: 1601791 | BR68: 2599230
B69: 上月留存用户本月流失数 | C69: 0 | D69: 0 | E69: 0 | F69: 0 | G69: 0 | H69: 0 | I69: 0 | J69: 0 | K69: 0 | L69: 0 | M69: 0 | N69: 0 | O69: 0 | P69: 0 | Q69: 0 | R69: 0 | S69: 0 | T69: 0 | U69: 0 | V69: 0 | W69: 0 | X69: 0 | Y69: 0 | Z69: 0 | AA69: 0 | AB69: 0 | AC69: 0 | AD69: 0 | AE69: 0 | AF69: 0 | AG69: 0 | AH69: 0 | AI69: 0 | AJ69: 0 | AK69: 0 | AL69: 0 | AM69: 945927 | AN69: 1195879 | AO69: 1350049 | AP69: 1060090 | AQ69: 972916 | AR69: 977587 | AS69: 1070092 | AT69: 1967192 | AU69: 2488294 | AV69: 1323396 | AW69: 1329872 | AX69: 1219440 | AY69: 895710 | AZ69: 841789 | BA69: 1156568 | BB69: 2658515 | BC69: 884857 | BD69: 982831 | BE69: 962155 | BF69: 1350603 | BG69: 1916917 | BH69: 1155253 | BI69: 1241154 | BJ69: 910742 | BK69: 568943 | BL69: 725352 | BM69: 1245389 | BN69: 840847 | BO69: 913051 | BP69: 949304 | BQ69: 805485 | BR69: 952217
B70: 上月回流用户本月流失数 | C70: 0 | D70: 0 | E70: 0 | F70: 0 | G70: 0 | H70: 0 | I70: 0 | J70: 0 | K70: 0 | L70: 0 | M70: 0 | N70: 0 | O70: 0 | P70: 0 | Q70: 0 | R70: 0 | S70: 0 | T70: 0 | U70: 0 | V70: 0 | W70: 0 | X70: 0 | Y70: 0 | Z70: 0 | AA70: 0 | AB70: 0 | AC70: 0 | AD70: 0 | AE70: 0 | AF70: 0 | AG70: 0 | AH70: 0 | AI70: 0 | AJ70: 0 | AK70: 0 | AL70: 0 | AM70: 601292 | AN70: 1137580 | AO70: 729865 | AP70: 727182 | AQ70: 640276 | AR70: 662828 | AS70: 715559 | AT70: 1058004 | AU70: 807907 | AV70: 507356 | AW70: 839399 | AX70: 637878 | AY70: 563878 | AZ70: 681338 | BA70: 1000575 | BB70: 537343 | BC70: 617004 | BD70: 663690 | BE70: 686582 | BF70: 1051990 | BG70: 858287 | BH70: 572499 | BI70: 858066 | BJ70: 586060 | BK70: 561418 | BL70: 937178 | BM70: 936217 | BN70: 534403 | BO70: 759882 | BP70: 619035 | BQ70: 698598 | BR70: 953886
A71: 流失率 | B71: 流失率 | C71: 0.3095 | D71: 0.4076 | E71: 0.4396 | F71: 0.346 | G71: 0.3816 | H71: 0.3495 | I71: 0.3355 | J71: 0.4108 | K71: 0.4907 | L71: 0.3917 | M71: 0.4792 | N71: 0.4147 | O71: 0.3452 | P71: 0.5651 | Q71: 0.5411 | R71: 0.487 | S71: 0.5589 | T71: 0.4826 | U71: 0.5134 | V71: 0.5737 | W71: 0.6437 | X71: 0.5338 | Y71: 0.617 | Z71: 0.5376 | AA71: 0.5421 | AB71: 0.5443 | AC71: 0.6294 | AD71: 0.5805 | AE71: 0.5417 | AF71: 0.5225 | AG71: 0.5105 | AH71: 0.5973 | AI71: 0.6607 | AJ71: 0.5516 | AK71: 0.6155 | AL71: 0.6172 | AM71: 0.5349 | AN71: 0.6363 | AO71: 0.64 | AP71: 0.615 | AQ71: 0.5966 | AR71: 0.5853 | AS71: 0.5644 | AT71: 0.6738 | AU71: 0.7353 | AV71: 0.619 | AW71: 0.6802 | AX71: 0.6696 | AY71: 0.6266 | AZ71: 0.634 | BA71: 0.7399 | BB71: 0.6343 | BC71: 0.6098 | BD71: 0.6088 | BE71: 0.5849 | BF71: 0.6602 | BG71: 0.7138 | BH71: 0.6044 | BI71: 0.6913 | BJ71: 0.6599 | BK71: 0.5748 | BL71: 0.6216 | BM71: 0.7225 | BN71: 0.6043 | BO71: 0.6332 | BP71: 0.6291 | BQ71: 0.6103 | BR71: 0.674
B72: 上月新增活跃用户本月流失率 | C72: 0 | D72: 0 | E72: 0 | F72: 0 | G72: 0 | H72: 0 | I72: 0 | J72: 0 | K72: 0 | L72: 0 | M72: 0 | N72: 0 | O72: 0 | P72: 0 | Q72: 0 | R72: 0 | S72: 0 | T72: 0 | U72: 0 | V72: 0 | W72: 0 | X72: 0 | Y72: 0 | Z72: 0 | AA72: 0 | AB72: 0 | AC72: 0 | AD72: 0 | AE72: 0 | AF72: 0 | AG72: 0 | AH72: 0 | AI72: 0 | AJ72: 0 | AK72: 0 | AL72: 0 | AM72: 0.7378 | AN72: 0.7844 | AO72: 0.8104 | AP72: 0.7796 | AQ72: 0.7695 | AR72: 0.7355 | AS72: 0.6685 | AT72: 0.7707 | AU72: 0.8341 | AV72: 0.7619 | AW72: 0.803 | AX72: 0.8009 | AY72: 0.7867 | AZ72: 0.7917 | BA72: 0.8507 | BB72: 0.7498 | BC72: 0.7352 | BD72: 0.736 | BE72: 0.727 | BF72: 0.7616 | BG72: 0.8311 | BH72: 0.7693 | BI72: 0.8335 | BJ72: 0.8189 | BK72: 0.7351 | BL72: 0.6987 | BM72: 0.789 | BN72: 0.705 | BO72: 0.7257 | BP72: 0.7517 | BQ72: 0.746 | BR72: 0.7823
B73: 上月留存用户本月流失率 | C73: 0 | D73: 0 | E73: 0 | F73: 0 | G73: 0 | H73: 0 | I73: 0 | J73: 0 | K73: 0 | L73: 0 | M73: 0 | N73: 0 | O73: 0 | P73: 0 | Q73: 0 | R73: 0 | S73: 0 | T73: 0 | U73: 0 | V73: 0 | W73: 0 | X73: 0 | Y73: 0 | Z73: 0 | AA73: 0 | AB73: 0 | AC73: 0 | AD73: 0 | AE73: 0 | AF73: 0 | AG73: 0 | AH73: 0 | AI73: 0 | AJ73: 0 | AK73: 0 | AL73: 0 | AM73: 0.3475 | AN73: 0.4273 | AO73: 0.4478 | AP73: 0.4187 | AQ73: 0.3955 | AR73: 0.3967 | AS73: 0.3883 | AT73: 0.5004 | AU73: 0.591 | AV73: 0.4545 | AW73: 0.5028 | AX73: 0.5033 | AY73: 0.4355 | AZ73: 0.422 | BA73: 0.5232 | BB73: 0.4626 | BC73: 0.4269 | BD73: 0.4313 | BE73: 0.3939 | BF73: 0.4744 | BG73: 0.5611 | BH73: 0.4414 | BI73: 0.5199 | BJ73: 0.4867 | BK73: 0.3877 | BL73: 0.4523 | BM73: 0.577 | BN73: 0.452 | BO73: 0.4845 | BP73: 0.4781 | BQ73: 0.4361 | BR73: 0.4802
B74: 上月回流用户本月流失率 | C74: 0 | D74: 0 | E74: 0 | F74: 0 | G74: 0 | H74: 0 | I74: 0 | J74: 0 | K74: 0 | L74: 0 | M74: 0 | N74: 0 | O74: 0 | P74: 0 | Q74: 0 | R74: 0 | S74: 0 | T74: 0 | U74: 0 | V74: 0 | W74: 0 | X74: 0 | Y74: 0 | Z74: 0 | AA74: 0 | AB74: 0 | AC74: 0 | AD74: 0 | AE74: 0 | AF74: 0 | AG74: 0 | AH74: 0 | AI74: 0 | AJ74: 0 | AK74: 0 | AL74: 0 | AM74: 0.5839 | AN74: 0.6536 | AO74: 0.7082 | AP74: 0.6553 | AQ74: 0.6346 | AR74: 0.5904 | AS74: 0.5419 | AT74: 0.6545 | AU74: 0.774 | AV74: 0.6397 | AW74: 0.691 | AX74: 0.6961 | AY74: 0.6366 | AZ74: 0.6019 | BA74: 0.7467 | BB74: 0.6603 | BC74: 0.6387 | BD74: 0.6395 | BE74: 0.5889 | BF74: 0.6389 | BG74: 0.7074 | BH74: 0.6211 | BI74: 0.736 | BJ74: 0.7378 | BK74: 0.6291 | BL74: 0.6669 | BM74: 0.799 | BN74: 0.6934 | BO74: 0.6842 | BP74: 0.6779 | BQ74: 0.6382 | BR74: 0.6917
A75: 在线情况 | B75: PCU | C75: 0 | D75: 0 | E75: 0 | F75: 0 | G75: 0 | H75: 0 | I75: 0 | J75: 0 | K75: 0 | L75: 0 | M75: 0 | N75: 0 | O75: 0 | P75: 0 | Q75: 0 | R75: 0 | S75: 0 | T75: 0 | U75: 0 | V75: 0 | W75: 0 | X75: 0 | Y75: 0 | Z75: 0 | AA75: 0 | AB75: 0 | AC75: 0 | AD75: 0 | AE75: 0 | AF75: 0 | AG75: 0 | AH75: 0 | AI75: 0 | AJ75: 0 | AK75: 0 | AL75: 0 | AM75: 0 | AN75: 0 | AO75: 0 | AP75: 0 | AQ75: 133988 | AR75: 173376 | AS75: 188822 | AT75: 134506 | AU75: 112962 | AV75: 97193 | AW75: 102063 | AX75: 122951 | AY75: 116436 | AZ75: 85855 | BA75: 88343 | BB75: 93167 | BC75: 125945 | BD75: 93689 | BE75: 123808 | BF75: 114028 | BG75: 85375 | BH75: 90713 | BI75: 62906 | BJ75: 57808 | BK75: 71295 | BL75: 79777 | BM75: 65342 | BN75: 64737 | BO75: 64246 | BP75: 80447 | BQ75: 53887 | BR75: 105675
B76: PCU增长率 | C76: 0 | D76: 0 | E76: 0 | F76: 0 | G76: 0 | H76: 0 | I76: 0 | J76: 0 | K76: 0 | L76: 0 | M76: 0 | N76: 0 | O76: 0 | P76: 0 | Q76: 0 | R76: 0 | S76: 0 | T76: 0 | U76: 0 | V76: 0 | W76: 0 | X76: 0 | Y76: 0 | Z76: 0 | AA76: 0 | AB76: 0 | AC76: 0 | AD76: 0 | AE76: 0 | AF76: 0 | AG76: 0 | AH76: 0 | AI76: 0 | AJ76: 0 | AK76: 0 | AL76: 0 | AM76: 0 | AN76: 0 | AO76: 0 | AP76: 0 | AQ76: 0 | AR76: 0.294 | AS76: 0.0891 | AT76: -0.2877 | AU76: -0.1602 | AV76: -0.1396 | AW76: 0.0501 | AX76: 0.2047 | AY76: -0.053 | AZ76: -0.2626 | BA76: 0.029 | BB76: 0.0546 | BC76: 0.3518 | BD76: -0.2561 | BE76: 0.3215 | BF76: -0.079 | BG76: -0.2513 | BH76: 0.0625 | BI76: -0.3065 | BJ76: -0.081 | BK76: 0.2333 | BL76: 0.119 | BM76: -0.1809 | BN76: -0.0093 | BO76: -0.0076 | BP76: 0.2522 | BQ76: -0.3302 | BR76: 0.961
B77: ACU | C77: 0 | D77: 0 | E77: 0 | F77: 0 | G77: 0 | H77: 0 | I77: 0 | J77: 0 | K77: 0 | L77: 0 | M77: 0 | N77: 0 | O77: 0 | P77: 0 | Q77: 0 | R77: 0 | S77: 0 | T77: 0 | U77: 0 | V77: 0 | W77: 0 | X77: 0 | Y77: 0 | Z77: 0 | AA77: 0 | AB77: 0 | AC77: 0 | AD77: 0 | AE77: 0 | AF77: 0 | AG77: 0 | AH77: 0 | AI77: 0 | AJ77: 0 | AK77: 0 | AL77: 0 | AM77: 0 | AN77: 0 | AO77: 0 | AP77: 0 | AQ77: 11503.97 | AR77: 55786.64 | AS77: 102017.72 | AT77: 69518.51 | AU77: 30264.08 | AV77: 30795.73 | AW77: 28010.38 | AX77: 25318.94 | AY77: 29700.22 | AZ77: 42403.08 | BA77: 26965.23 | BB77: 29499.53 | BC77: 31803.33 | BD77: 32579.11 | BE77: 53449.77 | BF77: 53899.22 | BG77: 25193.54 | BH77: 25014.87 | BI77: 16125.38 | BJ77: 13630.04 | BK77: 26521.14 | BL77: 34797.9 | BM77: 20251.67 | BN77: 22503.14 | BO77: 19528.55 | BP77: 24157.85 | BQ77: 29376.4 | BR77: 34274.51
B78: ACU增长率 | C78: 0 | D78: 0 | E78: 0 | F78: 0 | G78: 0 | H78: 0 | I78: 0 | J78: 0 | K78: 0 | L78: 0 | M78: 0 | N78: 0 | O78: 0 | P78: 0 | Q78: 0 | R78: 0 | S78: 0 | T78: 0 | U78: 0 | V78: 0 | W78: 0 | X78: 0 | Y78: 0 | Z78: 0 | AA78: 0 | AB78: 0 | AC78: 0 | AD78: 0 | AE78: 0 | AF78: 0 | AG78: 0 | AH78: 0 | AI78: 0 | AJ78: 0 | AK78: 0 | AL78: 0 | AM78: 0 | AN78: 0 | AO78: 0 | AP78: 0 | AQ78: 0 | AR78: 3.8493 | AS78: 0.8287 | AT78: -0.3186 | AU78: -0.5647 | AV78: 0.0176 | AW78: -0.0904 | AX78: -0.0961 | AY78: 0.173 | AZ78: 0.4277 | BA78: -0.3641 | BB78: 0.094 | BC78: 0.0781 | BD78: 0.0244 | BE78: 0.6406 | BF78: 0.0084 | BG78: -0.5326 | BH78: -0.0071 | BI78: -0.3554 | BJ78: -0.1547 | BK78: 0.9458 | BL78: 0.3121 | BM78: -0.418 | BN78: 0.1112 | BO78: -0.1322 | BP78: 0.2371 | BQ78: 0.216 | BR78: 0.1667
A79: 在线时长 | B79: 活跃用户日平均在线时长 | C79: 0 | D79: 0 | E79: 0 | F79: 0 | G79: 0 | H79: 0 | I79: 0 | J79: 0 | K79: 0 | L79: 0 | M79: 0 | N79: 0 | O79: 0 | P79: 0 | Q79: 0 | R79: 0 | S79: 0 | T79: 0 | U79: 0 | V79: 0 | W79: 0 | X79: 0 | Y79: 0 | Z79: 0 | AA79: 0 | AB79: 0 | AC79: 0 | AD79: 0 | AE79: 0 | AF79: 0 | AG79: 0 | AH79: 0 | AI79: 0 | AJ79: 0 | AK79: 0 | AL79: 0 | AM79: 0 | AN79: 0 | AO79: 0 | AP79: 0 | AQ79: 2030.13 | AR79: 3398.64 | AS79: 3805.08 | AT79: 3463.34 | AU79: 2843.55 | AV79: 2823.16 | AW79: 2956.74 | AX79: 3079.9 | AY79: 3262.78 | AZ79: 3319.76 | BA79: 3091.87 | BB79: 2854.38 | BC79: 2937.68 | BD79: 2812.41 | BE79: 3134.37 | BF79: 3158.75 | BG79: 2565.25 | BH79: 2619.31 | BI79: 2520.09 | BJ79: 2490.86 | BK79: 2796.31 | BL79: 2966.04 | BM79: 2537.91 | BN79: 2574.77 | BO79: 2419.76 | BP79: 2809.89 | BQ79: 2768.43 | BR79: 3373.26
B80: 付费用户日平均在线时长 | C80: 0 | D80: 0 | E80: 0 | F80: 0 | G80: 0 | H80: 0 | I80: 0 | J80: 0 | K80: 0 | L80: 0 | M80: 0 | N80: 0 | O80: 0 | P80: 0 | Q80: 0 | R80: 0 | S80: 0 | T80: 0 | U80: 0 | V80: 0 | W80: 0 | X80: 0 | Y80: 0 | Z80: 0 | AA80: 0 | AB80: 0 | AC80: 0 | AD80: 0 | AE80: 0 | AF80: 0 | AG80: 0 | AH80: 0 | AI80: 0 | AJ80: 0 | AK80: 0 | AL80: 0 | AM80: 0 | AN80: 0 | AO80: 0 | AP80: 0 | AQ80: 3166.45 | AR80: 5506.34 | AS80: 6428.15 | AT80: 6636.52 | AU80: 5097.2 | AV80: 5223.44 | AW80: 5271.93 | AX80: 5276 | AY80: 5922.69 | AZ80: 6771.09 | BA80: 5340.23 | BB80: 4980.61 | BC80: 5191.58 | BD80: 5280.3 | BE80: 6275.02 | BF80: 6709.49 | BG80: 5329.6 | BH80: 5576.75 | BI80: 5539.35 | BJ80: 5002.51 | BK80: 5904.27 | BL80: 7052.46 | BM80: 5163.4 | BN80: 5674.51 | BO80: 5266.53 | BP80: 5906.04 | BQ80: 6750.74 | BR80: 8032.42
B81: 新增用户日平均在线时长 | C81: 0 | D81: 0 | E81: 0 | F81: 0 | G81: 0 | H81: 0 | I81: 0 | J81: 0 | K81: 0 | L81: 0 | M81: 0 | N81: 0 | O81: 0 | P81: 0 | Q81: 0 | R81: 0 | S81: 0 | T81: 0 | U81: 0 | V81: 0 | W81: 0 | X81: 0 | Y81: 0 | Z81: 0 | AA81: 0 | AB81: 0 | AC81: 0 | AD81: 0 | AE81: 0 | AF81: 0 | AG81: 0 | AH81: 0 | AI81: 0 | AJ81: 0 | AK81: 0 | AL81: 0 | AM81: 0 | AN81: 0 | AO81: 0 | AP81: 0 | AQ81: 1998.21 | AR81: 3307.4 | AS81: 3627.17 | AT81: 3247.54 | AU81: 2751.6 | AV81: 2678.17 | AW81: 2797.03 | AX81: 2793.09 | AY81: 2949.84 | AZ81: 3032.62 | BA81: 2899.52 | BB81: 2838.27 | BC81: 2865.91 | BD81: 2577.59 | BE81: 2800.56 | BF81: 2716.5 | BG81: 2207.97 | BH81: 2206.12 | BI81: 2088.41 | BJ81: 2226.8 | BK81: 2716.29 | BL81: 2722.46 | BM81: 2449.46 | BN81: 2424.63 | BO81: 2354.94 | BP81: 2456.68 | BQ81: 2568.96 | BR81: 2810.8
B82: 留存用户日平均在线时长 | C82: 0 | D82: 0 | E82: 0 | F82: 0 | G82: 0 | H82: 0 | I82: 0 | J82: 0 | K82: 0 | L82: 0 | M82: 0 | N82: 0 | O82: 0 | P82: 0 | Q82: 0 | R82: 0 | S82: 0 | T82: 0 | U82: 0 | V82: 0 | W82: 0 | X82: 0 | Y82: 0 | Z82: 0 | AA82: 0 | AB82: 0 | AC82: 0 | AD82: 0 | AE82: 0 | AF82: 0 | AG82: 0 | AH82: 0 | AI82: 0 | AJ82: 0 | AK82: 0 | AL82: 0 | AM82: 0 | AN82: 0 | AO82: 0 | AP82: 0 | AQ82: 2041.82 | AR82: 3582.84 | AS82: 4001.65 | AT82: 3645.52 | AU82: 2964.32 | AV82: 3047.94 | AW82: 3165.68 | AX82: 3357.61 | AY82: 3625.83 | AZ82: 3718.41 | BA82: 3359.75 | BB82: 2974.39 | BC82: 3092.35 | BD82: 3041.78 | BE82: 3515.78 | BF82: 3479.69 | BG82: 2792.99 | BH82: 2920.68 | BI82: 2798.17 | BJ82: 2756.76 | BK82: 3090.49 | BL82: 3338.09 | BM82: 2698.29 | BN82: 2833.3 | BO82: 2565.42 | BP82: 3116.02 | BQ82: 3113.8 | BR82: 3891.78
